Workbook
Name _sc38: #REF!
Name Excel_BuiltIn__FilterDatabase_4: #REF!
Name __NF4: #REF!
Name mbw: #REF!
Name ____________________b111121: #REF!
Name CABLE_1_6_7: #REF!
Name Staircase: #REF!
Name CABLE_1_12: #REF!
Name __MC4: #REF!
Name ClientPhone: #REF!
Name _MC4: #REF!
Name DFG: #REF!
Name current3: #REF!
Name Overall_Summary_Title: #REF!
Name Field63: #REF!
Name _______________________Ki1: #REF!
Name ProjAddress1: #REF!
Name Excel_BuiltIn_Print_Area_3_1_1: #REF!
Name Engineering_total: #REF!
Name SP1Number: #REF!
Name Excel_BuiltIn_Print_Area_48: #REF!
Name Material: #REF!
Name ContWithAcct: #REF!
Name mmmmmmmmmm: #REF!
Name kb: #REF!
Name _a_1_6_7: #REF!
Name aeron: #REF!
Name ciff: #REF!
Name _900: #REF!
Name Full_Print: #REF!
Name Princ: #REF!
Name u: #REF!
Name A8____0: #REF!
Name Excel_BuiltIn_Print_Area_5_4: #REF!
Name ProdPct1: #REF!
Name _______________________TB2: #REF!
Name si: #REF!
Name I___13: #REF!
Name Q행: #REF!
Name CompRange1Main: #REF!
Name kc: #REF!
Name ______TB2: #REF!
Name _SDB5.: #REF!
Name Excel_BuiltIn_Print_Area_1_1_1_1: #REF!
Name ValveConn: #REF!
Name K_Genehmigung: #REF!
Name UFPrn20070606150313: #REF!
Name Lr: #REF!
Name _30cd__Vertical_strobe_light__wall_mounted: #REF!
Name Field319: #REF!
Name ww: #REF!
Name zlpu___0: #REF!
Name _sc36: #REF!
Name fff: #REF!
Name _Ki2: #REF!
Name Client_Equipment_Total: #REF!
Name Excel_BuiltIn_Print_Area_3_1_1_1: #REF!
Name WES: #REF!
Name Field288: #REF!
Name ___________________TB2: #REF!

Sheet General Notes
A2: PREAMBLE FOR CIVIL & INTERIOR WORKS
B4: GENERAL NOTES COVERING BILL OF QUANTITIES
B6: General Applicability
B7: These notes shall apply to all Bills of Quantities forming part of this document.
B8: The Works under this Bill shall be priced based on re-measurable quantities unless otherwise mentioned.
B9: This Bill shall be read in conjunction with the Drawings, Specifications of Materials and Workmanship, General Conditions of Contract, and all other associated Bills of Quantities. All these documents shall be construed as being complementary to one another, and any requirement shown on one shall be binding as though it appeared on all.
B10: The Contractor shall provide and execute everything reasonably necessary for the proper completion of the Works according to the true intent and meaning of the Drawings, Specifications, and Contract Documents, whether or not the same is specifically mentioned, provided that it can be reasonably inferred therefrom.
B11: In the event of any discrepancy between the Drawings, Specifications, or any other Contract Documents, the same shall be immediately brought to the notice of the Employer’s Representative / Consultant, whose decision shall be final and binding.
B12: Tenderers shall carefully examine all drawings, specifications, site conditions, and existing services before submitting their bid, and shall satisfy themselves as to the nature and scope of the works to be carried out. No claim shall be entertained on account of lack of knowledge of site conditions.
B13: Unit rates shall be inclusive of all mock-ups, samples, protection, cleaning, rectification, and housekeeping till handover.
B14: Quoted rate shall include all charges towards transportation, lead, lift, mathadi charges , Octroi, installation, levies, royalties, WCP & CAR insurance & other applicable insurances, ESI & PF premiums, overheards, fees and rectification of defects or replacement of defective material.
B16: Scope of Work and Pricing Requirements
B17: The rates and prices quoted shall be deemed to include the entire scope of work as defined in the Drawings, Specifications, and BOQ.
... B146: MS – Mild Steel

Sheet FINAL SUMMARY
A1: Project: KOHLER_PUNE
A2: Commercial Proposal by: FLIPSPACES TECHNOLOGY LABS PRIVATE LIMITED
A4: BILL OF QUANTITIES
B5: PROJECT AREA (SFT) - Approx | C5: 14905
A6: S.No. | B6: Cost Heads | C6: AMOUNT (INR) | D6: Rate Per Sft
A8: A | B8: ARCHITECTURAL WORKS : CIVIL AND INTERIORS | C8: =SUM(C9:C17) -> 31707619 | D8: =SUM(D9:D17) -> 2127.3143
A9: A1 | B9: CIVIL WORKS | C9: ='Civil Works'!H51 -> 3917558.5 | D9: =C9/$C$5 -> 262.83519
A10: A2 | B10: INTERIOR WORKS | C10: ='Interior Works'!I274 -> 20810221 | D10: =C10/$C$5 -> 1396.1906
A11: A3 | B11: MODULAR GLASS PARTITIONS AND DOORS | C11: ='Modular Glass Partition & Doors'!H37 -> 2074408 | D11: =C11/$C$5 -> 139.17531
A12: A4 | B12: SIGNAGES | C12: =Signages!H24 -> 433192 | D12: =C12/$C$5 -> 29.063536
A13: A5 | B13: GRAPHICS AND FILMS | C13: ='Graphics and Films'!H19 -> 313695 | D13: =C13/$C$5 -> 21.046293
A14: A6 | B14: BLINDS | C14: =Blinds!H10 -> 906562.95 | D14: =C14/$C$5 -> 60.822741
A15: A7 | B15: PLANTERS | C15: =Planters!G19 -> 426099 | D15: =C15/$C$5 -> 28.587655
A16: A8 | B16: TOILET WORKS | C16: ='TOILET WORKS'!H188 -> 2825883 | D16: =C16/$C$5 -> 189.59296
A18: B | B18: FURNITURE AND FURNISHING | C18: =SUM(C19:C22) -> 4937260.8 | D18: =SUM(D19:D22) -> 331.24863
A19: B1 | B19: CARPET FLOORING | C19: ='Carpet Flooring'!H8 -> 1326820.8 | D19: =C19/$C$5 -> 89.018502
A20: B2 | B20: MODULAR FURNITURE | C20: ='Modular Furniture'!H43 -> 1394656 | D20: =C20/$C$5 -> 93.569675
A21: B3 | B21: LOOSE FURNITURE & CHAIRS | C21: ='Loose Furniture & Chairs'!H36 -> 2215784 | D21: =C21/$C$5 -> 148.66045
A23: C | B23: ELECTRICAL WORKS | C23: =SUM(C24:C26) -> 8768969 | D23: =SUM(D24:D26) -> 588.32399
A24: C1 | B24: ELECTRICAL WORKS | C24: ='Electrical Works'!I710 -> 6382430 | D24: =C24/$C$5 -> 428.20731
A25: C2 | B25: LIGHT FIXTURES | C25: ='Light Fixtures'!I29 -> 2386539 | D25: =C25/$C$5 -> 160.11667
A27: D | B27: HVAC | C27: =SUM(C28:C29) -> 7528130.5 | D27: =SUM(D28:D29) -> 505.07417
A28: D1 | B28: HVAC | C28: =HVAC!H265+HVAC!F265 -> 7528130.5 | D28: =C28/$C$5 -> 505.07417
A30: E | B30: DATA NETWORK | C30: =C31 -> 1931970 | D30: =D31 -> 129.61892
A31: E1 | B31: PASSIVE NETWORKING | C31: ='Passive Networking'!G54 -> 1931970 | D31: =C31/$C$5 -> 129.61892
A33: F | B33: PHE WORKS | C33: =SUM(C34) -> 160300 | D33: =SUM(D34) -> 10.75478
A34: F1 | B34: PLUMBING WORKS | C34: =PHE!J100 -> 160300 | D34: =C34/$C$5 -> 10.75478
A36: G | B36: FLSS WORKS | C36: 400000 | D36: =C36/C5 -> 26.836632 | E36: refurbishment of existing fire services with minimum modification.
A37: G1 | B37: FIRE SPRINKLERS | D37: =C37/$C$5 -> 0
A38: G2 | B38: FIRE DETECTION SYSTEM | D38: =C38/$C$5 -> 0
A39: G3 | B39: PUBLIC ADDRESS SYSTEM | D39: =C39/$C$5 -> 0
A40: G4 | B40: FIRE EXTINGUISHERS | D40: =C40/$C$5 -> 0
A42: H | B42: OTHER ITEMS | C42: =SUM(C43,C44) -> 1569750 | D42: =SUM(D43,D44) -> 105.31701
A43: H1 | B43: DISHWASH AREA | C43: ='Dishwash Area'!H42 -> 666540 | D43: =C43/$C$5 -> 44.719222
A44: H2 | B44: KITCHEN EQUIPMENTS & OTHERS | C44: ='Kitchen Equipments'!I21 -> 903210 | D44: =C44/$C$5 -> 60.597786
A46: I | B46: AV WORKS | D46: =SUM(D47) -> 0 | E46: Excluded from scope
A47: I1 | B47: AV WORKS | D47: =C47/$C$5 -> 0 | E47: Excluded from scope
B49: TOTAL (EXCLUSIVE OF TAXES) | C49: =sum(C33,C36,C30,C27,C23,C18,C8,C42) -> 57004000 | D49: =sum(D33,D36,D30,D27,D23,D18,D8,D42) -> 3824.4884
B51: GRAND TOTAL (EXCLUSIVE OF TAXES) | C51: =C49 -> 57004000 | D51: =C51/C5 -> 3824.4884
B52: GST @ 18% | C52: =C51*18% -> 10260720
B53: GRAND TOTAL (WITH TAXES) | C53: =SUM(C51:C52) -> 67264720

Sheet Copy of FINAL SUMMARY
A1: Project: KOHLER_PUNE
A2: Commercial Proposal by: FLIPSPACES TECHNOLOGY LABS PRIVATE LIMITED
A4: BILL OF QUANTITIES
B5: PROJECT AREA (SFT) - Approx | C5: 14905
A6: S.No. | B6: Cost Heads | C6: AMOUNT (INR) | D6: Rate Per Sft
A8: A | B8: ARCHITECTURAL WORKS : CIVIL AND INTERIORS | C8: 31707620 | D8: =SUM(D9:D17) -> 2127.3143
A9: A1 | B9: CIVIL WORKS | C9: 3917559 | D9: =C9/$C$5 -> 262.83522
A10: A2 | B10: INTERIOR WORKS | C10: 20810221 | D10: =C10/$C$5 -> 1396.1906
A11: A3 | B11: MODULAR GLASS PARTITIONS AND DOORS | C11: 2074408 | D11: =C11/$C$5 -> 139.17531
A12: A4 | B12: SIGNAGES | C12: 433192 | D12: =C12/$C$5 -> 29.063536
A13: A5 | B13: GRAPHICS AND FILMS | C13: 313695 | D13: =C13/$C$5 -> 21.046293
A14: A6 | B14: BLINDS | C14: 906563 | D14: =C14/$C$5 -> 60.822744
A15: A7 | B15: PLANTERS | C15: 426099 | D15: =C15/$C$5 -> 28.587655
A16: A8 | B16: TOILET WORKS | C16: 2825883 | D16: =C16/$C$5 -> 189.59296
A18: B | B18: FURNITURE AND FURNISHING | C18: 4937261 | D18: =SUM(D19:D22) -> 331.24864
A19: B1 | B19: CARPET FLOORING | C19: 1326821 | D19: =C19/$C$5 -> 89.018517
A20: B2 | B20: MODULAR FURNITURE | C20: 1394656 | D20: =C20/$C$5 -> 93.569675
A21: B3 | B21: LOOSE FURNITURE & CHAIRS | C21: 2215784 | D21: =C21/$C$5 -> 148.66045
A23: C | B23: ELECTRICAL WORKS | C23: 8768969 | D23: =SUM(D24:D26) -> 588.32399
A24: C1 | B24: ELECTRICAL WORKS | C24: 6382430 | D24: =C24/$C$5 -> 428.20731
A25: C2 | B25: LIGHT FIXTURES | C25: 2386539 | D25: =C25/$C$5 -> 160.11667
A27: D | B27: HVAC | C27: =C28 -> 7528130 | D27: =SUM(D28:D29) -> 505.07414
A28: D1 | B28: HVAC | C28: 7528130 | D28: =C28/$C$5 -> 505.07414
A30: E | B30: DATA NETWORK | C30: 1931970 | D30: =D31 -> 129.61892
A31: E1 | B31: PASSIVE NETWORKING | C31: 1931970 | D31: =C31/$C$5 -> 129.61892
A33: F | B33: PHE WORKS | C33: =C34 -> 160300 | D33: =SUM(D34) -> 10.75478
A34: F1 | B34: PLUMBING WORKS | C34: 160300 | D34: =C34/$C$5 -> 10.75478
A36: G | B36: FLSS WORKS | C36: 400000 | D36: =C36/C5 -> 26.836632
A37: G1 | B37: FLSS WORKS (Refurbishment of existing services) | C37: =C36 -> 400000 | D37: =C37/C$5 -> 26.836632
A39: H | B39: OTHER ITEMS - DISHWASH & KITCHEN AREA | C39: =sum(C40:C41) -> 1569750 | D39: =sum(D40:D41) -> 105.31701
A40: H1 | B40: DISHWASH AREA | C40: 666540 | D40: =C40/C$5 -> 44.719222
A41: H2 | B41: KITCHEN EQUIPMENTS & OTHERS | C41: 903210 | D41: =C41/C$5 -> 60.597786
B43: TOTAL (EXCLUSIVE OF TAXES) | C43: =sum(C33,C36,C30,C27,C23,C18,C8,C39) -> 57004000 | D43: =sum(D33,D36,D30,D27,D23,D18,D8,D39) -> 3824.4884
B44: GST @ 18% | C44: =C43*0.18 -> 10260720
B45: GRAND TOTAL (WITH TAXES) | C45: 67264720

Sheet EXT FINAL SUMMARY
A1: Project: KOHLER_PUNE
A2: Commercial Proposal by: FLIPSPACES TECHNOLOGY LABS PRIVATE LIMITED
A4: BILL OF QUANTITIES
B5: PROJECT AREA (SFT) - Approx | C5: 14905
A6: S.No. | B6: Cost Heads | C6: AMOUNT (INR) | D6: Rate Per Sft
A8: A | B8: ARCHITECTURAL WORKS : CIVIL AND INTERIORS | C8: 31707620 | D8: =SUM(D9:D17) -> 2127.3143
A9: A1 | B9: CIVIL WORKS | C9: 3917559 | D9: =C9/$C$5 -> 262.83522
A10: A2 | B10: INTERIOR WORKS | C10: 20810221 | D10: =C10/$C$5 -> 1396.1906
A11: A3 | B11: MODULAR GLASS PARTITIONS AND DOORS | C11: 2074408 | D11: =C11/$C$5 -> 139.17531
A12: A4 | B12: SIGNAGES | C12: 433192 | D12: =C12/$C$5 -> 29.063536
A13: A5 | B13: GRAPHICS AND FILMS | C13: 313695 | D13: =C13/$C$5 -> 21.046293
A14: A6 | B14: BLINDS | C14: 906563 | D14: =C14/$C$5 -> 60.822744
A15: A7 | B15: PLANTERS | C15: 426099 | D15: =C15/$C$5 -> 28.587655
A16: A8 | B16: TOILET WORKS | C16: 2825883 | D16: =C16/$C$5 -> 189.59296
A18: B | B18: FURNITURE AND FURNISHING | C18: 4937261 | D18: =SUM(D19:D22) -> 331.24864
A19: B1 | B19: CARPET FLOORING | C19: 1326821 | D19: =C19/$C$5 -> 89.018517
A20: B2 | B20: MODULAR FURNITURE | C20: 1394656 | D20: =C20/$C$5 -> 93.569675
A21: B3 | B21: LOOSE FURNITURE & CHAIRS | C21: 2215784 | D21: =C21/$C$5 -> 148.66045
A23: C | B23: ELECTRICAL WORKS | C23: 8768969 | D23: =SUM(D24:D26) -> 588.32399
A24: C1 | B24: ELECTRICAL WORKS | C24: 6382430 | D24: =C24/$C$5 -> 428.20731
A25: C2 | B25: LIGHT FIXTURES | C25: 2386539 | D25: =C25/$C$5 -> 160.11667
A27: D | B27: HVAC | C27: =C28 -> 7528130 | D27: =SUM(D28:D29) -> 505.07414
A28: D1 | B28: HVAC | C28: 7528130 | D28: =C28/$C$5 -> 505.07414
A30: E | B30: DATA NETWORK | C30: 1931970 | D30: =D31 -> 129.61892
A31: E1 | B31: PASSIVE NETWORKING | C31: 1931970 | D31: =C31/$C$5 -> 129.61892
A33: F | B33: PHE WORKS | C33: =C34 -> 160300 | D33: =SUM(D34) -> 10.75478
A34: F1 | B34: PLUMBING WORKS | C34: 160300 | D34: =C34/$C$5 -> 10.75478
A36: G | B36: FLSS WORKS | C36: 400000 | D36: =C36/C5 -> 26.836632
A37: G1 | B37: FLSS WORKS (Refurbishment of existing services) | C37: =C36 -> 400000 | D37: =C37/C$5 -> 26.836632
A39: H | B39: OTHER ITEMS - DISHWASH & KITCHEN AREA | C39: =sum(C40:C41) -> 1569750 | D39: =sum(D40:D41) -> 105.31701
A40: H1 | B40: DISHWASH AREA | C40: 666540 | D40: =C40/C$5 -> 44.719222
A41: H2 | B41: KITCHEN EQUIPMENTS & OTHERS | C41: 903210 | D41: =C41/C$5 -> 60.597786
B43: TOTAL (EXCLUSIVE OF TAXES) | C43: =sum(C33,C36,C30,C27,C23,C18,C8,C39) -> 57004000 | D43: =sum(D33,D36,D30,D27,D23,D18,D8,D39) -> 3824.4884
B44: GST @ 18% | C44: =C43*0.18 -> 10260720
B45: GRAND TOTAL (WITH TAXES) | C45: =C44+C43 -> 67264720

Sheet Exclusion
A2: LIST OF EXCLUSIONS
A3: ACTIVE NETWORKING
A4: COMPACTOR / SLOTTED ANGLE RACKS
A5: VIDEO CONFERENCING EQUIPMENT
A6: EPABX
A7: TELEPHONE INSTRUMENTS
A8: LED SCREENS
A9: POLYCOM INSTRUMENTS
A10: PHOTOCOPIER
A11: UPS BATTERIES AND HARDWARE
A12: COMPUTERS/LAPTOPS ETC
A13: PRINTERS
... A47: AV WORKS

Sheet Payment Terms
B3: RA | C3: Day | D3: Payment | E3: Milestone
B4: Advance Payment | C4: 0 | D4: 0.3 | E4: Project mobilisation.
B5: RA1 | C5: 45 | D5: 0.2 | E5: Execution: Demolition, partition line marking, frameworks, single-side skinning, civil wall, plastering, plumbing, ceiling and wall electrical conduiting, floor raceway laying. Material delivery: gypsum frames, gypsum sheets, electrical conduits and raceway, siporex blocks. Key order closures: HVAC, fire alarm system, carpentry.
B6: RA2 | C6: 70 | D6: 0.15 | E6: Execution: closing of partitions from double side, electrical wiring, fire sprinkler piping, FAS wiring. Material delivery: duct material, wires/cables, ply for carpentry items, vitrified tiles. Key order closures: modular furniture, chairs, carpets, glass.
B7: RA3 | C7: 85 | D7: 0.15 | E7: Execution: painting base-coat preparation, glass channel, HVAC duct installation, false ceiling framing. Material delivery: carpets, sanitary fittings and fixtures, doors, DB/MCB. Key order closures: decorative elements, glass films, wallpapers, canvas frames, branding.
B8: RA4 | C8: 110 | D8: 0.15 | E8: Execution: electrical switches/sockets, sanitary fixtures, carpentry structures ready, flush doors, first coat of paint, false ceiling, before HVAC final commissioning and before LV commissioning. Material delivery: modular furniture on site, carpet on site and before chair delivery. Key order closure: deep cleaning.
B9: RA5 | C9: 120 | D9: 0.05 | E9: Release against unconditional bank guarantee of equal amount, valid for 6 months Defects Liability Period.
D11: =sum(D4:D9) -> 1
B12: * Payment to be released within 15 days from invoice date

Sheet Civil Works
A1: SL NO | B1: ITEM DESCRIPTION | C1: LOCATION | D1: BASIC RATE | E1: UNIT | F1: QTY | G1: RATE(INR) | H1: AMOUNT(INR) | I1: REMARKS
A3: 1 | B3: CIVIL WORKS
A5: 1.1 | B5: AAC (AUTOCLAVED AERATED CONCRETE) Block Wall
B6: Providing and constructing autoclaved 6" thick wall of 150mm X 240mm X 600mm Light Weight Block in proper line and level, at all levels in cement mortor 1:4 (1 cement and 4 river sand) using standard size of blocks. Rate shall include providing concrete binders in proportion 1:2:4, RCC binder to be at every 1mtr interval from floor level. The rate to be inclusive of cost of reinforcement and formwork, cover block for reinforcement and all other incidental charges etc., all complete and as directed. The rate shall also include closing the gap between the masonary and RCC beam/ slab finished to required slope.
A7: a | B7: 150mm Thik AAC Block Wall | C7: CRITICAL ZONE, PANTRY | E7: SQM | F7: 120 | G7: 1692 | H7: =G7*F7 -> 203040
A9: 1.2 | B9: Gypsum Plaster
B10: Providing and applying 10 mm thick (average) premixed gypsum plaster of approved make (e.g., Saint Gobain Gyproc) with special additives, conforming to IS:2547 Part I & II–1976, applied in one or two coats over internal surfaces such as gypsum boards, wooden partitions, and false ceiling areas. The surface shall be prepared by cleaning, treating wooden substrates with suitable bonding agents, and applying approved bonding chemical (e.g., Gyproc Bondit) on RCC areas wherever applicable. Chicken mesh to be fixed at all junctions—between blockwork, RCC elements, patli bands, mullions, and wooden framing—to prevent cracks. The plaster shall be finished smooth, in line, level, and plumb, free of undulations, ready for paint finish. Rates include all labour, materials, adhesives, scaffolding, and execution as per architect’s directions.
A11: a | B11: Block Work with Paint | C11: New construction | E11: SQM | F11: 300 | G11: 464 | H11: =G11*F11 -> 139200
A12: b | B12: Builder Walls | C12: AHU, Existing walls | E12: SQM | F12: 150 | G12: 464 | H12: =G12*F12 -> 69600
A14: 1.3 | B14: Cement Plastering | E14: SQM | F14: 110 | G14: 484 | H14: =G14*F14 -> 53240
B15: Providing and applying 12 mm to 15 mm thick cement plaster in 1:5 mix (1 part cement : 5 parts sand — 75% fine and 25% coarse sand) using approved readymade dry mix on blockwork, brickwork, and RCC surfaces. Includes surface preparation, cleaning, wetting, and hacking wherever required. Plaster to be applied evenly in true line, level, and plumb, finished with a smooth trowel finish. Necessary curing to be carried out to ensure strength and durability, all as per architect’s instructions and approved specifications.
A17: 1.4 | B17: Self levelling (3-5mm thickness) | C17: Areas with Carpet/LVT | E17: SQM | F17: 605 | G17: 338 | H17: =G17*F17 -> 204490
B18: Providing and laying of Ardex Commercial levelling cementitious flooring system Surface preparation: Removing all existing weak, un sound CC floor to reach the strong substrate, cleaning the floor area to make it free from all contaminants and complete as per manufacturer's specification. Providing and applying Ardex P 51 primer to the base substrate and allow it to dry completely. Providing and mixing of CL 11, commercial levelling compound consisting of high quality special cement and selected fillers, with water at rate of 5.5-6 Ltr for 25 Kg bag of CL 11, installing at required 3mm to 5mm thickness using suitable pin rake trowel and notch trowel, finally rolling the surface with spike roller and allowed to dry completely, installing vinyl /LVT flooring as per client's requirement, etc and complete as per manufacturer's specification. [ The properties shall confirm to:- Bulk density of powder: Approx. 1.3 kg / Ltr; Weight of fresh mortar: Approx. 2.0 kg / Ltr; Working time: Approx. 25 min; Flow life: Approx. 15 min; Initial set (Vicat): Approx. 40 min; Final set (Vicat) Approx. 1 hr; Ball impact hardness: 6.5mm; Scratch hardness: 1.6mm; Compressive strength: 20 N / mm2
A20: =A17+0.1 -> 1.5 | B20: PCC - upto 75-100mm thick for complete floor area | C20: ENTIRE AREA | E20: SQM | F20: 1400 | G20: 1015 | H20: =G20*F20 -> 1421000
B21: Providing & laying plain cement concrete 1:3:6 nominal mix (1 cement :3 coarse sand : 6 graded stone aggregate 25 mm nominal size) of approved quality with all lead & lift below/above the ground level as per drawing including the cost of cement, levelling of surface of concrete with al lead and lift, labour, material as per specifications and directed by Architect up to thickness of 75-100mm.
A23: =A20+0.1 -> 1.6 | B23: POP Punning
B24: Providing and applying of Plaster of Paris Punning (1st Quality ISI approved POP) over plastered with minimum thickness of 8mm-12mm to existing wall surfaces , column & concrete members etc., to be finished in line and plumb with smooth surface ready to receive paint base. Rate to be inclusive of hacking wall surfaces for better bonding, cleaning, scrubbing the surface, providing grooves if necessary etc., complete as per architect's approval. | C24: Existing Walls | E24: SQM | F24: 120 | G24: 300 | H24: =G24*F24 -> 36000
A26: =A23+0.1 -> 1.7 | B26: RCC Lintel (for Doors) | C26: HUB ROOM | E26: RMT | F26: 6.5 | G26: 2127 | H26: =G26*F26 -> 13825.5
B27: Providing and laying in place reinforced cement concrete with cement concrete of grade 1:2:4 (1 cement: 2 fine aggregates: coarse aggregates) in Lintels, beam counters, shelves etc., at all heights & width and level, including vibrating and curing. Rate shall include cost of centring and shuttering including strutting, propping etc. and removal of form for all heights. The rate shall also include for reinforcement with Fe500 grade TMT bars including straightening, cutting, bending, placing in position and binding all complete.
A29: =A26+0.1 -> 1.8 | B29: Cinder filling - Including cinder filling / block work required to raise the floor area, Pantry / Kitchen | C29: PANTRY | E29: CUM | F29: 25 | G29: 12088 | H29: =G29*F29 -> 302200
B30: Providing and filling Cinder to an average depth of up to 300 mm at locations as indicated on the drawings or as instructed by the architects. Cost to include for proper compaction of the laid cinder and filling the complete area with 1:3:6 cement concrete to fill all gaps in the cinder to form a level even surface on top. The rate shall be inclusive of creating ramp from floor finish to raised area.
A32: =A29+0.1 -> 1.9 | B32: Raised Flooring - 150mm Height | C32: DISHWASH AREA, HANDWASH AREA | E32: SQM | F32: 30 | G32: 1354 | H32: =G32*F32 -> 40620
B33: Providing and laying in line and level up to 150mm height on sunken areas broken light weight concrete block bats of approximately 600 kg. per cum density laid, consolidated, finished smooth, the rate shall be inclusive of 50 mm thk pcc flooring with cement concrete 1:2:4 (1 unit - cement, 2 units - sand, 4 units - coarse aggregates) to receive final smooth finish.
A35: 1.1 | B35: Waterproofing (For Floor + Walls 600 mm High) | C35: DISHWASH AREA, HANDWASH AREA | E35: SQM | F35: 50 | G35: 1015 | H35: =G35*F35 -> 50750
B36: Providing of water proofing - chemical Treatment – the slab to be cleaned and apply 3 coats of chemical on the floor. Base coat – Applying base coat of 1:6 mortar over chemical treatment on the floor and on the peripheral walls upto 600mm.Cost of the water proofing shall include cleaning of the surface of all dirt and grit before the application. The water proofed area shall be ponded and tested for a minimum of 24 hours or as per manufacturer's specification. Note - Warranty to be provided upto 10 years
B37: * Clean surface to remove all dust, foreign matters, loose particles or any deposits of contaminants which could affect the bond between the surface and waterproof coating. * Remove all sharp projections and make surface reasonably smooth * Thoroughly pre-wet all concrete surfaces for at least one hour prior to application of coating, by ponding of water on flat surfaces and by vigorous spraying of water on vertical surfaces. * Remove all water from surfaces prior to applying of water proof coating, so that the surface is only damp or surface dry. Standing water or shiny wet surface shall not be present under any circumstances * Apply water proof coating / Brush Topping as specified for various conditions. * Apply 12mm thick cement plaster 1:4 (1cement : 4 coarse sand) after applications of final coat. * After application of final coat of Tape Crete, allow to air dry for 4-6 hours. Do not use any water for curing during this time. * In case of high temperatures and low humidity combined with high wind condition, cover the coating with polythene sheet to prevent rapid drying. * Maximum 6 hours after final application, moist cure for 24 hours by spraying water. Ensure that at no time during this 24 hour period the coating is completely dry or completely submerged in water. * After moist curing, allow to air dry for 3 days. * After air drying, complete the curing by submersion in water for 24 hours.
A39: 1.11 | B39: Pest Control and Anti-Termite Treatment | C39: Entire Floor | E39: SQM | F39: 1400 | G39: 73 | H39: =G39*F39 -> 102200
B40: Providing & applying Pest Control & Anti-termite treatment by appointing a specialized agency. All work shall in general be executed as specified in IS : 6313 Part II-1981 & as per approved specification of the agency having special know-how for the job. All necessary work to ensure uniform distribution & proper penetration of treatment of treating solution shall be done according to the instruction of the Engineer. This includes treatment to floor area, Walls, Soil Surrounding pipes, Waste & Conduits, Expansion Joints, Junction of the Wall & the floor, Timber & Carpentry Works, Gypsum related works, etc all complete as per the instructions of architect. Pest control need to be done in 3 steps including periodic monthly fumigation and pest control at stores/site/temporary off as EHS requirement. Note: 10 year warranty to be provided on stamp paper.
A42: =A39+0.01 -> 1.12 | B42: Floor chipping upto 100mm thk | C42: - | E42: SQM | F42: 200 | G42: 290 | H42: =G42*F42 -> 58000
B43: Cutting of screed and then chipping of existing hard screed floor and carry debris away from site as per PM instructions. Cost to include levelling the chipped floor area wherever required. Necessary protection with polythene sheet to be provided while execution of floor chipping.
A45: =A42+0.01 -> 1.13 | B45: Dismantling of Doors , Partitions, False flooring etc + Salvage | E45: LS | F45: 1 | G45: 483593 | H45: =G45*F45 -> 483593
B46: Dismantling and removal of existing partitions( gypsum or glass ), ceiling, flooring, wall finishes, furniture, and MEP items. Including protection of base structure, debris disposal, and handing over the site in clean bare shell condition ready for fit-out. Salvaging the material dismantled and not utilized is in contractor's scope
A48: =A45+0.01 -> 1.14 | B48: Debris Removal | E48: Loads | F48: 90 | G48: 8220 | H48: =G48*F48 -> 739800
B49: "Collection, loading, transportation, and disposal of construction debris, excavated soil, and dismantled material from site to an approved dumping location (as per State PCB Norms). Includes all labour, tools, transportation, Mathadi, and incidental charges, ensuring site is left clean and level as directed by the Project Manager. 1 Load = 1 Truck/ Large Vehicle"
B51: TOTAL FOR CIVIL WORKS | H51: =sum(H5:H50) -> 3917558.5

Sheet Interior Works
A1: SL NO | B1: ITEM DESCRIPTION | C1: LOCATION | D1: REFERENCE IMAGE | E1: BASIC RATE | F1: UNIT | G1: QTY | H1: RATE(INR) | I1: AMOUNT(INR) | J1: REMARKS
A3: 1 | B3: FLOORING WORKS
A5: 1.1 | B5: Vitrified Tile Flooring (Level to Match Finished Floor Level)
B6: Providing & laying vitrified flooring with 1st quality homogeneous tiles of approved make, of size as per details, set in average 10mm thk approved tile based adhesive or 1:4 CM upto 30mm average thickness as per site conditions. Rate to include for laying tiles to the pattern as directed by Architect/Consultant including curing, soft cleaning chemical wash etc. Tiles to be laid with spacers (4mm) in-between as per architects/PM instructions. Rate to include the cutting the tiles to size if there are any variations. Cost should include house keeping & cleaning for the vitrified flooring till the handover. Tile to tile joints to be filled with epoxy grout of approved shade. Quoted rate to include the cost of curing, protection with polythene sheet and POP overlay till hand-over.
A7: a | B7: Tile - Type -01 (Size: 600mm X 600mm) | C7: HAND WASH AREA, DISHWASH AREA, TUCK SHOP | E7: INR 80/SFT | F7: SQM | G7: 85 | H7: 2021 | I7: =H7*G7 -> 171785 | J7: Basic Rate: Vitrified Tile - INR 60/SFT
A8: b | B8: Designer Tile - 02 (Size: 300mm X 600mm ) | C8: CAFETERIA | E8: INR 150/SFT | F8: SQM | G8: 50 | H8: 2756 | I8: =H8*G8 -> 137800 | J8: Basic Rate: Pattern Tile - INR 80/SFT
A10: 1.2 | B10: Subway Tile Dado / Cladding
B11: Providing & cladding of Premium vitrified tiles or stone-finish ceramic tiles with specified slip resistance. tile dadoing with 1st quality homogeneous tiles of approved make, of size as per drawings, set in average 6mm thk approved tile based adhesive or CM 1:4. Rate to include for cladding tiles to the pattern as directed by Architect / Consultant, including curing, approved chemical wash etc. Tiles to be cladded with 3mm spacers in between as per architects/PM instructions. Rate to include the cutting the tiles to size if there are any variations. Cost should include house keeping & cleaning of vitrified dadoing till the handover. Rate to include approved epoxy grouting matching to tile colour and also to include cladding of tile with necessary adhesive as per Architects /Pms instructions. Rate to include necessary corner beading / Fine edge curve 10mm corner guard profile to match the tile shade. To have necessary provision for switch cutout other necessary services cut out to be considered. Make: Kajaria, Nitco, Somany.
A12: a | B12: Tile Cladding (300mm X 100mm) - Type 1 | C12: TUCK SHOP, DRY PANTRY | E12: INR 150/SFT | F12: SQM | G12: 12 | H12: 2848 | I12: =H12*G12 -> 34176 | J12: Basic Rate: Wall Tile INR 80/SFT
A13: b | B13: Tile Cladding (600mm X 600mm) - Type 2 | C13: DISHWASH, HAND WASH | E13: INR 100/SFT | F13: SQM | G13: 90 | H13: 2021 | I13: =H13*G13 -> 181890 | J13: Basic Rate: Wall Tile INR 80/SFT
A15: 1.3 | B15: Epoxy Flooring ( Normal)
B16: Providing and applying 2–3 mm thick self-leveling, anti-static, chemical-resistant epoxy flooring in AHU, electrical, UPS, hub, battery, and server rooms using a multi-layer epoxy system of approved make. Surface preparation shall include cleaning, grinding, and priming to ensure proper adhesion. Application shall consist of base coat, conductive copper strip/grid (where required), intermediate coat, and a final topcoat in approved shade with semi-gloss/smooth finish. The flooring shall be non-dusting, jointless, easy to maintain, and resistant to moisture, oils, and chemicals. Includes coving at wall junctions up to 100 mm height, finishing around cut-outs, and all necessary edge detailing. Execution to be carried out in accordance with manufacturer specifications and under the supervision of architect. | C16: HUB ROOM | F16: SQM | G16: 10 | H16: 1378 | I16: =H16*G16 -> 13780
A18: 1.4 | B18: Antistatic Raised Flooring - 300mm Height | C18: HUB ROOM | F18: SQM | G18: 10 | H18: 5053 | I18: =H18*G18 -> 50530
B19: Providing & Fixing antistatic laminate False flooring / Raised floor as per approved sample and as per manufacturer's specifications with 1.5mm thk antistatic laminate, with 600mm x 600mm grid made of fully removable flooring panels with all uncut panels to be interchangeable. The access floor panel type shall be Solid fill of unitized welded steel construction, cementations filled. Panel shall be factory finished with soft surface laminate. The panel edge trim shall have PVC. Floor panel support structure shall be treated to prevent corrosion. Pedestals shall be of adjustable height and will accommodate stringers of approved make or as per the Technical Specification document of the Architect. The vertical surface to be close similar to the horizontal surface. Quoted Rate shall include all materials, labour, tools & tackles, lead & lift, surface preparation, cleaning and etc.., complete at all levels as per the drawings, specifications and as directed by the Engineer In charge.
A21: =A18+0.1 -> 1.5 | B21: Marble flooring
B22: laying Italian marble flooring using selected grade marble slabs of approved make, color, and thickness (typically 18–20 mm), machine-cut and mirror-polished, laid over a cement mortar bed (1:4) or tile adhesive as per site requirement. The surface shall be prepared, leveled, and cured before laying. Marble pieces shall be laid in desired pattern with matching veins and grain flow, maintaining tight joints and proper alignment. Joints shall be filled with color-matched epoxy grout. The laid surface shall be machine-ground, honed, and polished to achieve a seamless, high-gloss finish. Rates to include edge chamfering, corner detailing, protection, curing, and execution in accordance with architect instructions and approved mock-up. | C22: BOARD ROOM, MD CABIN, RECEPTION, PRODUCTION DISPLAY AREA & PASSAGE | E22: INR 650/SFT | F22: SQM | G22: 290 | H22: 11894 | I22: =H22*G22 -> 3449260 | J22: Basic Rate: INR 500/SFT
A24: =A21+0.1 -> 1.6 | B24: Toughened Glass Flooring
B25: Providing and creating a 225 mm (9") deep sunken floor feature at the reception area, including necessary substructure, waterproofing, MS support framework, clear toughened laminated glass panels with anti-skid finish, integrated planter bed below, concealed warm-white LED strip lighting with aluminium profiles and diffusers, access provisions for maintenance, edge trims, all necessary supports, fixings, wiring, and making good, complete as per approved design and drawings. | C25: RECEPTION | E25: INR 3350/SFT | F25: SQM | G25: 8 | H25: 36746 | I25: =H25*G25 -> 293968 | J25: Basic Rate: INR 1050/SFT
A27: =A24+0.1 -> 1.7 | B27: Water Body Flooring - Product Display Feature
B28: Providing, fabricating and installing a multi-level water body product display feature comprising three stepped tiers of varying heights (1st layer height - 250mm, 2nd layer height- 150mm, 3rd layer height- 300mm to 450mm), including RCC/brick masonry base structure, waterproofing treatment, IPS screed, stone/marble cladding finish, pebble bed infill at each level, concealed recirculating water fountain system with collection sump, SS water nozzles, submersible pumps, filtration system, piping network, control valves, access chambers, concealed LED strip lighting with drivers, electrical wiring, drainage provisions, necessary supports, edge trims, testing & commissioning and all associated civil, electrical and finishing works, complete as per approved design, specifications and drawings. Water shall be recirculated through an integrated filtration and pumping mechanism. | C28: DISPLAY AREA, FEATURE WALL | E28: INR 7500/SFT | F28: SQM | G28: 6 | H28: 83404 | I28: =H28*G28 -> 500424 | J28: Basic Rate: INR 3000/SFT
A30: 1.8 | B30: Wooden Tile Flooring
B31: Providing and fixing 10 mm thick laminated wooden flooring over existing prepared surface, including 4 mm thick foam underlay sheet with polyethylene moisture barrier, click-lock interlocking system, matching skirting/trims, edge profiles, cutting, finishing, and all necessary accessories, complete as per manufacturer's specifications and approved design. | C31: CAFETERIA | E31: INR 150/SFT | F31: SQM | G31: 350 | H31: 1768 | I31: =H31*G31 -> 618800 | J31: Basic Rate: Wooden Tile - INR 120/SFT
A33: 1.9 | B33: Epoxy Water Flooring Under Designer Feature Wall (230 mm Height)
B34: Providing and creating a decorative epoxy water-effect feature trench below the designer feature wall, comprising a 230 mm high recessed base structure, necessary waterproofing treatment, decorative natural river pebbles, self-levelling UV-stable transparent epoxy resin finish to achieve a water-like appearance, edge trims, substrate preparation, necessary supports, formwork, finishing, polishing and all associated materials, labour, accessories and making good works, complete as per approved design and drawings. | C34: FOYER AREA | E34: INR 800/SFT | F34: SQM | G34: 3 | H34: 9187 | I34: =H34*G34 -> 27561 | J34: Basic Rate: INR 200/SFT
B36: TOTAL FOR FLOORING WORKS | I36: =SUM(I3:I35) -> 5479974
A38: 2 | B38: PARTITION & ASSOCIATED WORKS
A40: 2.1 | B40: 100mm Gypsum Board Full Height Partition Without Finish - GI Framework (Both Side GYP Board) | C40: ALL AREAS | F40: SQM | G40: 295 | H40: 3170 | I40: =H40*G40 -> 935150
B41: Providing and fixing full height 100mm thick partition with GI framework of approved brand @ 600 mm c/c both ways finished with Double layer of 12.5mm thick gypsum board both sides and inclusive of 50mm thk Rockwool wool insulation of approved make (40kg/m3 density grade as specified) fixed to floor & RCC roof with screw, including provisions for grooves and fiber tape to be used for jointing and space/ cut-outs for electrical sockets/switches and conduits etc., as per detail drawings and specification and duly fixed to floor/wall/RCC roof with fasteners. Member placement to be worked out as per grooves.12mm comm. ply frame for all openings (doors/windows) and 10x10mm wide Aluminium Corner guard (as per approved make) edge protection profile at all the corners of the walls ,shall be provided. One side of the partition to be measured and paid for. Rockwool insulation shall be wrapped in Tissue paper prior to installation. Care must be taken that the boards are raised 3mm from the floor and in this gap, chauking compound is injected, for successive layers and similarly for the true ceiling channel. Gypsum partition to be installed as per OEM Installation Guidelines Make: USG Boral / Gyproc / India Gypsum Asouctic ratings to be maintained at, for Enclosed rooms: STC45 VP and Director’s room: STC50 VC & Meeting rooms: STC50
A42: a | B42: Above Door/Glass Partition | F42: SQM | G42: 35 | H42: 3170 | I42: =H42*G42 -> 110950
B43: Specs same as 2.01
A45: b | B45: 200mm thick partition for AV Support | C45: BOARD ROOM/AV AREA | F45: SQM | G45: 40 | H45: 5053 | I45: =H45*G45 -> 202120
B46: Specs same as 2.01, but with Aluminium channel and one side 12 mm ply finish
A48: 2.2 | B48: Ply backing
B49: Providing and fixing 8mm/12mm thick plywood backing on the existing surface Specification to be considered as per low VOC for LEED Compliance as per consultant guidelines. Decorative Cladding Acoustic Panelling Laminate Panelling Lacquered Glass Panelling | C49: MEETING RM, BOARD RM, MD CABIN, HOD CABIN, DESIGN FEATURE WALL, PRODUCT DISPLAY & CAFE | F49: SQM | G49: 350 | H49: 1378 | I49: =H49*G49 -> 482300
A51: 2.3 | B51: Decorative Wooden Rafter partition - pine wood
B52: Providing and fixing floor-to-ceiling decorative vertical wooden rafter partition comprising solid pine wood members of size 50 mm x 50 mm (or as per approved drawings), installed at uniform spacing to create a semi-open screening element. The rafters shall be fixed to a concealed MS support framework fabricated from minimum 25 x 25 x 1.6 mm thick box sections, securely anchored to the floor slab and ceiling structure. The MS framework shall be treated with anti-rust primer and finished with synthetic enamel paint. Pine wood members shall be machine-finished, sanded and coated with melamine/PU polish in approved shade and finish. The scope shall include all connectors, brackets, anchoring hardware, edge finishing, cutting, alignment, fixing and making good works, complete as per approved design, specifications and architect's drawings. | C52: RECEPTION, WORKSTATION AREA | E52: INR 555/SFT | F52: SQM | G52: 40 | H52: 6672 | I52: =H52*G52 -> 266880 | J52: Basic Rate: INR 300/SFT
A54: 2.4 | B54: Window Sill with Flexible Stone Finish | F54: RMT | G54: 165 | H54: 2067 | I54: =H54*G54 -> 341055
B55: Providing and fixing window sill finished with 2–3 mm thick natural flexible stone veneer sheets over 18 mm thick MDF/plywood backing substrate, in approved texture and shade, including adhesive fixing, edge finishing, joint treatment, cutting, alignment and all necessary accessories, complete as per detailed drawings and approved design. Size: 250 mm to 300 mm wide window sill, complete in all respects.
B57: TOTAL FOR PARTITION & ASSOCIATED WORKS | I57: =SUM(I38:I56) -> 2338455
A59: 3 | B59: CEILING WORKS
A61: 3.1 | B61: Painting for False Ceiling | F61: SQM | G61: 1000 | H61: 336 | I61: =H61*G61 -> 336000
B62: Providing and applying Acrylic Emulsion Paint of approved shade 3 or more coats on False ceiling /bulkheads etc. complete as per design & details shown in drawing. Job shall include thoroughly brushing & grinding the surface to a proper level, preparing surface, make it good to receive new paint and finishing of surface with approved paint. Cost to include taping of downlights to save it from any damage. Rate to include PT slab marking enamel paint as architect instructions. Rate shall include all wastages, scaffolding etc. Refer to detail drawing & specification document. | C62: ALL AREA
A64: 3.2 | B64: Plain Gypsum board ceiling | F64: SQM | G64: 780 | H64: 1102 | I64: =H64*G64 -> 859560
B65: Providing and fixing plain Gypsum Board Ceiling finished with acrylic emulsion paint of approved shade, using G.I. framework suspended from the RCC slab. 12.5mm tapered edge gypsum boards shall be screw-fixed to ceiling sections, jointed and finished with compound, paper tape, and primer to achieve a smooth surface. Work includes all perimeter channels, suspension systems, supports, and coordination for electrical, fire alarm, HVAC, and light fixture cut-outs, complete as per architect’s direction. | C65: ALL AREA
A67: 3.3 | B67: Designer Ceiling - Veneer finish ( with cove light) | E67: INR 550/SFT | F67: SQM | G67: 10 | H67: 5971 | I67: =H67*G67 -> 59710 | J67: Basic Rate: INR 300/SFT
B68: Providing and installing decorative laminated false ceiling, comprising GI framework (perimeter channels, intermediate channels, and hangers) suspended from RCC slab as per approved layout, finished with 12mm thick commercial plywood base and high-pressure laminate (HPL) finish of approved shade and texture pasted using adhesive, including formation of custom-cut geometric/coffered patterns with rounded edges as per design, provision of concealed LED profile lighting, including all necessary backing supports, cut-outs for profile lights and services, complete with screws, fasteners, and accessories, ensuring proper alignment, level, and finish, all as per drawings and specifications; rate to include material, labour, lighting integration support, and complete installation. | C68: BOARD ROOM | J68: Basic Rate : Veneer INR 150/SFT
A70: 3.4 | B70: Fire Rated modular grid ceiling | F70: SQM | G70: 10 | H70: 2297 | I70: =H70*G70 -> 22970
B71: Providing and installing fire-rated modular grid ceiling system using mineral fiber or metal tiles of approved make and thickness, tested and certified for the required fire rating (typically 60 or 120 minutes) as per IS/UL/BS standards. Ceiling tiles to be factory-finished, fire-resistant, and installed in an exposed or concealed T-grid framework suspended from the RCC slab using GI suspension system with fire-rated hangers and accessories. Includes perimeter channels, edge trims, and cut-outs for fire-compliant light fixtures, HVAC, sprinklers, and other services. The entire system shall be installed in line and level, ensuring airtight joints and compliant integration with fireproof barriers or walls. Work to be executed as per manufacturer’s guidelines, fire consultant’s requirements, and under architect supervision | C71: HUB ROOM
A73: 46086 | B73: Modular Metal Grid false ceiling | C73: DISH WASH AREA, WASHROOM | F73: SQM | G73: 70 | H73: 1709 | I73: =H73*G73 -> 119630
B74: Providing & Applying perlite based Gypsum plaster with Bulk density of 650-710 Kg/m3 and finesses of 95% passing through 150 micron like “Gyproc” make Elite FS 90 One Coat plaster on RCC Ceilings (with Trowel Finish on Wall). Rate to include for Surface Preparation, filling cracks in the background if any, surface cleaning/curing (if required) ,applying 6 mm to 8 mm thick Gypsum (on surface already coated with bonding agent) and finishing in line and level with trowel with neat and smooth surfaces free of undulations, cracks, levelling marks etc or any other deformities arising out of poor workmanship. Rate to include for providing & Erecting MS H frame scaffolding, as per the directions of Site Engineer. Rate to include Hacking and scraping of the existing true ceiling. Rate to include necessary scaffolding.
A76: 3.6 | B76: Decorative Circular Ceiling Feature - PVD Champagne Water Ripple Effect (Corrugated Sheet Material)
B77: Providing and fixing 1.0–1.2 mm thick SS304 PVD Champagne finish water-ripple textured metal sheet over a custom-fabricated circular concealed framework, including suspension system, edge detailing, backing supports, LED integration provisions, cutting, finishing and all necessary accessories, complete as per approved design and drawings. | E77: INR 3000/SFT | F77: SQM | G77: 15 | H77: 36746 | I77: =H77*G77 -> 551190 | J77: ⁠Basic Rate: Metal beaten sheet - INR 450/SFT
A79: 3.7 | B79: Decorative Suspended Open Cell ceiling/Acoustic Baffle ceiling
B80: Providing, fabricating and installing decorative suspended metal baffle ceiling modules of varying diameters and patterns, comprising powder-coated aluminium/MS sections with concealed support framework, GI suspension system, hangers and all necessary hardware, complete as per approved design and drawings. The metal baffles shall have a factory-applied 60–80 micron powder-coated finish, UV, scratch and corrosion resistant, applied on all exposed and concealed surfaces for a uniform and durable finish. Complete in all respects. | C80: CAFETERIA | E80: INR 345/SFT | F80: SQM | G80: 200 | H80: 3858 | I80: =H80*G80 -> 771600 | J80: Basic Rate: INR 250/SFT
A82: 3.8 | B82: Cassette AC Boxing | F82: NOS | G82: 40 | H82: 4593 | I82: =H82*G82 -> 183720
B83: Boxing for cassette AC unit: P/F 1200 X 1200 X 400H boxing for cassette AC unit fabricated out of 19mm thk commercial ply and finished with 1mm thk laminate clad on 4mm thk water proof MDF. Boxing shall be suspended from slab [5.4 meter high] with 4 no's 10mm dia threaded rods. Boxing to have a cut-out in the centre to accommodate cassette AC units as per design. Rate to include internal bracing for the boxing and all required hardware and accessories | C83: ALL AREA
A85: 3.9 | B85: Cove Gypsum Ceiling
B86: Providing and fixing suspended gypsum cove ceiling comprising 12.5 mm thick gypsum board fixed over a GI framework system made of perimeter channels, intermediate channels and ceiling sections suspended from the slab with approved hangers. The scope shall include cove formation for concealed LED lighting, joint treatment, corner beads, necessary cut-outs for MEP services, surface preparation and painting finish, complete with all accessories, labour and making good works as per approved design and drawings. | C86: RECEPTION, MD CABIN, BOARDROOM | F86: RMT | G86: 120 | H86: 506 | I86: =H86*G86 -> 60720
B88: TOTAL CEILING WORKS | I88: =SUM(I59:I87) -> 2965100
A90: 4 | B90: WALL FINISHES
A92: 4.1 | B92: Premium Acrylic Emulsion Paint (Wall / Partitions / Column) | F92: SQM | G92: 750 | H92: 349 | I92: =H92*G92 -> 261750
B93: Providing & applying of Premium, low-VOC acrylic emulsion paint. Color to be selected by the client. for walls. Shall be applied with oil based primer coat after rubbing with sand paper onto the existing wall surface. Surface to be smoothened using acrylic based putty as directed. Uneven surfaces to be finished with 2 coats of acrylic based putty on the primer. Surfaces are then sandpapered to achieve a smooth surface and 3 coats of premium acrylic emulsion Paint of approved shade to be applied. The top coat should be 3 coats of 'Superfine' roller matt finish. The colour should be approved by Architect. Note : Rate should be inclusive of Masking for fixtures & wooden frames & Protection to be provided to all finished surfaces including ceiling / wall / flooring as per site conditions. Make: Paint: Asian Paints, Berger, Dulux. | C93: ALL AREA
A95: 4.2 | B95: Acoustic Panelling | E95: INR 275/SFT | F95: SQM | G95: 150 | H95: 3389 | I95: =H95*G95 -> 508350 | J95: Basic Rate: Acoustic Panel INR 120/SFT - 9mm thick
B96: Providing and fixing 9mm thick acoustic panels of minimum of 0.7 NRC on to existing partition by using suitable adhessive as per manufacturer's recommendation. Acoustic felt panels, approved by Architect / interior Designer, shall be installed in sizes as specified in construction drawings / documents. Rate shall be inclusive of material cost (comprising of felt panels & adhesive), labour cost, complete in all respects. Location: As per project, Model: As mentioned in drawings/documents, Size: As mentioned in drawings/documents | C96: MEETING ROOM, BOARD ROOM, MD CABIN, HOD CABIN, BOARD ROOM, WORKSATION AREA
A98: 4.3 | B98: Lacquered Glass Panelling | E98: INR 500/SFT | F98: SQM | G98: 50 | H98: 5971 | I98: =H98*G98 -> 298550 | J98: Basic Rate: INR 300/SFT
B99: Provifding & fixing of 6mm thk lacquered / backpainted glass on 12mm thk ply panelling. Rate shall include 12mm thk commercial ply, Edge machine grinding fixing, all wastage, melamine polish etc. complete as per details provided. Glass: Saint-Gobain, ModiGuard. | C99: MEETING ROOM, BOARD ROOM
A101: 4.4 | B101: Laminate Paneling | F101: SQM | G101: 10 | H101: 2297 | I101: =H101*G101 -> 22970 | J101: Basic Rate: Laminate Panel INR 60/SFT
B102: Supply and installation of Ply paneling made from approved grade Ply fixed on necessary framework, finished in approved Sample, edge finishing, necessary hardware, and all complete as per approved drawings and specifications. | C102: MD CABIN
A104: 4.5 | B104: CNC Cut Designer Feature Paneling
B105: Providing, fabricating and installing CNC-cut designer feature wall paneling of overall size 1650 mm x 3400 mm, comprising 12 mm MDF panels with layered 2D/3D graphic elements, CNC-routed patterns and motifs finished with PU paint in approved colours and shades. The paneling shall be fixed over a concealed framework/backing substrate and shall include all edge finishing, spacers, supports, adhesives, hardware, cutting, alignment and installation accessories, complete as per approved design, artwork and architect's drawings. | C105: HOD CABINS | E105: INR 450/sft | F105: SQM | G105: 24 | H105: 5053 | I105: =H105*G105 -> 121272 | J105: Basic Rate: INR 300/SFT
A107: =A104+0.1 -> 4.6 | B107: Veneer Fluted Paneling (Wooden effect) Type -01 | E107: INR 300/SFT | F107: SQM | G107: 130 | H107: 3578 | I107: =H107*G107 -> 465140 | J107: Basic Rate: Veneer Panel INR 150/SFT
B108: Providing and fixing fluted wall paneling/cladding using factory-finished panels in MDF, PU-coated profiles, engineered wood as per approved material and design. Panels shall feature regular vertical grooves or rounded flute profiles, supplied in standard sizes (typically 8' x 4' sheets or custom modular sections), and fixed over a plywood backing or GI framework using adhesive and concealed fasteners. Joints between panels to be finished seamlessly or with matching trims as required. Final finish may include pre-laminated surfaces, PU paint, veneer, or textured coat depending on the selected variant. Includes all edge detailing, corner finishes, and cut-outs for electrical or services. Work to be executed in true vertical line and level, as per architect drawings and approved sample. | C108: MD CABIN, HOD CABIN, BOARD ROOM,
A110: =A107+0.1 -> 4.7 | B110: MDF Fluted Curve Paneling (Wooden effect) Type -02 | E110: INR 300/SFT | F110: SQM | G110: 70 | H110: 3675 | I110: =H110*G110 -> 257250 | J110: Basic Rate: Fluted Panel INR 150/SFT
B111: Providing and fixing fluted wall paneling/cladding using factory-finished panels in MDF, PU-coated profiles, engineered wood as per approved material and design. Panels shall feature regular vertical grooves or rounded flute profiles, supplied in standard sizes (typically 8' x 4' sheets or custom modular sections), and fixed over a plywood backing or GI framework using adhesive and concealed fasteners. Joints between panels to be finished seamlessly or with matching trims as required. Final finish may include pre-laminated surfaces, PU paint, veneer, or textured coat depending on the selected variant. Includes all edge detailing, corner finishes, and cut-outs for electrical or services. Work to be executed in true vertical line and level, as per architect drawings and approved sample. | C111: WORKSTATION COLUMN
A113: =A110+0.1 -> 4.8 | B113: 50mm HT Aluminium Wall Skirting (As per appd. PVD Finish) | E113: INR 275/RMT | F113: RMT | G113: 750 | H113: 322 | I113: =H113*G113 -> 241500 | J113: Basic Rate: Skirting - INR 180/RMT
B114: Supply and installation of 50mm high aluminium wall skirting made from approved grade aluminium profile with black powder-coated finish, fixed with necessary fasteners/adhesive, including corner joints, edge finishing, accessories, and all complete as per approved drawings and specifications. | C114: All area
A116: =A113+0.1 -> 4.9 | B116: Acrylic Solid Surface (Corian) Cladding | E116: INR 1175/SFT | F116: SQM | G116: 36 | H116: 15617 | I116: =H116*G116 -> 562212 | J116: Basic Rate: Corian - Solid Acrylic INR 550/SFT , 6mm thick
B117: Corian cladding fixed on approved backing/framework, including cutting, edge finishing, joint treatment, and all accessories. Provision of concealed LED cove lighting with aluminum profile, diffuser, wiring, and complete installation as per approved drawings and specifications. Measurement in Sq.m for paneling and Rm for cove lighting, unless otherwise specified. | C117: FEATURE WALL | J117: Basic Rate: Corian - Solid Acrylic INR 550/SFT , 6mm thick
A119: 46122 | B119: Stucco/Textured Paint Finish- Wall finishing | E119: INR 150/SFT | F119: SQM | G119: 60 | H119: 1861 | I119: =H119*G119 -> 111660 | J119: Basic Rate: INR 80/SFT
B120: The Stucco Wall Paint shall include the supply and application of three coats of paint on interior walls. It shall have a lustrous finish and be easy to apply using a brush or roller. The paint shall dry quickly and provide a smooth, durable, washable finish. The scope of work includes site preparation, cleaning and preparation of walls, supply, and application of paint. Base rate : 250 RS/SFT | C120: RECEPTION, DISPLAY WALL
A123: 4.11 | B123: Corner Guard (As per appd. PVD Finish) | C123: All corners | E123: INR 275/RMT | F123: RMT | G123: 250 | H123: 322 | I123: =H123*G123 -> 80500 | J123: Basic Rate: Corner Profile INR 150/RMT
B124: Providing and fixing of Modular Black anodized aluminium corner 'L' guard and to be fixing with tape / adhesive as per architect's approval / manufacturer specifications.. Corner Guard of size - 12 x 12mm x 1.5mm thick
A126: =A123+0.01 -> 4.12 | B126: Decorative Feature Column Cladding (MDF with Wood Finish Paint)
B127: Providing, fabricating and installing decorative feature column cladding comprising 18 mm thick MDF ribs of varying profiles and curvature, fixed over a concealed MS framework to create an organic sculptural form as per approved design. The MDF members shall be machine-cut, edge-rounded, sanded and finished with wood-finish PU paint in approved shade. The scope shall include top canopy integration, concealed supports, fixing hardware, edge finishing, cutting, alignment, making good works and all necessary accessories, complete as per approved design and architect's drawings. | C127: CAFETERIA | E127: INR 490/SFT | F127: SQM | G127: 80 | H127: 5420 | I127: =H127*G127 -> 433600 | J127: Basic Rate: Cladding - Column INR 150/SFT
A129: =A126+0.01 -> 4.13 | B129: VERTICAL GYPSUM BOXING | F129: SQM | G129: 40 | H129: 3491 | I129: =H129*G129 -> 139640
B130: Providing and installing vertical gypsum board boxing over the existing gypsum false ceiling using 12.5 mm thick gypsum boards fixed on a concealed GI metal framework. The work includes fabrication of vertical GI studs and channels, cutting and fixing of gypsum boards, joint treatment with tape and compound, sanding, and preparation for painting. The boxing shall be true to line, rigid, and finished smooth as per drawings and specifications. All necessary supports, hangers, fasteners, and accessories for a complete and durable installation are included.
A132: =A129+0.01 -> 4.14 | B132: WALLPAPAER (Stone Finish) | C132: Cafe, ws, Hod Cabins, Etc | E132: INR 300/SFT | F132: SQM | G132: 320 | H132: 3858 | I132: =H132*G132 -> 1234560 | J132: Basic Rate: Wallpaper - INR 100/SFT
B133: Providing and fixing 2–3 mm thick natural flexible stone veneer sheets in approved texture and shade over prepared backing substrate using approved adhesive system, complete with edge finishing, joint treatment, cutting, alignment and all necessary accessories to achieve a seamless natural stone appearance. The material shall be lightweight, flexible and suitable for application on flat and curved surfaces, complete as per approved design and drawings.
B135: TOTAL FOR WALL FINISHES | I135: =SUM(I90:I134) -> 4738954
A137: 5 | B137: MILLWORKS
A139: 5.1 | B139: Reception Table 2500mm X 900mm X 1000mm | C139: Reception | E139: INR 355000/UNIT | F139: NOS | G139: 1 | H139: 394053 | I139: =H139*G139 -> 394053 | J139: Basic Rate: INR 250000/UNIT
B140: Providing, fabricating and fixing of reception table with 50mm thick table top formed of 19mm thick ply boxing with necessary concealed support & ply surface cladded with 12mm thick acrylic solid surface + veneer of approved shade & make with necessary edge as per details. Inside surface of the table to be finished with laminate of approved shade and make. To have transaction counter vertical 150mm thick and top 300mm deep & 1050mm high ply boxing formed of 19mm thk ply boxing with necessary concealed MS / aluminium supports and ply all exposed surface (Front fascia & top) cladded with 12mm acrylic solid surface of approved shade & pattern as per details. Table to have vertical support ply boxing formed of necessary concealed MS / aluminium frame work cladded with 19mm thick ply & ply surface finished with 12mm acrylic solid surface of approved shade. All inside ply surface finished with 1.0mm thick laminate of approved shade. Front fascia to have necessary cove light provision as per details. Table top to have wire gromet as per details. Table to have provision for raceways as per details. Vendor to submit the shop drawing for approval. To have necessary skirting as per details. Rate to include one no's of pedestal units finished with laminate. Providing drawer pedestals with two drawers of 150mm ht and one drawer of 325 ht & 50mm laminate skirting as per details. Drawers made of 19mm ply finished with laminate inside & outside of approved colour. Rate should include necessary hardware like castors, brass hinges, ball catches, fully extendable drawer slides, locks, brushed SS handles etc., To have 50mm laminate skirting as per details. All internal surfaces to be finished with laminate and exposed surfaces to be finished with 12mm thick acrylic solid surface of approved shade. Cost to include Borer/Ant termite treatment for wood/plywood.
A142: 5.2 | B142: Boardroom Table (5600mm X 1800mm) | C142: Boardroom | E142: INR 275000/UNIT | F142: NOS | G142: 1 | H142: 292518 | I142: =H142*G142 -> 292518 | J142: Basic Rate: INR 200000/UNIT
B143: Providing and installing custom-made boardroom table in veneer finish, comprising MS/plywood internal structure with 12mm/18mm commercial plywood substrate, finished with natural veneer of approved species and shade with melamine/polish coating, including rounded/curved edge profile and smooth edge banding, complete with integrated central cable management system (metal/laminate box with cut-outs for power, data, HDMI, and AV connectivity), supported on solid base/leg structure in laminate/PU painted finish as per design, including necessary reinforcement for stability, provision for floor access points if required, and all hardware, fittings, and accessories; ensuring proper alignment, level, and finish, complete with material, labour, polishing, transportation, and installation as per drawings and specifications.
A145: 5.3 | B145: Dry Pantry Counter / Plate Counter Providing and fixing Pantry Cabinetry of 750mm depth and length as per design, with storage made in 19mm thick marine plywood frame work, as per approved materials, shade and drawings. The counter top of 19mm thickness 40mm facia and 200mm high back splash shall be finished in approved granite of polished finish with 19mm thick marine ply backing. The storage units under shall have intermediate shelves and per intent with shutters and drawer units all made in 19mm thick marine plywood and finished with approved laminate. The counter shall have necessary cut out to accommodate approved sink, plumbing attachments, openings for bins and others. Counter edge to be finished as per the detailed drawings. The insides of the shutters, and the storage and all exposed plywood surfaces shall be finished in laminate of approved shade with PVC edge lipping as per the detailed drawings. Cost to include all hardwares of approved make, accessories and supports, complete as per drawings and Architect's approval. The measurement of all materials shall be as per actuals, with water dispenser unit of 750mm depth made from 18mm thick marine plywood with full-height shutters, finished with approved laminate on exposed surfaces, including necessary internal supports, edge banding, hardware, hinges, handles, locking arrangement, and all complete as per approved drawings and specifications. | C145: CAFETERIA | J145: Basic Rate: Granite Top INR 200/SFT
A146: a | B146: Counter Size 01-850mm H 750mm D 3290mm L | F146: NOS | G146: 1 | H146: 78085 | I146: =H146*G146 -> 78085
A147: b | B147: Counter Size 01-850mm H 750mm D 1500mm L | F147: NOS | G147: 1 | H147: 50526 | I147: =H147*G147 -> 50526
A148: c | B148: Counter Size 03-850mm H Standard D 4500mm L (Plate Counter / Storage counter / Serving counter) | F148: NOS | G148: 1 | H148: 105645 | I148: =H148*G148 -> 105645
A149: d | B149: Counter Size 04-850mm H Standard D 3300mm L (Plate Counter / Storage counter / Serving counter) | F149: NOS | G149: 1 | H149: 78085 | I149: =H149*G149 -> 78085
A151: =A145+0.1 -> 5.4 | B151: Overhead Storage and Wall shelf with cove light | C151: CAFETERIA | F151: NOS | G151: 1 | H151: 50526 | I151: =H151*G151 -> 50526
...

Sheet Modular Glass Partition & Doors
A1: SL NO | B1: ITEM DESCRIPTION | C1: LOCATION | D1: BASIC RATE | E1: UNIT | F1: QTY | G1: RATE (INR) | H1: AMOUNT (INR) | I1: REMARKS
A3: 1 | B3: MODULAR GLASS PARTITION
A5: 1.1 | B5: Glass Partition - (till 2400 mm high as per design)
B6: Providing & Fixing of Single glazed partitions: Use 10-12mm thick, clear, tempered glass with polished edges at both sides. 100mm wide Frame with a high-quality, slim-profile aluminum section of a specified make. Use stainless steel (SS) patch fittings and soft-close hinges. Aluminium section of 45*25mm. All sections duly coated in up to 15-20 microns and required accessories ie glass to glass aluminium I sections, T section & 90 degree sections & Glass packing to adjust the floor level. Ceiling profile, Floor profile and wall profile are 25 mm visible face and 45 mm wide & insertion of gasket to adhere the glass firm & airtight.- Black Powder Coated. Mode of measurements:- Front Elevation, one side only Glass: Saint-Gobain, ModiGuard.
A7: a | B7: Single Glazed Partition | E7: SQM | F7: 16 | G7: 5319 | H7: =G7*F7 -> 85104
A8: B | B8: Curve Single Glazed Partition | E8: SQM | F8: 65 | G8: 10154 | H8: =G8*F8 -> 660010
A10: 1.2 | B10: Above Glass Gypsum partition | E10: SQM | F10: 81 | G10: 3481 | H10: =G10*F10 -> 281961
B11: "Above glass partition (100mm thick Gypsum Partition) with Al Frame (both side gyp board) :- Providing and constructing 100 mm thick gypsum board partition below full-height glass using powder-coated aluminium framework with double skin gypsum board on both sides. Aluminium sections (minimum 1.2 mm thick) shall form the base and vertical framework at required spacing, securely anchored to the floor and ceiling. Both sides of the framework to be clad with 12.5 mm thick gypsum boards, screw-fixed and finished with joint tape and jointing compound in multiple coats. Partition height to be as per approved drawings, terminating at the glass sill level with proper interface detailing between gypsum and glass. Includes cut-outs for electrical boxes, MEP provisions, and necessary supports. All work to be completed in line, level, and plumb, finished smooth and ready for paint, as per architect instructions and approved details."
B13: TOTAL FOR MODULAR GLASS PARTITION | H13: =SUM(H3:H12) -> 1027075
A15: 2 | B15: DOORS
A17: 2.1 | B17: Fire Metal Doors
B18: Fire rated door of 45mm thick powdered coated metal shutter (single/double) . Door shall be of 2 hour fire resistance rating conforming to BS:476 part-22, IS:3614 suitable for mounting on MS frame as recommended by manufacturer, with heat activated intumescent fire seal strips of size 12x4mm fixed on all sides. Shutter to be mounted with approved make SS fire rated hinges with necessary screws and one coat of anti-termite fire resistant primer. Door shall be factory finished with powder coating. Rate to include, drop down seal and 3mm undercut, nail groove, complete hardware of approved make & provision for Access Control.
A19: a | B19: 1000mm X 2400mm - Single leaf door (FRD) with vision panel | C19: HUB ROOM | E19: NOS | F19: 1 | G19: 41073 | H19: =G19*F19 -> 41073
A21: 2.2 | B21: Solid Door
B22: Providing, making & fixing of 38mm thick single leaf Laminated Flush door fixed on frame with 4nos hinges & fixing lugs including 4 hinges per leaf per door, door closer/door stop on door completed as per design. The door shall have 500x225mm powder coated louvers to match door frame. Rate is inclusive of all necessary hardware (i.e. lock, handle on both sides, hinges, latch or tower bolt, door stopper, PVC buffer etc.), fixtures, laminate finish etc. Makes: Plywood/MDF: Greenply, CenturyPly, Action Tesa. Hardware: Hafele, Hettich, Ebco. Adhesives: Fevicol, Jivanjor.
A23: a | B23: Door Size : 1000mm X 2400mm | C23: WASHROOM | E23: NOS | F23: 2 | G23: 33071 | H23: =G23*F23 -> 66142
A24: b | B24: Door Size : 1200mm X 2400mm - with Vision Panel | C24: HANDICAP WASHROOM | E24: NOS | F24: 1 | G24: 42355 | H24: =G24*F24 -> 42355
A25: c | B25: Door Size : 1200mm X 2400mm - with Vision Panel | C25: DISHWASH AREA | E25: NOS | F25: 1 | G25: 42355 | H25: =G25*F25 -> 42355
A26: d | B26: Door Size :750mm X 2400mm | C26: JANITOR | E26: NOS | F26: 1 | G26: 27076 | H26: =G26*F26 -> 27076
A28: 2.3 | B28: Glass Door Stiled
B29: Fabricating and fixing of 10mm thk toughned glazed stiled doors of mentioned imension with necessary Stiled fittings lock Hardware with 300mm high Handle door stopper etc. 19mm thk MDF Door Jamb to be provided alound the Door & To be fixed on existing partiton / necessary wooden supports are inclusive. Design to be as per reference image Glass: Saint Gobain / Equivalent Hardware: Dorset / Ozone
A30: a | B30: Door Type - D1 1500mm x 2400mm Double Leaf Single Glazed Door. | C30: CAFETERIA | E30: NOS | F30: 1 | G30: 90511 | H30: =G30*F30 -> 90511
A31: b | B31: Door Type - D2 1000mm x 2400mm Single Leaf Single Glazed Door. | C31: all areas | E31: NOS | F31: 11 | G31: 48350 | H31: =G31*F31 -> 531850
A32: c | B32: Door Type - D3 1800mm x 2400mm Single Leaf Single Glazed Double Door | C32: WAITING FOYER | E32: NOS | F32: 1 | G32: 95733 | H32: =G32*F32 -> 95733
A33: d | B33: Door Type - D4 1800mm x 2400mm Single Leaf Single Glazed Double Door( F.R.D) | C33: MAIN ENTRANCE | E33: NOS | F33: 1 | G33: 110238 | H33: =G33*F33 -> 110238
B35: TOTAL FOR DOORS | H35: =SUM(H15:H34) -> 1047333
B37: TOTAL FOR MODULAR GLASS PARTITION & DOORS | H37: =H35+H13 -> 2074408

Sheet Signages
A1: SL NO | B1: ITEM DESCRIPTION | C1: LOCATION | D1: BASIC RATE | E1: UNIT | F1: QTY | G1: RATE (INR) | H1: AMOUNT (INR) | I1: REMARKS
A3: 1 | B3: Signages
A5: 1.1 | B5: Room Signages - 300mm x 100mm | C5: All Doors | E5: NOS | F5: 20 | G5: 870 | H5: =IF(F5="QRO",0,(F5*$G5)) -> 17400
B6: Supply and fixing of door signage of size 300mm x 100mm formed of anodised aluminium plate fixed with 3M double sided tape. To have black vinyl letters pasted onto the aluminium plate. Rate to include braille as per design
A8: 1.2 | B8: Push/Pull Signages - 100mm x 25mm | C8: All Doors | E8: SET | F8: 45 | G8: 653 | H8: =IF(F8="QRO",0,(F8*$G8)) -> 29385
B9: Supply and fixing of push / pull signage of size 4"x1" formed of SS plate with vinyl stickers in it fixed onto the door with 3M double sided tape. Rate to include braille as per design
A11: 1.3 | B11: Way Finding Signage - 10" x 7" | D11: INR 3600/UNIT | E11: NOS | F11: 30 | G11: 3916 | H11: =IF(F11="QRO",0,(F11*$G11)) -> 117480 | I11: Basic Rate: INR 1500/UNIT
B12: Way Finding Signage: 12mm thick Opaque White Acrylic laser cut to the size of the Sign, Bevell the edges to Smooth Finish, sides painted to Oracle Red Color Matte Finish / Oracle Grey Color Matte Finish. Artwork to be UV printed on Acrylic as per the Brand Guidelines. Sign to be installed Perpendicular to the Wall or Hung from ceiling with necessary fixtures. - Small Sign. Rate to include braille as per design
A14: 1.4 | B14: Corporate / GST Signage (450mm x600mm) | C14: Entrance | E14: NOS | F14: 1 | G14: 7833 | H14: =IF(F14="QRO",0,(F14*$G14)) -> 7833
B15: Supply & installation of corporate / GST signage in approved material & finish, size 450x600mm, fixed securely as per site requirements.
A17: 1.5 | B17: Brand Logo Display | C17: Reception, Behind Feature Wall, Cafeteria | D17: INR 50000/UNIT | E17: NOS | F17: 3 | G17: 52218 | H17: =IF(F17="QRO",0,(F17*$G17)) -> 156654 | I17: Basic Rate: INR 20000/Unit
B18: Supply, fabrication, and installation of brand logo in approved metal material with specified finish, fixed securely on the wall/backdrop using concealed mechanical fixing or approved adhesive method as per site requirement. The scope includes surface preparation, precision cutting, edge finishing, alignment, levelling, installation, and optional LED backlighting/illumination as per approved design, complete with all necessary hardware, accessories, wiring provisions, labour, tools, and tackles. Size: 1800 mm (W) × 600 mm (H)
A20: 1.6 | B20: Acrylic Design Letter- Design Feature wall | C20: Reception | D20: INR 90000/UNIT | E20: LS | F20: 1 | G20: 104440 | H20: =IF(F20="QRO",0,(F20*$G20)) -> 104440 | I20: Basic Rate: INR 50000/UNIT
B21: Providing, fabricating and fixing custom-made acrylic design lettering for feature wall graphics, comprising 10–15 mm thick laser-cut acrylic letters and graphical elements in approved font, size and finish. The scope shall include spacers/standoffs, adhesive fixing, templates for alignment, edge polishing, installation hardware and all accessories required for complete installation as per approved artwork, design and drawings. Complete in all respects.
B24: TOTAL FOR SIGNAGES | H24: =SUM(H3:H23) -> 433192

Sheet Graphics and Films
A1: SL NO | B1: ITEM DESCRIPTION | C1: LOCATION | D1: BASIC RATE | E1: UNIT | F1: QTY | G1: RATE (INR) | H1: AMOUNT (INR) | I1: REMARKS
A3: 1 | B3: Graphics and Films
A5: 1.1 | B5: Graphics / Branding – Wall & Partition | C5: CAFETERIA | D5: INR 125/SFT | E5: SQM | F5: 70 | G5: 1547 | H5: =IF(F5="QRO",0,(F5*$G5)) -> 108290 | I5: Basic Rate: INR 80/SFT
B6: Supply and installation of vinyl-based wall graphics as per the approved design. Materials shall be of premium quality, UV-resistant, and sourced from approved makes. Installation shall be executed neatly, ensuring proper alignment and a smooth, bubble-free finish as per the approved mock-up.
A8: 1.2 | B8: Framed Graphics / Framed Artwork
B9: Supply and installation of high-quality canvas artwork mounted in wooden or MDF frames as per the approved design. Frames shall be finished as per the approved make and installed securely, level, and neatly aligned, matching the approved mock-up.
A10: a | B10: Size: 600mm X 450mm | C10: ALL AREAS | D10: INR 2400/UNIT | E10: NOS | F10: 10 | G10: 2901 | H10: =IF(F10="QRO",0,(F10*$G10)) -> 29010 | I10: Basic Rate: INR 1200/UNIT
A11: b | B11: Size: 1500mm X 900mm | C11: ALL AREAS | D11: INR 3600/UNIT | E11: NOS | F11: 5 | G11: 4341 | H11: =IF(F11="QRO",0,(F11*$G11)) -> 21705 | I11: Basic Rate: INR 1800/UNIT
A13: 1.3 | B13: Primer for Wallpaper / Graphics | C13: ALL AREAS | E13: SQM | F13: 140 | G13: 155 | H13: =IF(F13="QRO",0,(F13*$G13)) -> 21700
B14: Providing and applying Oil based primer finish to walls of approved shade, texture. Existing wall surfaces to be prepare by scraping away any loose particles, dust, etc by washing and scrubbing and 2 coats of oil based primer applied. The wall surfaces are then smoothened using chalk putty as directed. Surfaces are then sandpapered to achieve a smooth finish and made ready to receive wallpaper / graphics as directed.Note : Rate should be inclusive of Masking for fixtures & wooden frames.
A16: 1.4 | B16: Frost Film | C16: MEETING ROOM, HOD CABINS, MD CABIN | D16: INR 110/SFT | E16: SQM | F16: 110 | G16: 1209 | H16: =IF(F16="QRO",0,(F16*$G16)) -> 132990 | I16: Basic Rate: INR 60/SFT
B17: Supply & fixing of approved coloured Frost film/ Privacy Film for Glass Partitions as per manufacturer specification and as per architect instruction.(The successful vendor should submit 10 years Warranty certificate to the client. Product to be certified by Manufacturer's Representative). Wastages to be included in the quoted rate.
B19: TOTAL FOR GRAPHICS & FROST FILM | H19: =SUM(H3:H18) -> 313695

Sheet Blinds
A1: SL NO | B1: ITEM DESCRIPTION | C1: LOCATION | D1: BASIC RATE | E1: UNIT | F1: QTY | G1: RATE (INR) | H1: AMOUNT (INR) | I1: REMARKS
A3: 1 | B3: Blinds
B5: Supply and installation of Roller blinds: Use high-quality, motorized roller blinds with flame-retardant, acoustic fabric. List of makes: roller blinds including gear based mechanism as per specifications mentioned below. Fabric to be combination of glass fiber and polyester as per manufacturer's standards.Bottom of the blind shall be provided with steel profile . The fabric shall be enclosed in the suitably created pocket along with the tube. The tube shall be closed from sides with end caps to give a neat look.Clutch driven roller mechanism with stopper and load bar, all in SS finish to be considered. Make: Vista / Hunter Douglas / MAC
A6: 1.1 | B6: Supply & Installation of manually operated roller blinds as per approved style and shade | C6: ALONG FACADE SIDE | D6: INR 115/SFT | E6: SQM | F6: 450 | G6: 1305 | H6: =IF(F6="QRO",0,(F6*$G6)) -> 587250 | I6: Basic Rate: INR 75/SFT
B7: "Supply & Installation of manually operated Roller blinds as per approved style and shade. HARDWARE - Top Tube : Made of extruded aluminium 38 mm Dia. With wall thickness of 1.2 mm with spline adoptable to accommodate clutch of ACMEDA make. Clutch Mechanism : Moulded plastic having antifriction additive with Glass fibre reinforcement. Should have a minimum lifting capacity of 8 lbs. Operating Chain: #10 steel ball chain adoptable to the clutch pitch for smooth lifting & lowering of blind. Locking Member : #12 steel stop locks for limit setting adoptable to the steel chain. Load Tube : 38 mm Extruded aluminium wall thickness :1.2 mm + / - 5%. Bonding ( Fabric > Tube ) : 15 mm wide double sided adhesive tape of 3M. SPRING BOOSTERS: All blinds above 2.4 mtr width or 3.36 mtr height and for total weight exceeding 4.0 kgs. Bottom Bar : aluminium extruded box section with powder coatecd finish matching the roller fabric -Min weight to be 365 gms / Lmr for a perfect fall of fabric to avoid warpage / floating.Instalattion to be insert type with end caps. Screens to be with 3% Openness. Fabric selection will be based on the approval of mock up (Vendor to do the mock up at site)"
A8: 1.2 | B8: Supply & Installation of motorised roller blinds as per approved style and shade | C8: BOARD ROOM, MD CABIN | D8: INR 485/SFT | E8: SQM | F8: 55 | G8: 5805.69 | H8: =IF(F8="QRO",0,(F8*$G8)) -> 319312.95 | I8: Basic Rate: INR 350/SFT
B9: Motorized Blinds blackout blind fabric as per site measurements spanning between mullions Operation: Tubular motorized system, smooth and silent operation Motor: Tubular motor with built-in limit switches, compatible with wall switch / remote control (BMS integration, if required, shall be paid separately) Control: Individual / group control via wall-mounted switch or remote, as specified Roller Tube: Extruded aluminium roller with adequate diameter as per blind width Supply & Installation of Silent Motors with 1 motor driving 2 blinds Maximum size 2.2 meter width and 3.36 meter height along with remote control Motor Specification : Silent motor 3/30 RTS For approved size of Blinds as per project specific requirements with Open/Close/Stop operation of Blinds from Remote or wireless Remote Or third party system , will fix on wooden palmate/ceiling/walls. Silent Blinds motor having voltage range of 230V – Frequency 50Hz, ,Radio Frequency 433.42M,Range 20 m with 2 reinforced concrete walls to be passed through, Nominal Torque (nm) 3 nm,RPM 30 rpm, Sound level (dBA) 42dBA, Maximum Current 0.9 A ,Adjustable Limits, Blind Maximum Weight capacity 10kg, 20kg ,it will cover upto 3 meter straight window, diameter of the motor should be 40 mm, Thermal Time 4 minutes Supply AC Index Protection Rating IP30 Limit Switch Unit Electronic Temperature Working Range 0ºC to +60ºC Electric Insulation Class. Having ultra powerfull,ultra flexible, ultra quiet. Control from Remote or Wireless wall mounted switch using frequency also Compatible with multiple technologies (WT/DCT/RTS/RS485) to meet the needs of smart buildings as recommended by the manufacturer for suitable above motor & warranty of the motors should be 5 years. 1 motor driving 1 blind Maximum size 2.5 meter width and 3.6 meter height.
B10: TOTAL FOR BLINDS | H10: =SUM(H3:H9) -> 906562.95

Sheet Planters
A1: SL NO | B1: ITEM DESCRIPTION | C1: BASIC RATE | D1: UNIT | E1: QTY | F1: RATE (INR) | G1: AMOUNT (INR) | H1: IMAGES | I1: REMARKS
A3: 1 | B3: Planters
B5: SPECIFICATIONS : Planters shall be made of high-quality Fibre Reinforced Plastic (FRP), molded to the required shape and size. The material shall be UV-resistant, durable, and corrosion-free, making it suitable for indoor and semi-outdoor use. The wall thickness shall be 4–5 mm to ensure rigidity and strength, and all surfaces must be smooth, even, and free from joints or defects. The exterior shall have a gel-coated finish in a matte or semi-gloss look, in the approved color, while the interior shall be coated with waterproof resin to prevent leakage or moisture damage. Planters shall be fabricated according to the approved design and dimensions, whether square, rectangular, cylindrical, or custom shapes, and each planter shall include a drainage hole with a plug or mesh. Planters shall be supplied empty unless otherwise specified, ready for planting. GI trays shall be provided beneath the planters to protect carpentry, flooring, or storage items. The rate shall include material, fabrication, finishing, delivery, placement, and the protective tray, complete in all respects.
A7: 1.1 | B7: FRP planter 1 Size: 300-450 dia x 900mm High. species : Schefflera arboricola Xanadu - Medium Dwarf Umbrella Tree. | C7: INR 2500/Unit | D7: NOS | E7: 30 | F7: 2924 | G7: =F7*E7 -> 87720 | I7: Half The Basic Rate: INR 1250/UNIT
A9: 1.2 | B9: FRP planter 2 Planter Size: 450 dia x 900-1050mm High. Plant Species : Schefflera arboricola Dwarf Umbrella Tree. | C9: INR 3500/Unit | D9: NOS | E9: 15 | F9: 4177 | G9: =F9*E9 -> 62655 | I9: Basic Rate: INR 1750/UNIT
A11: 1.3 | B11: Planter Material : Wonido Plant Pot Removable Plant Insert for Indoor and Outdoor Use Made of High-Quality Polypropylene. Size : Height 85 mm Diameter 38 mm Plant White Tulips (Cut Flowers) | C11: INR 4500/Unit | D11: NOS | E11: 15 | F11: 5222 | G11: =F11*E11 -> 78330 | I11: Basic Rate: INR 2250/UNIT
A13: 1.4 | B13: Planter Material : Wonido Plant Pot Removable Plant Insert for Indoor and Outdoor Use Made of High-Quality Polypropylene. Size : Height 55 cm Diameter 50 cm Matt White with Removable Plant Insert for Indoor and Outdoor Use Made of High-Quality Polypropylene. Plant: Lady Palm — Rhapis excelsa. Areca Palm (Dypsis lutescens) Ficus benjamina | C13: INR 4500/Unit | D13: NOS | E13: 15 | F13: 5222 | G13: =F13*E13 -> 78330 | I13: Basic Rate: INR 2250/UNIT
A15: 1.5 | B15: Planter Material : Wonido Plant Pot Removable Plant Insert for Indoor and Outdoor Use Made of High-Quality Polypropylene. Size : Height 75 cm Diameter 42 cm Matt White with Removable Plant Insert for Indoor and Outdoor Use Made of High-Quality Polypropylene. Plant: Dieffenbachia Green Magic Dieffenbachia Green Magic Philodendron Sellom (Medium) Heart Leaf Money Plant | C15: INR 3500/Unit | D15: NOS | E15: 12 | F15: 4178 | G15: =F15*E15 -> 50136 | I15: Basic Rate: INR 1750/UNIT
A17: 1.6 | B17: Planter Material : Wonido Plant Removable Plant Insert for Indoor and Outdoor Use Made of High-Quality Polypropylene. Size : Height 100MM Diameter 150MM HIGH Matt White with Removable Plant Insert for Indoor and Outdoor Use Made of High-Quality Polypropylene. Plant: Dieffenbachia Green Magic Teardrop Peperomia Varigated Turtle Vine (Callisia Repens) MONEY PLANT Marble Queen Philodendron Sellom | C17: INR 5000/Unit | D17: NOS | E17: 12 | F17: 5744 | G17: =F17*E17 -> 68928 | I17: Basic Rate: INR 2500/UNIT
B19: TOTAL FOR PLANTERS | G19: =SUM(G3:G18) -> 426099

Sheet Modular Furniture
A1: SL NO | B1: ITEM DESCRIPTION | C1: IMAGES | D1: BASIC RATE | E1: UNIT | F1: QTY | G1: RATE (INR) | H1: AMOUNT (INR) | I1: Remarks
A3: 1 | B3: Modular Furniture
A5: 1.01 | B5: Workstation Linear Sharing/Non sharing - 1500mm X 750mm | E5: NOS | F5: 38 | G5: 12619 | H5: =G5*F5 -> 479522
B6: Fabrication, Supply & Installation of the E1 Grade modular workstations with the following specifications Workstation of size - 1500mm (L) x 750mm (D) System - Desk based system Table top @ 750mm ht Table top made of 25mm thick Pre Laminated particleboard table top with ABS edge banding on all exposed edges. Above table top - Primary privacy screen Workstation to be provided with privacy screen - 300mm high above worksurface 30mm thick Independent fabric screen & to be fixed with necessary accessories as per manufacturer recommendation. Below table top - Modestry panel - Main screen Workstation to be provided with modestry panel - 450mm High & 20mm thick laminated panel of approved shared and fixed with necessary accessories as per details. Below table top - Modestry panel - Aisle side Workstation to be provided with aisle modestry panel - 450mm High & 20mm thick laminated panel of approved shared and fixed with necessary accessories as per details. Under Structure Table top to be supported with Metal powder coated loop legs (Color as approved by architect/client) and table top to be mounted on necessary metal powder coated beams as per manufacturers specs. Legs to have levellers at the bottom of legs as per architects / clients approval. Intermediate legs to have metal powder coated straight legs as per architect / clients approval. Table top to be mounted on necessary metal support beams as per manufacturers specs. Metal Raceways To comprise of two tier cable raceways with end cover for effective wire management (both for power & data), below the table top of height as per client requirement with vertical raceway (if any). The metal raceway cover is to be clip on type for easy access. The cover is to be provided with necessary cut-outs for electrical & data socket cable access. The raceway is to consist of necessary clipping mechanisms to fasten cables. Raceway to be provided as approved by architect/client. Flipup box Table top to be provided with soft close universal flip up box with brush on the table to access the cables fixed with gas lift mechanism as per details. Vertical junction box Supply & installation of metal vertical junction box for cable entry as per architects/clients approval Metal Signage : Name plates / holder Supply & installation of name plates / holder in each workstations as per clients approval. Cost to include grommet wherever required Pedestal for each Workstation -Size 400mm L x 450mm D x 635mm H Make: Featherlite, Monarch , AFC, Spacewood equivalent
A8: a | B8: Curve Workstation Sharing/Non sharing - 1500mm X 750mm | E8: NOS | F8: 4 | G8: 16971 | H8: =G8*F8 -> 67884
A9: b | B9: Workstation Linear Sharing/Non sharing - 1200mm X 600mm (Finance + HR) | E9: NOS | F9: 11 | G9: 8703 | H9: =G9*F9 -> 95733
A11: 1.02 | B11: Meeting tables
B12: Fabrication, Supply & Installation of meeting room tables as per details with table top formed of 25mm thk prelaminated table top with ABS edge banding & supported on Metal powder coated legs. Leg to legs are connected with connection beam for extra stability & reinforcement. Table legs to be provided with leveller adjustment to take care of floor undulation. Below table top to be provided with high density cable tray to house power and data cables with internal separation / divider for power and data as per details or as per architect's/client's approval. Table top to be provided with soft close universal flip up box with brush on the table to access the cables fixed with gas lift mechanism as per details. Make: Featherlite, Monarch , AFC, Spacewood equivalent
A13: a | B13: 4 Pax MR Table (1500mm x 1000mm x 750mm ) | E13: NOS | F13: 0 | G13: 20250 | H13: =G13*F13 -> 0
A14: b | B14: 6 Pax MR Table ( 2250mm x 1000mm X 750mm) | E14: NOS | F14: 2 | G14: 26544 | H14: =G14*F14 -> 53088
A15: c | B15: 8 Pax MR Table ( 3000mm x 1200mm X 750mm) | E15: NOS | F15: 1 | G15: 38293 | H15: =G15*F15 -> 38293
A17: 1.03 | B17: Cabin Table (HOD AND HR) | E17: NOS | F17: 4 | G17: 22193 | H17: =G17*F17 -> 88772
B18: Main table of size : 1400mm x 750mm Main table : Fabricating and fixing of Main table formed of 25mm thk prelaminated board. Table top to have ABS edge banding as per architects instructions. Table top to be supported MS powder coated loop legs. Table legs to be provided with leveller adjustment to take care of floor undulation. Also to have MS Powder coated modesty panel. To have soft close universal flip up box with brush for power & data access as per architects / clients approval. Side storage unit of size - 3200mm L X 500mm D X 750mm H Fabricating and fixing of Side storage unit as per details. To have counter top made of 25mm thk prelaminated table top. Table top to have ABS edge banding as per architects instructions. To have storage below finished in laminate. Storage to have adjustable shelves finished with laminate as per details. Storage to have shutters finish with laminate and to be fitted with necessary hardware's like handles, locks, hinges, tower bolts, magnetic catchers, finger pull profile etc., complete as per architects instructions. Non-Height Adjustable Type Make: Featherlite, Monarch , AFC, Spacewood equivalent
A20: 1.04 | B20: AV Rack Storage ( 3000mm X 600mm X 1200mm) | E20: NOS | F20: 1 | G20: 47867 | H20: =G20*F20 -> 47867
B21: Custom-made AV rack cabinet with MS/CRCA frame structure and perforated/solid panels, finished in powder coating, complete with adjustable rack mounting rails (19” standard), ventilation slots/fans, lockable front glass/metal door, and removable side panels, including provision for cable management, power distribution unit (PDU), and equipment mounting trays, with base supports/leveling feet; suitable for housing AV equipment like amplifiers, processors, and networking devices. Make: Custom
A23: 1.05 | B23: Repro Table 650mm Deep, 850mm High: Custome Made Table. | E23: NOS | F23: 2 | G23: 13925 | H23: =G23*F23 -> 27850
B24: Providing and fixing custom-made Repro Table of 650 mm depth and 850 mm height, fabricated with 19 mm thick plywood framework as per approved design and drawings. All exposed surfaces including tabletop shall be finished with 1.5 mm thick laminate of approved shade with PVC edge banding/moulding. The table shall include necessary cut-outs/provisions for electrical/data switches and sockets as required. Rate shall include all necessary hardware, supports, fittings, labour, materials, finishing, installation, and all incidentals required to complete the work as directed by the Architect/client.
A26: 1.06 | B26: Medium Height Storage With Planter Box - 1500mm X450mm X 1050mm
B27: TOP: 19MM Thick Prelaminated Particle Board with 2MM PVC edge band on all edges CARCASS (Body/ Shutter / Back) : 19 MM thick Prelaminated Particle Board with PVC edge band on all exposed edges. SHELF : One adjustable and One fixed shelf made of 18MM thick Prelaminated Particle Board with PVC edge band on all edges SHUTTERS : Lockable Swing shutters with Finger Groove HARDWARE : Hettich Hinges, Lock | E27: NOS | F27: 4 | G27: 19582 | H27: =G27*F27 -> 78328
A29: 1.07 | B29: Cafeteria Rectangular Table
B30: A rectangular cafeteria table with a Laminated HDHMR based tabletop and black powder-coated metal frame. Supported on sturdy square metal legs, the table provides ample seating space for group dining or collaborative setting. Complete with all materials, edge finishing, and installation as per design and specifications.
A31: a | B31: Type 01- 1200mm x 800mm x 750mm | D31: INR 10000 / UNIT | E31: NOS | F31: 17 | G31: 10879 | H31: =G31*F31 -> 184943 | I31: Basic Rate: INR 6000/UNIT
A32: b | B32: Type 02-1800mm x 800mm x 750mm | D32: INR 15000 / UNIT | E32: NOS | F32: 6 | G32: 16536 | H32: =G32*F32 -> 99216 | I32: Basic Rate: INR 9000/UNIT
A34: 1.8 | B34: Cafeteria Circular Table
B35: A rectangular cafeteria table with a Laminated HDHMR based tabletop and black powder-coated metal frame. Supported on sturdy square metal legs, the table provides ample seating space for group dining or collaborative setting. Complete with all materials, edge finishing, and installation as per design and specifications.
A36: a | B36: Type 01- 1200mm DIA x 750mm H | D36: INR 10000 / UNIT | E36: NOS | F36: 3 | G36: 11314 | H36: =G36*F36 -> 33942 | I36: Basic Rate: INR 6000/UNIT
A37: b | B37: Type 02-900mm DIA x 750mm H | D37: INR 7700 / UNIT | E37: NOS | F37: 4 | G37: 8485 | H37: =G37*F37 -> 33940 | I37: Basic Rate: INR 4620/UNIT
A38: C | B38: Type 03-800mm DIA x 750mm H | D38: INR 7000 / UNIT | E38: NOS | F38: 3 | G38: 7615 | H38: =G38*F38 -> 22845 | I38: Basic Rate: INR 9000/UNIT
A40: 1.9 | B40: Full Ht. Storage (1600mm L x 500mm D x 1800mm H) | E40: NOS | F40: 1 | G40: 42433 | H40: =G40*F40 -> 42433
B41: Fabricating and fixing of full ht. storage unit as per details. To have counter top made of 25mm thk prelaminated table top. Table top to have ABS edge banding as per architects instructions. To have storage below finished in laminate. Storage to have adjustable shelves finished with laminate as per details. Storage to have shutters finish with laminate and to be fitted with necessary hardware's like handles, locks, hinges, tower bolts, magnetic catchers, finger pull profile etc., complete as per architects instructions.
B43: TOTAL FOR MODULAR FURNITURE | H43: =SUM(H3:H42) -> 1394656

Sheet Carpet Flooring
A1: SL NO | B1: ITEM DESCRIPTION | C1: LOCATION | D1: BASIC RATE | E1: UNIT | F1: QTY | G1: RATE (INR) | H1: AMOUNT (INR) | I1: IMAGES | J1: REMARKS
A3: 1 | B3: Carpet
B5: Supply and Installation of Carpet as per selection. Commercial-grade, low-VOC (Volatile Organic Compounds), anti-static modular carpet tiles with a minimum AC4/Class 32 rating for high traffic areas.The carpet should be protected with 2 layers clear white polythene sheets immediately after laying. The carpet laying shall be done with manufacturers’ approved imported adhesive. Please note that the rate shall also be inclusive of one round of shampoo as per EIC instructions before handover to client.Carpet tiles make: Interface, Mohawk, Shaw. Pattern: As per Selection Yarn/ Fiber: NY 6 + Construction: Tufted Pattern/ textured Loop pile Tufting Gauge: 1/10 or 1/12 Pile Weight: 18.0 Oz + Primary Backing : PVC free underscore cushion Tile Size: 500X500mm / 600X600mm / 300X1200mm / 250x1000mm Carpet pattern/ Colour/ Shade to be strictly as per Client/ PM/ Architect approval. (Consider 5% attic stock within the mentioned quantity)
A6: 1.1 | B6: Carpet Type - 1 | C6: HoD Cabin 01, 02, 03 Workstations Meeting Rooms Collab REPRO HR Zone HR Cabin Finance Room | D6: INR 200 / SFT | E6: SQM | F6: 470 | G6: 2495 | H6: =IF(F6="QRO",0,(F6*$G6)) -> 1172650 | J6: Basic Rate: INR 120/SFT
A7: 1.2 | B7: Carpet Type - 2 | C7: Board Room MD CABIN | D7: INR 240 / SFT | E7: SQM | F7: 55 | G7: 2803.1049 | H7: =IF(F7="QRO",0,(F7*$G7)) -> 154170.77 | J7: Basic Rate: INR 140/SFT
B8: TOTAL FOR CARPET | H8: =SUM(H3:H7) -> 1326820.8

Sheet Loose Furniture & Chairs
A1: SL NO | B1: ITEM DESCRIPTION | C1: IMAGE | D1: BASIC RATE | E1: UNIT | F1: QTY | G1: RATE (INR) | H1: AMOUNT (INR) | I1: REMARKS
A3: 1 | B3: Table
B5: Top: 25mm thick pre-laminated particle board or MDF with 1mm HPL laminate in approved colour. All visible edges finished with 2mm PVC edge banding.Corners to be rounded for a smooth finish. Base / Legs: Metal frame made of MS pipe (40x20mm), powder coated in approved colour, or Solid wooden legs (teak or beech) with PU polish or laminate finish. Size: As mentioned in the BOQ Finish: Laminate top in approved shade; base powder-coated or PU-finished as per design. Hardware: SS screws and fittings with nylon glides below the legs to protect the floor. Approved Makes: Laminate: Greenlam / Merino / Century Board: Greenply / Action Tesa / Century | I5: Through out 60%
A6: 1.1 | B6: Reception Area - Round Center Table (600mm DIA x 450mm H) | D6: INR 24000 / UNIT | E6: Nos | F6: 2 | G6: 26109 | H6: =G6*F6 -> 52218 | I6: Basic Rate: INR 14400/UNIT
A7: 1.2 | B7: Collab Area side table (450mm DIA x 450mm H) | D7: INR 12500 / UNIT | E7: Nos | F7: 2 | G7: 13925 | H7: =G7*F7 -> 27850 | I7: Basic Rate: INR 7500/UNIT
A8: 1.3 | B8: MD Office Centre Table (600mm DIA x 450mm H) | D8: INR 20000 / UNIT | E8: Nos | F8: 1 | G8: 21755 | H8: =G8*F8 -> 21755 | I8: Basic Rate: INR 12000/UNIT
A9: 1.4 | B9: MD Office Centre Table (450mm DIA x 450mm H) | D9: INR 14500 / UNIT | E9: Nos | F9: 1 | G9: 15665 | H9: =G9*F9 -> 15665 | I9: Basic Rate: INR 8700/UNIT
A10: 1.5 | B10: Board Room Plug in Table (450mm DIA x 450mm H) | D10: INR 13000 / UNIT | E10: Nos | F10: 2 | G10: 13925 | H10: =G10*F10 -> 27850 | I10: Basic Rate: INR 7800/UNIT
G11: 0
A12: 2 | B12: Sofa and Lounge Chairs | G12: 0
G13: 0
B14: Free-standing upholstered sofa suitable for lounge or waiting areas. Frame: Made from seasoned hardwood and plywood framework for strength and durability. All joints to be glued, screwed, and reinforced for rigidity. Seat & Back: High-density foam cushions (40D for seat, 32D for back) upholstered with approved fabric or leatherette. Seat support with elastic webbing or nylon straps for added comfort. Upholstery: Fabric / Leatherette finish in approved shade and make. Legs / Base: MS powder-coated legs or wooden legs finished with PU polish, as per design intent. Non-slip rubber / nylon buffers to be provided at the base for floor protection. Dimensions: Single seater: 900W x 850D x 450SH x 750H (mm) Two seater: 1600W x 850D x 450SH x 750H (mm) Three seater: 2100W /2400x 850D x 450SH x 750H (mm) L shapes Sofa (To be finalized as per layout and design.) Finish: Upholstery fabric/leatherette: approved shade and texture. Legs/base: Powder-coated / PU finish in approved colour. | G14: 0
A15: 2.1 | B15: Reception - Armchairs | D15: INR 24000 / UNIT | E15: Nos | F15: 2 | G15: 26109 | H15: =G15*F15 -> 52218 | I15: Basic Rate: Lounge Chair (Off white) INR 7000/UNIT
A16: 2.2 | B16: Waiting Foyer Sofa- 3100 mm x 700 mm x 800 mm | D16: INR 60000 / UNIT | E16: Nos | F16: 1 | G16: 65273 | H16: =G16*F16 -> 65273 | I16: Basic Rate: INR 36000/UNIT
A17: 2.3 | B17: MD Office Curve Sofa (3400mm DIA x 1700mm L) | D17: INR 67500 / UNIT | E17: Nos | F17: 1 | G17: 73976 | H17: =G17*F17 -> 73976 | I17: Basic Rate: INR 40500/UNIT
A18: 2.4 | B18: MD Office Armchair | D18: INR 22500 / UNIT | E18: Nos | F18: 2 | G18: 24804 | H18: =G18*F18 -> 49608 | I18: Basic Rate: Lounge Chair (Orange) INR 12000/UNIT
A19: 2.5 | B19: Chair Cafeteria | D19: INR 2750 / UNIT | E19: Nos | F19: 143 | G19: 3046 | H19: =G19*F19 -> 435578 | I19: Basic Rate: Cafe chair (2 colours) INR 2000/UNIT
A20: 2.6 | B20: High Chair Cafeteria | D20: INR 6000 / UNIT | E20: Nos | F20: 65 | G20: 6527 | H20: =G20*F20 -> 424255 | I20: Basic Rate: Cafe high chairs INR 5500/UNIT
G21: 0
A22: 3 | B22: Chairs | G22: 0
G23: 0
B24: Type: Medium-back ergonomic office chair with mesh backrest and cushioned seat as per the 3D Image & sample approved by client. Structure: Heavy-duty nylon or fiber-reinforced frame with robust 5-star nylon base for enhanced stability and long-term durability. Recline Mechanism: Synchro-tilt mechanism with recline tension control knob, allowing the user to adjust reclining resistance as per comfort. Locking Function: Single-lock recline at 90° position for upright working posture. Swivel Function: 360° smooth swivel for easy mobility and multi-directional movement without shifting the chair base. Seat Material: High-density molded foam cushion with premium fabric upholstery ensuring breathability and long-lasting shape retention. Backrest: High-quality breathable mesh designed for ventilation, reducing heat build-up during prolonged sitting hours. Ergonomics: Contoured backrest with integrated lumbar support for spinal alignment and posture correction during extended use. Gas Lift: Class 4 certified pneumatic gas lift, tested for safety and performance, offering smooth height adjustment and supporting up to 150 kg. Base & Castors: Reinforced 5-legged nylon base with 50mm twin-wheel PU castors for noise-free, smooth rolling on hard and carpeted surfaces. Armrests: Fixed armrests with soft PU pads for forearm comfort. Finish: All plastic and metal parts finished in black/grey powder coat or moulded finish, by the architect/client. | G24: 0 | H24: =IF(F24="QRO",0,(F24*$G24)) -> 0
A25: 3.1 | B25: Reception | D25: INR 6750 / UNIT | E25: Nos | F25: 2 | G25: 7398 | H25: =F25*G25 -> 14796 | I25: Basic Rate: Reception Chair - INR 5000/UNIT
A26: 3.2 | B26: Workstations | D26: INR 7500 / UNIT | E26: Nos | F26: 42 | G26: 8268 | H26: =F26*G26 -> 347256 | I26: Basic Rate: WS Chairs INR 4500/UNIT
A27: 3.3 | B27: Meeting Room 4,6 Pax | D27: INR 7500 / UNIT | E27: Nos | F27: 20 | G27: 8268 | H27: =F27*G27 -> 165360 | I27: Basic Rate: INR 4500/UNIT
A28: 3.4 | B28: HR & FINANCE ZONE | D28: INR 7500 / UNIT | E28: Nos | F28: 11 | G28: 8268 | H28: =F28*G28 -> 90948 | I28: Basic Rate: INR 4500/UNIT
A29: 3.5 | B29: Board Room | D29: INR 9500 / UNIT | E29: Nos | F29: 18 | G29: 10444 | H29: =F29*G29 -> 187992 | I29: Basic Rate: Boardroom chair INR 10000/UNIT
A30: 3.6 | B30: HoD & HR Cabin Main chair | D30: INR 9500 / UNIT | E30: Nos | F30: 4 | G30: 10444 | H30: =F30*G30 -> 41776 | I30: Basic Rate: HOD Cabin main chair INR 8000/UNIT
A31: 3.7 | B31: HoD Cabin visitor chair - With Headrest | D31: INR 7500 / UNIT | E31: Nos | F31: 8 | G31: 8268 | H31: =F31*G31 -> 66144 | I31: Basic Rate: HOD Visitor chair INR 5000/UNIT
A32: 3.8 | B32: MD Cabin Main chair | D32: INR 14500 / UNIT | E32: Nos | F32: 1 | G32: 16101 | H32: =F32*G32 -> 16101 | I32: Basic Rate: MD Cabin - Main chair INR 12000/UNIT
A33: 3.9 | B33: MD Cabin Visitor chair | D33: INR 12000 / UNIT | E33: Nos | F33: 3 | G33: 13055 | H33: =F33*G33 -> 39165 | I33: Basic Rate: MD Cabin - Visitor chair INR 7000/UNIT
B36: TOTAL FOR LOOSE FURNITURE | H36: =SUM(H3:H35) -> 2215784

Sheet Dishwash Area
A1: SL NO | B1: ITEM DESCRIPTION | C1: IMAGE | D1: BASIC RATE | E1: UNIT | F1: QUANTITY | G1: RATE (INR) | H1: AMOUNT (INR) | I1: REMARKS
A3: 1 | B3: Soiled Dish Table with 3 Sink Pre-Wash Unit | D3: INR 40500/unit | E3: Nos. | F3: 1 | G3: 44919 | H3: =G3*F3 -> 44919 | I3: Basic Rate: INR 32400/UNIT
B4: The soiled dish table shall measure 3850 mm in width, 750 mm in depth, and 850 mm in height with an additional 150 mm splash. It shall have a 2.0 mm thick stainless steel (S.S.) top with all free sides turned up 75 mm and returned 40 mm for strength and hygiene. The unit will include three sink bowls, each fabricated from S.S. with radius corners and a lever-operated waste outlet. It shall be mounted on 38 mm × 38 mm × 1.6 mm thick S.S. legs with suitable cross-bracing and sound-deadening provisions. The table will be of custom-built make, and detailed shop drawings in plan, elevation, and section shall be approved prior to fabrication.
A6: 2 | B6: Cutlery Soak Sink | D6: INR 17500/unit | E6: Nos. | F6: 1 | G6: 19803 | H6: =G6*F6 -> 19803 | I6: Basic Rate: INR 14000/UNIT
B7: The cutlery soak sink shall be fabricated from 16-gauge S.S. 304 and shall measure 610 mm × 610 mm × 750 mm high. It will include a single sink bowl of 535 mm × 535 mm × 305 mm deep, with fully rounded internal corners for hygiene. The sink shall be provided with a 38 mm lever-operated waste outlet complete with a tailpipe and shall be mounted on S.S. square tube legs with full cross bracing and adjustable bullet feet. This unit shall be custom-built and supplied as per approved drawings.
A9: 3 | B9: Wall Mounted Pre-Rinse Unit | D9: INR 23500/unit | E9: Nos. | F9: 1 | G9: 25599 | H9: =G9*F9 -> 25599 | I9: Basic Rate: INR 18800/UNIT
B10: The wall-mounted pre-rinse unit shall be a spring-action wall-mounted model, complete with an 8-inch mixing faucet made of chrome-plated brass, a 18-inch riser, and a 44-inch stainless steel braided hose connected to a 1.42 GPM spray valve. The inlet connections shall be ½-inch NPT female, and the assembly shall comply with ASME, NSF, and EP Act 2005 standards. It shall be supplied with all necessary mounting brackets, finger hooks, and accessories for proper installation. The preferred make shall be T&S or Fisher – Model B-0133-ADF12-B or equivalent.
A12: 4 | B12: Dishwasher | E12: Nos. | F12: 1 | G12: 289800 | H12: =G12*F12 -> 289800
B13: Providing, supplying & installing Free-Standing Dishwasher of 14 place settings capacity, Model: SMS6IKI01 of Bosch or equivalent approved make, with EcoSilence Drive motor, Wi-Fi connectivity and anti-fingerprint brushed steel finish, complete in all respects as per approved specifications and site requirements.
A15: 5 | B15: Off-Loading Table | D15: INR 65500/unit | E15: Nos. | F15: 1 | G15: 72450 | H15: =G15*F15 -> 72450 | I15: Basic Rate: INR 52400/UNIT
B16: The off-loading table shall be fabricated from 2.0 mm thick S.S. 304 with a top measuring 1330 mm × 750 mm × 850 mm in height plus 150 mm backsplash. It shall have a full-length removable roller bed made of food-grade plastic rollers and a reinforced underframe of 25 × 100 × 25 × 2 mm S.S. channel. The table shall be supported on 38 mm square pipe legs with bullet feet for height adjustment. The equipment shall be custom fabricated, and drawings shall be submitted for approval before manufacture.
A18: 6 | B18: Clean Dish Rack | D18: INR 22000/unit | E18: Nos. | F18: 2 | G18: 24150 | H18: =G18*F18 -> 48300 | I18: Basic Rate: INR 17600/UNIT
B19: The clean dish rack shall measure 1100 mm in width, 550 mm in depth, and 1800 mm in height, fabricated entirely from S.S. 304. It shall have five adjustable shelves, each made from 1.2 mm thick S.S. sheets with turned-up edges on all sides for rigidity. The frame shall be constructed using 38 × 38 × 1.6 mm S.S. tubes mounted on heavy-duty castors to facilitate mobility. The unit shall be custom-built and fabricated in accordance with approved drawings.
A21: 7 | B21: Drain Box with Grating and Perforated Tray | D21: INR 23500/unit | E21: Nos. | F21: 1 | G21: 25599 | H21: =G21*F21 -> 25599 | I21: Basic Rate: INR 18800/UNIT
B22: The drain box shall measure 550 mm × 550 mm × 75/150 mm deep and shall be constructed entirely from S.S. 304. It shall be provided with a pressure-locked grating, a removable perforated strainer tray with a stainless steel rod handle, and an integrated foul air trap and silt basket. The complete assembly shall be designed to ensure smooth drainage and hygiene. Samples shall be submitted and approved prior to final fabrication. The unit shall be custom-built.
A24: 8 | B24: Hose Reel Assembly | D24: INR 25000/unit | E24: Nos. | F24: 1 | G24: 28014 | H24: =G24*F24 -> 28014 | I24: Basic Rate: INR 20000/UNIT
B25: The hose reel shall measure approximately 230 mm × 538 mm × 498 mm and shall comprise a stainless-steel hose reel rack, braided steel hose, and brass nozzle with an integrated cast bronze mixing valve. The reel shall withstand up to 300 PSI pressure and be supplied with a wall-mounting swing bracket for convenient operation. The model shall be T&S 5HR-242-01 with G019430-45 bracket or equivalent.
A27: 9 | B27: Insect Killer | D27: INR 6000/unit | E27: Nos. | F27: 1 | G27: 7245 | H27: =G27*F27 -> 7245 | I27: Basic Rate: INR 4800/UNIT
B28: The insect killer shall be a wall or ceiling-mounted twin-tube electric fly trap, measuring 528 mm × 128 mm × 344 mm, designed for use in commercial kitchens. It shall be fitted with replaceable glue boards and a plastic-coated mild steel safety guard. The unit shall be supplied complete with a power cord, mounting accessories, and fixtures. The make shall be PCIL / Mid Link – Spider Electric Fly Catcher (Wall Mounted) or equivalent.
A30: 10 | B30: Drain Box with Grating and Perforated Tray | D30: INR 20500/unit | E30: Nos. | F30: 1 | G30: 21735 | H30: =G30*F30 -> 21735 | I30: Basic Rate: INR 16400/UNIT
B31: Size: 1200 (W) × 350 (D) × 75/150 (H) mm Specification: Fabricated entirely from S.S. 304, with a 38 × 4 mm bearing-bar framework and 32 × 4 mm cross members, pressure-locked and welded to a 1.6 mm thick, 70 mm-deep S.S. trough sloped towards the floor drain. Provided with a 100 mm dia. cut-out and integral flange, 100 × 100 × 2 mm plate, and a full-size perforated strainer tray (1.6 mm S.S.) with rod handle. Accessories: Foul Air Trap (FAT) and Silt Basket. MEP: Waste outlet – 100 mm Ø; no hot/cold/gas/electric requirement. Special Note: Shop drawing (plan/elevation/section) and sample to be submitted for consultant approval prior to fabrication. Make/Model: Custom Built.
A33: 11 | B33: Air Curtain | D33: INR 15000/unit | E33: Nos. | F33: 1 | G33: 16905 | H33: =G33*F33 -> 16905 | I33: Basic Rate: INR 12000/UNIT
B34: The air curtain shall measure 1800 mm × 255 mm × 255 mm and shall be constructed from stainless steel and aluminum. It shall include a remote or automatic control system with a door sensor and three-speed operation (low, medium, and high). The air velocity shall be 18 meters per second, ensuring effective air separation at entry points. The preferred make shall be Mitzvah Engineering Inc. / Euronics – Model EAS 4 or equivalent.
A36: 12 | B36: Garbage Bin | D36: INR 4500/unit | E36: Nos. | F36: 2 | G36: 5313 | H36: =G36*F36 -> 10626 | I36: Basic Rate: INR 3600/UNIT
B37: The garbage bin shall measure 420 mm × 585 mm × 790 mm and be constructed from high-quality polyethylene, resistant to rust, dents, and chips. It shall feature a heavy-duty foot pedal-operated lid, an overlapping cover for odor control, and two heavy-duty rear wheels for mobility. The preferred make shall be Frontier – FLB-ROL 70 / Nilkamal – GMWBFC68BASE + Wheels or equivalent.
A39: 13 | B39: Vapour Hood | D39: INR 50000/unit | E39: Nos. | F39: 1 | G39: 55545 | H39: =G39*F39 -> 55545 | I39: Basic Rate: INR 40000/UNIT
B40: Providing, supplying and installing Vapour Hood of size 900 mm x 900 mm x 450 mm, manufactured by JEW Innovative or approved equivalent, complete with SS304 construction, grease filters, vapour extraction system, concealed supports, necessary accessories, electrical connections and all fittings required for complete installation, testing and commissioning as per approved drawings and manufacturer's specifications.
H42: =SUM(H3:H41) -> 666540

Sheet Kitchen Equipments
A1: SL NO | B1: ITEM DESCRIPTION | C1: LOCATION | D1: IMAGE | E1: BASIC RATE | F1: UNIT | G1: QUANTITY | H1: RATE (INR) | I1: AMOUNT (INR) | J1: REMARKS
A3: 1 | B3: Bain-Marie Counter | C3: CAFETERIA
B4: Providing, supplying and installing a stainless steel Bain-Marie counter complete with SS304 grade construction, insulated hot food wells, GN pan accommodation, electric heating system with temperature controls, under-counter storage, adjustable levelling feet, electrical connections, necessary accessories, testing and commissioning, complete as per approved design and manufacturer's specifications.
A5: a | B5: 850 mm (H) x 800 mm (D) x 2100 mm (L) | E5: INR 95000/UNIT | F5: NOS | G5: 2 | H5: 106260 | I5: =H5*G5 -> 212520 | J5: Basic Rate: INR 76000/UNIT
A7: 2 | B7: Water Dispenser/ RO unit | C7: CAFETERIA
B8: Providing and fixing water dispenser unit of 1800mm high 900mm wide 600mm deep, fabricated out of 19mm thk BWP ply with 1.5mm thk approved laminate from outside and 1mm liner matcing laminate on the inside. Unit to be made in combination of closed shutters & open shelves as per design/dwg. All exposed edges to be finshed with 2mm thk PVC edge banding as per edge detail.Hardware- Lock sets, self-closing hinges, spring loaded shutter latch inside, all cabinet hardware to be kich / dorset or equivalent, complete as per architect's approval. Also include full ht storage for bubble top dispenser with cutout at desired ht.
A9: a | B9: Size of 1100mm X 680mm D X 1800mm H | E9: INR 105000/UNIT | F9: NOS | G9: 1 | H9: 120750 | I9: =H9*G9 -> 120750 | J9: Basic Rate: INR 84000/UNIT
A10: b | B10: Size of 900mm X 600mm D X 1800mm H | E10: INR 90000/UNIT | F10: NOS | G10: 2 | H10: 96600 | I10: =H10*G10 -> 193200 | J10: Basic Rate: INR 72000/UNIT
A12: 3 | B12: Hot Plate | C12: CAFETERIA
B13: Providing, supplying and installing a stainless steel electric hot plate of size 1200 mm (L) x 750 mm (D) x 850+150 mm (H), fabricated in SS304 grade with heavy-duty flat heating surface, thermostatic temperature controls, insulated body, splash back, adjustable levelling feet, electrical connections, control panel, necessary accessories, testing and commissioning, complete as per approved design and manufacturer's specifications. | E13: INR 60000/UNIT | F13: NOS | G13: 2 | H13: 67620 | I13: =H13*G13 -> 135240 | J13: Basic Rate: INR 48000/UNIT
A15: 4 | B15: S.S. Twin Basket Deep Fat Fryer | C15: CAFETERIA | E15: INR 105000/UNIT | F15: NOS | G15: 1 | H15: 120750 | I15: =H15*G15 -> 120750 | J15: Basic Rate: INR 84000/UNIT
B16: Providing, supplying and installing a heavy-duty stainless steel twin basket deep fat fryer of size 600 mm (L) x 600 mm (D) x 850+150 mm (H), fabricated in SS304 grade construction, complete with dual frying baskets, oil tank, thermostatic temperature controls, insulated body, drain valve, splash back, adjustable levelling feet, control panel, electrical connections, all necessary accessories, testing and commissioning, complete as per approved drawings and manufacturer's specifications. Make: JEW Innovative or approved equivalent.
A18: 5 | B18: Exhaust Hood | C18: CAFETERIA | E18: INR 105000/UNIT | F18: NOS | G18: 1 | H18: 120750 | I18: =H18*G18 -> 120750 | J18: Basic Rate: INR 84000/UNIT
B19: Providing, supplying and installing a custom-made kitchen exhaust hood of size 5100 mm x 2300 mm, fabricated from SS304 stainless steel (minimum 1.2 mm thick), complete with baffle grease filters, grease collection tray, drain arrangement, integrated LED light provision, hanging supports, suspension system, all necessary brackets, fasteners and accessories required for complete installation. The hood shall be suitable for commercial kitchen applications and shall be connected to the exhaust system as per approved drawings and manufacturer's specifications, complete in all respects.
B21: TOTAL FOR KITCHEN EQUIPMENTS & OTHERS | I21: =sum(I5:I19) -> 903210

Sheet Electrical Works
A1: SL NO | B1: ITEM DESCRIPTION | C1: UNIT | D1: QTY | E1: RATE (INR) | G1: Amount (INR)
E2: SUPPLY | F2: INSTALLATION | G2: SUPPLY | H2: INSTALLATION | I2: TOTAL
A4: 1 | B4: LT PANELS :
A6: 1.1 | B6: Supply, Installation, Testing, Commissioning of MAIN L.T & HVAC PANEL - MCCB INCOMER AND MCCB / MCB OUTGOING. with fire suppression systems | C6: NOS | D6: 1 | E6: 488936 | F6: 48350 | G6: =N(D6)*N(E6) -> 488936 | H6: =N(D6)*N(F6) -> 48350 | I6: =G6+H6 -> 537286
A8: 1.2 | B8: Supply, Installation, Testing, Commissioning of UPS POWER O/P PANEL - with fire suppression systems | C8: NOS | D8: 1 | E8: 426447 | F8: 38680 | G8: =N(D8)*N(E8) -> 426447 | H8: =N(D8)*N(F8) -> 38680 | I8: =G8+H8 -> 465127
B11: Total for LT Panels | G11: =SUM(G5:G10) -> 915383 | H11: =SUM(H5:H10) -> 87030 | I11: =SUM(I5:I10) -> 1002413
A13: 2 | B13: LT CABLES & ENDTERMINATIONS
B15: Supply, Laying, Testing and Commissioning of stranded XLPE/PVC insulated, Armoured / Unarmoured / Flexible, Aluminum / Copper conductor, laid in tray / hume pipe / in ready made trenches, with nylon cable ties / MS Clamps @ 600mm interval etc., as required. The cost of the nylon tie and overlapping GI strip shall be included in the cost of installation.
B16: Supply, Installation, Testing and Commissioning of Compression type cable gland, aluminum lugs for aluminum cables / copper lugs for copper cables, insulation tape, anti corrosive paste, brass clamps for gland earthing with 14 SWG copper wire to connect to nearest earth flat.
B17: Insulation: XLPE above 25Sqmm and Class A PVC below 25Sqmm
B18: Inner sheath: Extruded PVC only for Multicore
B19: Outer sheath: Extruded Type ST2 PVC with FLAME RETARDANT
B20: Voltage grade:1100Volts
B21: Armoure: Galvanized Steel strip/Wire for multicore
B22: Non Magnetic Aluminum Wire/Strip for Single core
B23: Gland type : Brass with nickel plated
B24: Compression : Double compression above 35 Sq.mm
B25: Sealing Ring : Natural rubber for indoor, Neoprene for Outdoor
B26: Bimetallic lugs to be used
B27: Gland earthing to be included as part of LT panel cable end terimations
A29: 2.1 | B29: XLPE / PVC insulated, steel armoured, aluminum conductor 3.5 Core and 4 core cables.
A31: a | B31: 3.5 Core X 300 Sqmm | C31: MTS | E31: 1350 | F31: 300 | G31: =N(D31)*N(E31) -> 0 | H31: =N(D31)*N(F31) -> 0 | I31: =G31+H31 -> 0
B32: End terminations | C32: NOS | E32: 1980 | F32: 400 | G32: =N(D32)*N(E32) -> 0 | H32: =N(D32)*N(F32) -> 0 | I32: =G32+H32 -> 0
A34: b | B34: 3.5 Core X 150 Sqmm | C34: MTS | E34: 1089 | F34: 300 | G34: =N(D34)*N(E34) -> 0 | H34: =N(D34)*N(F34) -> 0 | I34: =G34+H34 -> 0
B35: End terminations | C35: NOS | E35: 1733 | F35: 400 | G35: =N(D35)*N(E35) -> 0 | H35: =N(D35)*N(F35) -> 0 | I35: =G35+H35 -> 0
A37: c | B37: 3.5 Core X 95 Sqmm | C37: MTS | E37: 891 | F37: 200 | G37: =N(D37)*N(E37) -> 0 | H37: =N(D37)*N(F37) -> 0 | I37: =G37+H37 -> 0
B38: End terminations | C38: NOS | E38: 1089 | F38: 300 | G38: =N(D38)*N(E38) -> 0 | H38: =N(D38)*N(F38) -> 0 | I38: =G38+H38 -> 0
A40: d | B40: 4 Core X 70 Sqmm | C40: MTS | D40: 18 | E40: 740 | F40: 193 | G40: =N(D40)*N(E40) -> 13320 | H40: =N(D40)*N(F40) -> 3474 | I40: =G40+H40 -> 16794
B41: End terminations | C41: NOS | D41: 2 | E41: 862 | F41: 193 | G41: =N(D41)*N(E41) -> 1724 | H41: =N(D41)*N(F41) -> 386 | I41: =G41+H41 -> 2110
A43: e | B43: 4 Core X 25 Sqmm | C43: MTS | D43: RO | E43: 297 | F43: 200 | G43: =N(D43)*N(E43) -> 0 | H43: =N(D43)*N(F43) -> 0 | I43: =G43+H43 -> 0
B44: End terminations | C44: NOS | D44: RO | E44: 693 | F44: 200 | G44: =N(D44)*N(E44) -> 0 | H44: =N(D44)*N(F44) -> 0 | I44: =G44+H44 -> 0
A46: f | B46: 4 Core X 16 Sqmm | C46: MTS | D46: 90 | E46: 261 | F46: 193 | G46: =N(D46)*N(E46) -> 23490 | H46: =N(D46)*N(F46) -> 17370 | I46: =G46+H46 -> 40860
B47: End terminations | C47: NOS | D47: 6 | E47: 623 | F47: 193 | G47: =N(D47)*N(E47) -> 3738 | H47: =N(D47)*N(F47) -> 1158 | I47: =G47+H47 -> 4896
A49: g | B49: 4 Core X 10 Sqmm | C49: MTS | D49: 322 | E49: 214 | F49: 145 | G49: =N(D49)*N(E49) -> 68908 | H49: =N(D49)*N(F49) -> 46690 | I49: =G49+H49 -> 115598
B50: End terminations | C50: NOS | D50: 24 | E50: 479 | F50: 193 | G50: =N(D50)*N(E50) -> 11496 | H50: =N(D50)*N(F50) -> 4632 | I50: =G50+H50 -> 16128
A52: h | B52: 4 Core X 6 Sqmm | C52: MTS | D52: 90 | E52: 218 | F52: 145 | G52: =N(D52)*N(E52) -> 19620 | H52: =N(D52)*N(F52) -> 13050 | I52: =G52+H52 -> 32670
B53: End terminations | C53: NOS | D53: 6 | E53: 479 | F53: 193 | G53: =N(D53)*N(E53) -> 2874 | H53: =N(D53)*N(F53) -> 1158 | I53: =G53+H53 -> 4032
A55: i | B55: 4 Core X 4 Sqmm | C55: MTS | D55: 106 | E55: 191 | F55: 145 | G55: =N(D55)*N(E55) -> 20246 | H55: =N(D55)*N(F55) -> 15370 | I55: =G55+H55 -> 35616
B56: End terminations | C56: NOS | D56: 12 | E56: 479 | F56: 193 | G56: =N(D56)*N(E56) -> 5748 | H56: =N(D56)*N(F56) -> 2316 | I56: =G56+H56 -> 8064
A58: 2.2 | B58: PVC insulated, sheathed, unarmoured, flexible copper conductor cables - single Core - for end connection in grounding.
A60: a | B60: 1 Core x 70 Sq. mm | C60: MTS | E60: 1643 | F60: 100 | G60: =N(D60)*N(E60) -> 0 | H60: =N(D60)*N(F60) -> 0 | I60: =G60+H60 -> 0
B61: End terminations | C61: NOS | E61: 747 | F61: 100 | G61: =N(D61)*N(E61) -> 0 | H61: =N(D61)*N(F61) -> 0 | I61: =G61+H61 -> 0
A63: b | B63: 1 Core x 16 Sq. mm | C63: MTS | E63: 767 | F63: 100 | G63: =N(D63)*N(E63) -> 0 | H63: =N(D63)*N(F63) -> 0 | I63: =G63+H63 -> 0
B64: End terminations | C64: NOS | E64: 297 | F64: 100 | G64: =N(D64)*N(E64) -> 0 | H64: =N(D64)*N(F64) -> 0 | I64: =G64+H64 -> 0
A66: c | B66: 1 Core x 10 Sq. mm | C66: MTS | D66: 90 | E66: 320 | F66: 97 | G66: =N(D66)*N(E66) -> 28800 | H66: =N(D66)*N(F66) -> 8730 | I66: =G66+H66 -> 37530
B67: End terminations | C67: NOS | D67: 12 | E67: 287 | F67: 97 | G67: =N(D67)*N(E67) -> 3444 | H67: =N(D67)*N(F67) -> 1164 | I67: =G67+H67 -> 4608
A69: d | B69: 1 Core x 6 Sq. mm | C69: MTS | D69: 18 | E69: 278 | F69: 97 | G69: =N(D69)*N(E69) -> 5004 | H69: =N(D69)*N(F69) -> 1746 | I69: =G69+H69 -> 6750
B70: End terminations | C70: NOS | D70: 2 | E70: 218 | F70: 97 | G70: =N(D70)*N(E70) -> 436 | H70: =N(D70)*N(F70) -> 194 | I70: =G70+H70 -> 630
A72: e | B72: 1 Core x 4 Sq. mm | C72: MTS | D72: 36 | E72: 209 | F72: 97 | G72: =N(D72)*N(E72) -> 7524 | H72: =N(D72)*N(F72) -> 3492 | I72: =G72+H72 -> 11016
B73: End terminations | C73: NOS | D73: 2 | E73: 165 | F73: 97 | G73: =N(D73)*N(E73) -> 330 | H73: =N(D73)*N(F73) -> 194 | I73: =G73+H73 -> 524
A75: f | B75: 1 Core x 2.5 Sq. mm | C75: MTS | D75: 150 | E75: 174 | F75: 97 | G75: =N(D75)*N(E75) -> 26100 | H75: =N(D75)*N(F75) -> 14550 | I75: =G75+H75 -> 40650
B76: End terminations | C76: NOS | D76: 16 | E76: 139 | F76: 97 | G76: =N(D76)*N(E76) -> 2224 | H76: =N(D76)*N(F76) -> 1552 | I76: =G76+H76 -> 3776
A78: g | B78: 1 Core x 1.5 Sq. mm | C78: MTS | D78: 90 | E78: 104 | F78: 97 | G78: =N(D78)*N(E78) -> 9360 | H78: =N(D78)*N(F78) -> 8730 | I78: =G78+H78 -> 18090
B79: End terminations | C79: NOS | D79: 8 | E79: 104 | F79: 97 | G79: =N(D79)*N(E79) -> 832 | H79: =N(D79)*N(F79) -> 776 | I79: =G79+H79 -> 1608
A82: 2.3 | B82: PVC Insulated & Steel Armoured Copper Conductor cables (YFY Type)
A84: a | B84: 3 Core x 16 Sq. mm | C84: MTS | D84: RO | E84: 441 | F84: 200 | G84: =N(D84)*N(E84) -> 0 | H84: =N(D84)*N(F84) -> 0 | I84: =G84+H84 -> 0
B85: End terminations | C85: NOS | D85: RO | E85: 495 | F85: 100 | G85: =N(D85)*N(E85) -> 0 | H85: =N(D85)*N(F85) -> 0 | I85: =G85+H85 -> 0
A87: b | B87: 3 Core x 10 Sq. mm | C87: MTS | D87: RO | E87: 315 | F87: 200 | G87: =N(D87)*N(E87) -> 0 | H87: =N(D87)*N(F87) -> 0 | I87: =G87+H87 -> 0
B88: End terminations | C88: NOS | D88: RO | E88: 495 | F88: 100 | G88: =N(D88)*N(E88) -> 0 | H88: =N(D88)*N(F88) -> 0 | I88: =G88+H88 -> 0
A90: c | B90: 3 Core x 6 Sq. mm | C90: MTS | D90: 214 | E90: 196 | F90: 193 | G90: =N(D90)*N(E90) -> 41944 | H90: =N(D90)*N(F90) -> 41302 | I90: =G90+H90 -> 83246
B91: End terminations | C91: NOS | D91: 12 | E91: 383 | F91: 97 | G91: =N(D91)*N(E91) -> 4596 | H91: =N(D91)*N(F91) -> 1164 | I91: =G91+H91 -> 5760
A93: d | B93: 3 Core x 4 Sq. mm | C93: MTS | D93: 78 | E93: 188 | F93: 193 | G93: =N(D93)*N(E93) -> 14664 | H93: =N(D93)*N(F93) -> 15054 | I93: =G93+H93 -> 29718
B94: End terminations | C94: NOS | D94: 8 | E94: 287 | F94: 97 | G94: =N(D94)*N(E94) -> 2296 | H94: =N(D94)*N(F94) -> 776 | I94: =G94+H94 -> 3072
A96: e | B96: 3 Core x 2.5 Sq. mm | C96: MTS | D96: 108 | E96: 131 | F96: 193 | G96: =N(D96)*N(E96) -> 14148 | H96: =N(D96)*N(F96) -> 20844 | I96: =G96+H96 -> 34992
B97: End terminations | C97: NOS | D97: 8 | E97: 287 | F97: 97 | G97: =N(D97)*N(E97) -> 2296 | H97: =N(D97)*N(F97) -> 776 | I97: =G97+H97 -> 3072
A99: f | B99: 4 Core x 16 Sq. mm | C99: MTS | D99: RO | E99: 810 | F99: 200 | G99: =N(D99)*N(E99) -> 0 | H99: =N(D99)*N(F99) -> 0 | I99: =G99+H99 -> 0
B100: End terminations | C100: NOS | D100: RO | E100: 297 | F100: 100 | G100: =N(D100)*N(E100) -> 0 | H100: =N(D100)*N(F100) -> 0 | I100: =G100+H100 -> 0
A102: g | B102: 4 Core x 10 Sq. mm | C102: MTS | D102: 24 | E102: 566 | F102: 193 | G102: =N(D102)*N(E102) -> 13584 | H102: =N(D102)*N(F102) -> 4632 | I102: =G102+H102 -> 18216
B103: End terminations | C103: NOS | D103: 4 | E103: 287 | F103: 97 | G103: =N(D103)*N(E103) -> 1148 | H103: =N(D103)*N(F103) -> 388 | I103: =G103+H103 -> 1536
A105: h | B105: 4 Core x 6 Sq. mm | C105: MTS | D105: 30 | E105: 392 | F105: 193 | G105: =N(D105)*N(E105) -> 11760 | H105: =N(D105)*N(F105) -> 5790 | I105: =G105+H105 -> 17550
B106: End terminations | C106: NOS | D106: 2 | E106: 287 | F106: 97 | G106: =N(D106)*N(E106) -> 574 | H106: =N(D106)*N(F106) -> 194 | I106: =G106+H106 -> 768
A108: i | B108: 4 Core x 4 Sq. mm | C108: MTS | D108: 75 | E108: 305 | F108: 193 | G108: =N(D108)*N(E108) -> 22875 | H108: =N(D108)*N(F108) -> 14475 | I108: =G108+H108 -> 37350
B109: End terminations | C109: NOS | D109: 2 | E109: 287 | F109: 97 | G109: =N(D109)*N(E109) -> 574 | H109: =N(D109)*N(F109) -> 194 | I109: =G109+H109 -> 768
A112: 2.4 | B112: Control Cables
B114: SITC of 11000 M.S insulated sheathed and screened Fire Retarded Low Smoke (FRLS) control cables with copper conductors generally as specified and shown on drgs. and same as for power cables.
A115: a | B115: 2C x 1.5 smm | C115: MTS | D115: 30 | E115: 131 | F115: 29 | G115: =N(D115)*N(E115) -> 3930 | H115: =N(D115)*N(F115) -> 870 | I115: =G115+H115 -> 4800
A117: 2.5 | B117: MATV System
A118: a | B118: SITC pulling of RG-6 coaxial cable, centre copper conductor with foam Shielded jelly filed (Make - Comscope ) pulling through 20mm M.S pipes including all conduit accessories like JBs pull boxes bends fish wire etc as directed by the engineer incharge . | C118: MTS | D118: 72 | E118: 104 | F118: 39 | G118: =N(D118)*N(E118) -> 7488 | H118: =N(D118)*N(F118) -> 2808 | I118: =G118+H118 -> 10296
A120: b | B120: SITC of RG-11 coaxial cable , centre copper conductor with foam Shielded jelly filed (Make - Comscope ) pulling through 20mm M.S pipes as directed by the engineer incharge . | C120: MTS | D120: 36 | E120: 218 | F120: 39 | G120: =N(D120)*N(E120) -> 7848 | H120: =N(D120)*N(F120) -> 1404 | I120: =G120+H120 -> 9252
A122: c | B122: SITC of 2 way splitter proper fixture inside and earthing screw provision.splitters in die cast Alum. casing.( Make - Diamond/Triax) with required Baloon Pins ( Shall be provided with Switch (Amplifier )(Note:Splitter should be 2100 to 2400 mHZ) | C122: NOS | D122: 4 | E122: 870 | F122: 193 | G122: =N(D122)*N(E122) -> 3480 | H122: =N(D122)*N(F122) -> 772 | I122: =G122+H122 -> 4252
A124: d | B124: SITC of 1 way splitter proper fixture inside and earthing screw provision.splitters in die cast Alum. casing.( Make - Diamond/Triax) with required Baloon Pins ( Shall be provided with Switch (Amplifier ) | C124: NOS | D124: 4 | E124: 653 | F124: 145 | G124: =N(D124)*N(E124) -> 2612 | H124: =N(D124)*N(F124) -> 580 | I124: =G124+H124 -> 3192
A126: e | B126: RG11 F2F connector | C126: NOS | D126: 8 | E126: 131 | F126: 29 | G126: =N(D126)*N(E126) -> 1048 | H126: =N(D126)*N(F126) -> 232 | I126: =G126+H126 -> 1280
A127: f | B127: RG06 F2F connector | C127: NOS | D127: 8 | E127: 78 | F127: 29 | G127: =N(D127)*N(E127) -> 624 | H127: =N(D127)*N(F127) -> 232 | I127: =G127+H127 -> 856
B129: Total for LT Cables and End terminations | G129: =SUM(G13:G128) -> 412707 | H129: =SUM(H13:H128) -> 259219 | I129: =SUM(I13:I128) -> 671926
A131: 3 | B131: MCB DISTRIBUTION BOARDS (DB)
B133: Supply, Installation, Testing and Commissioning of MCB Distribution board as per approved installation dwgs.
B134: Wall mounted MCB DBs with MS wire way box on top / bottom & on sides. MCBs shall be rated for 10kA with current limiting feature. Dummy ways to be covered with blank plates. All out going ways shall be labelled & laminated.
B135: Enclosure:1.2mm CRCA Sheet Steel, Powder Coated
B136: Door : Double Door
B137: Protection : IP 42
B138: Cable Entry : Top & Bottom
B139: For UPS distribution RCBO's shall be harmonic resistant (SI Series)
B140: Bus bar : Shall be tinned Copper and 200% rating for UPS DB Neutral Link
B141: MCB's : 10kA 'C' Curve for Lighting & Raw power, 10kA 'D' Curve for UPS Distribution
B142: Note:
B143: 1) Separate Earth bus/Neutral bus for each phase
B144: 2) Each Circuit shall have yellow ferrules with circuit number.
... B149: 7) For all DB's Ground and neutral bus bar to have insulator and DB should consist busbar box where from earthpit cable will be connected and distributed to all the DB's
A151: 3.1 | B151: Lighting /RawPower DBS | C151: NOS | D151: 1 | E151: 28720 | F151: 4835 | G151: =N(D151)*N(E151) -> 28720 | H151: =N(D151)*N(F151) -> 4835 | I151: =G151+H151 -> 33555
B152: FLOOR RAW POWER DB
...

Sheet Light Fixtures
A1: SL NO | B1: ITEM DESCRIPTION | C1: LOCATION | D1: IMAGE | E1: BASIC RATE | F1: UNIT | G1: QTY | H1: RATE (INR) | I1: AMOUNT (INR) | J1: REMARKS
A4: 1 | B4: DECORATIVE LIGHTS
B6: Supply, Installation, Testing and Commissioning of Light fixtures and lamps with all accessories, fixing on the wall / ceiling/false ceiling with wooden blocks, screws ,hardware's ,suspended chain hooks as required as per the site conditions (including the earthing of fixture) "Note : All light fixtures should have CRI < 80, luminaire System efficacy of >110 lm/watt, PF >0.95, CCT 5000K, Anti glare diffuser. It is proposed to achieve USGBC LEED Gold Certification for this Project. Vendor to go through the LEED documents & comply to the requirement in reference to this BOQ & Specification. "Fittings: Kohler/Bajaj/Crompton/Wipro/Havells
A7: =A4+0.1 -> 1.1 | B7: Decorative Hanging Light Type 01 | C7: CAFETERIA | E7: INR 4250 / UNIT | F7: NOS | G7: 75 | H7: 4777 | I7: =N(H7)*N(G7) -> 358275 | J7: Basic Rate: INR 2550/UNIT
A8: =A7+0.1 -> 1.2 | B8: Decorative Track light | C8: DISPLAY AREA | E8: INR 5500 / UNIT | F8: NOS | G8: 6 | H8: 6431 | I8: =N(H8)*N(G8) -> 38586 | J8: Basic Rate: INR 3300/UNIT
A9: =A8+0.1 -> 1.3 | B9: DECORATIVE LIGHT - BOARDROOM Custom embedded profile light , size – 4500 x 50 mm. | C9: BOARDROOM | E9: INR 47500 / UNIT | F9: NOS | G9: 2 | H9: 55256 | I9: =N(H9)*N(G9) -> 110512 | J9: Basic Rate: Profile Light - 1200/rmt or 350/rft
A10: =A9+0.1 -> 1.4 | B10: DECORATIVE LIGHT - MD CABIN Linear Decorative light with Metal Body - 1500 mm Length | C10: MD Cabin, HOD, HR | E10: INR 22000 / UNIT | F10: NOS | G10: 5 | H10: 25263 | I10: =N(H10)*N(G10) -> 126315 | J10: Basic Rate: Linear Light - 1200/rmt or 350/rft
A11: 2 | B11: STANDARD LIGHT FIXTURES
A15: 2.3 | B15: Recessed Mounted 2’x2’ LED Panel
B16: Supply of recessed mounted 2X2 LED panel ,made of CRCA housing with high efficiency PS Diffuser. LED Used shall be SMD type and fixture should have minimum efficacy at System level >=100 lumens/watt with Minimum system Lumens 3600 & Max , Life of fixture : 50000 burning Hrs. @ L70B50 Lumen maintenance,CCT-4000K/5700K/6500K, (SDCM<=5), CRI Ra >=80, THD<10%, PF >0.95, an operating Voltage Range of 140 - 270 VAC.Minimum Internal Surge Protection 3.0KV & IP20/IK02 protection, Manufacturer shall have inhouse lab approved by NABL or ministry of science of govt of India. LM 79 and LM80 reports need to be submitted from a NABL/UL accredited lab to verify above parameters. Both the fixture and Driver should have separate BIS approval . | C16: HUB ROOM | F16: NOS | G16: 2 | H16: 2273 | I16: =N(H16)*N(G16) -> 4546
A18: 2.4 | B18: 1500 mm concealed Linear LED Light Fixture
B19: Extruded aluminium concealed linear LED, white/black powder-coated finish, high-efficiency opal diffuser, width not more than 50 mm ±3 mm, SMD LED, approx. 2200 lm ±10%, efficacy 100 lm/W, 4000K, CRI 80, PF ≥0.95, THD ≤10%, 140–270V AC, Class I protection, Class B serviceability, 3.5kV surge protection, LM79/LM80 documentation, suspension kit, supply and installation complete | C19: WORKSTATION AREA, MEETING ROOM, BOARD ROOM | E19: INR 2750 / RMT | F19: RMT | G19: 290 | H19: 3215 | I19: =N(H19)*N(G19) -> 932350 | J19: Basic Rate: INR 1650/RMT
A21: 2.5 | B21: Ceiling Recessed Downlight (LED)
B22: Recessed LED Downlighter ,made up of pressure die cast aluminum housing with high efficiency PS diffuser, LED Used shall be SMD type and fixture should have minimum efficacy at System level 120 lumens/watt with Minimum system Lumens 1200 , CCT of 4000K (SDCM<=5), CRI Ra >=80, PF >0.9, an Operating working temp range - 0°C < Ta < 45°C & operating Voltage Range of 160-270 V AC. Minimum Internal Surge Protection 2.5KV. Manufacturer shall have inhouse lab approved by NABL or ministry of science of govt of India. LM 79 and LM80 reports need to be submitted from a NABL/UL accredited lab to verify above parameters. Both the fixture and Driver should have separate BIS approval. | C22: all areas | F22: NOS | G22: 335 | H22: 873 | I22: =N(H22)*N(G22) -> 292455
A25: 2.6 | B25: Cove lighting of size 100mm to 150mm x 100mm to 150mm | F25: RMT | G25: 300 | H25: 1745 | I25: =N(H25)*N(G25) -> 523500
B26: Providing and fixing of cove lighting formed of GI framework and cladded with double layer of 12.5mm thick plain gypsum board as per drawings. All gypsum board surface to be finished with putty, primer and 3 coat of acrylic emulsion paint of approved shade as per details.
B29: GRAND TOTAL - LIGHTING FIXTURES | I29: =sum(I4:I28) -> 2386539

Sheet HVAC
A1: SR. NO | B1: DESCRIPTION | C1: UNIT | D1: QTY | E1: Supply - A | G1: Installation - B
E2: Rate | F2: Amount | G2: Rate | H2: Amount
B4: Vendor shall visit site before sending quote as there are specialised support while installing Ducts,Pipes etc
B5: Note: Prices shall be based on supply, installation, testing & commissioning at site including all taxes, duties, transportation & insurance etc.
A7: A | B7: VRF SYSTEM:
B8: SITC of Air cooled Variable Refrigerant Flow modular type Air conditioning System complete with Indoor & Outdoor Units with individual corded controller as per the following capacities of the ODU & IDU.
A10: 1 | B10: VRF OUTDOOR UNIT
B11: SITC and lifting shifting of following capacity modular type fully Imported outdoor units equipped with highly efficient DC twin rotary / inverter scroll compressors, pre-coated heat exchanger/condensing coil, Fins of Multi Row with “Anti Corrosive” treatment, low noise condenser fan, auto check function for connection error, auto address setting, with multiple outdoor units, including providing initial gas charging, System Should Run at nominal working voltage, suitable electrical & refrigerant line interconnections complete including, cartage etc. as required. Each Outdoor units with High Pressure switch, Fan driver overload protector, Over current relay, Inverter Overload Protector & Fusible Plug. Refrigerant shall be R 410 A ready for use with single point electrical supply & refrigerant suction / liquid line tapping, all compressors shall be of inverter type only for better efficiency. The COP should be minimum 5.40 at 50% part load under normal operating conditions.
B12: ODU shall be mounted on suitable Civil Blocks with Vibration Isolators as required.
B13: ODU shall be BMS compatible with all necessary accessories for controlling & monitoring.
B14: Supply, Installation, testing and commissioning of below mentioned VRF Outdoor Units (condensing Units) -TOP/SIDE DISCHARGE with Hot / Cold Technology shall be selected as per requirement, with minimum 2 Nos. of compressors for the better reliability of the system. Special pre-coated fins, panel, corrosion resistant coated condenser, condenser fan , electrical & microprocessor panel, isolating valves and all the necessary accessories for proper functioning of the units. having following approximate capacities. Power Supply will be made available at one point only near outdoor unit. Note: HVAC Contractor shall have to coordinate the exact location of VRF ODU on site with the developer team. Accordingly, the actual quantity of refrigerant pipes shall be varied.
A17: I | B17: SSYTEM-I LHS SIDE 44 HP | C17: Set | D17: 1 | E17: 946714.49 | F17: =+E17*$D17 -> 946714.49 | G17: 112752 | H17: =+G17*$D17 -> 112752
A18: II | B18: SSYTEM-III LHS SIDE 62 HP | C18: Set | D18: 1 | E18: 1354646.5 | F18: =+E18*$D18 -> 1354646.5 | G18: 177638 | H18: =+G18*$D18 -> 177638
A19: III | B19: T Joint for connection of necessary combination of Outdoors | C19: Lot | D19: 1 | E19: 4148 | F19: =+E19*$D19 -> 4148 | G19: 532 | H19: =+G19*$D19 -> 532
B21: ALL DIFFUSER PANELS HAS TO BE BLACK
A23: 2 | B23: INDOOR UNIT
B24: Cassette Type IDU ( 4way Cassette Units )+ Compact Cassette
B25: i VRF Indoor Unit (Duct Type) – Technical Specification: Unit Type: Ceiling Concealed Ductable (Low Static / Medium Static / High Static variants); Capacity Range: 0.6 TR to 8.5 TR; Airflow Range: 280 CFM to 3000 CFM; External Static Pressure (ESP): Low Static: 5–30 Pa, Medium Static: 30–100 Pa, High Static: up to 150–200 Pa (model dependent); Fan Type: Direct Driven Multi-Speed / DC Fan Motor; Cooling Coil: Copper Tube with Aluminium Fins, Blue Fin Anti-Corrosion Coating; Refrigerant: R410A compatible with City Multi VRF System; Expansion Device: Electronic Expansion Valve (EEV) factory fitted; Drain Pump: Built-in (standard up to 850 mm lift for most models); Filter: Washable Synthetic Return Air Filter; Casing: Galvanized Steel Powder Coated; Insulation: Internal Thermal Insulation to prevent condensation; Sound Level: Low Noise Design suitable for office/commercial applications; Power Supply: 230V/1Ph/50Hz (small units) / 415V/3Ph/50Hz (higher capacity models); Controls: Compatible with Mitsubishi PAR wired controller, centralized controller, BMS integration (BACnet/Modbus); Installation: Ceiling suspended with flexible duct connection; Applications: Office, retail, restaurants, large open areas, high static suitable for long duct routing; Safety: High pressure protection, overload protection, condensate overflow safety; Make: Mitsubishi Electric (City Multi Series).
A27: 2.1 | B27: COMPACT CASSETTE
A28: a | B28: 0.63 TR Compact Cassette | C28: Nos | D28: 0 | E28: 30225 | F28: =+E28*$D28 -> 0 | G28: 3255 | H28: =+G28*$D28 -> 0
A29: b | B29: 0.83 TR Compact Cassette | C29: Nos | D29: 0 | E29: 32550 | F29: =+E29*$D29 -> 0 | G29: 3534 | H29: =+G29*$D29 -> 0
A30: c | B30: 1.05 TR Compact Cassette | C30: Nos | D30: 0 | E30: 34410 | F30: =+E30*$D30 -> 0 | G30: 3720 | H30: =+G30*$D30 -> 0
A31: d | B31: 1.25 TR Compact Cassette | C31: Nos | D31: 0 | E31: 38595 | F31: =+E31*$D31 -> 0 | G31: 4185 | H31: =+G31*$D31 -> 0
A32: e | B32: 1.59 TR Compact Cassette | C32: Nos | D32: 0 | E32: 39990 | F32: =+E32*$D32 -> 0 | G32: 4185 | H32: =+G32*$D32 -> 0
A34: 2.2 | B34: 4-WAY/ROUND FLOOR STANDARD CASSETTE
A36: a | B36: 0.63 TR 4-Way/Round Flow Cassette | C36: Nos | D36: 0 | E36: 18600 | F36: =+E36*$D36 -> 0 | G36: 2325 | H36: =+G36*$D36 -> 0
A37: b | B37: 0.83 TR 4-Way/Round Flow Cassette | C37: Nos | D37: 0 | E37: 23250 | F37: =+E37*$D37 -> 0 | G37: 2558 | H37: =+G37*$D37 -> 0
A38: c | B38: 1.05 TR 4-Way/Round Flow Cassette | C38: Nos | D38: 0 | E38: 29760 | F38: =+E38*$D38 -> 0 | G38: 3255 | H38: =+G38*$D38 -> 0
A39: d | B39: 1.25 TR 4-Way/Round Flow Cassette | C39: Nos | D39: 0 | E39: 34875 | F39: =+E39*$D39 -> 0 | G39: 3720 | H39: =+G39*$D39 -> 0
A40: e | B40: 1.59 TR 4-Way/Round Flow Cassette | C40: Nos | D40: 5 | E40: 41845 | F40: =+E40*$D40 -> 209225 | G40: 4946 | H40: =+G40*$D40 -> 24730
A41: f | B41: 2.05 TR 4-Way/Round Flow Cassette | C41: Nos | D41: 4 | E41: 43626 | F41: =+E41*$D41 -> 174504 | G41: 5195 | H41: =+G41*$D41 -> 20780
A42: g | B42: 2.59 TR 4-Way/Round Flow Cassette | C42: Nos | D42: 0 | E42: 43106 | F42: =+E42*$D42 -> 0 | G42: 5348 | H42: =+G42*$D42 -> 0
A43: h | B43: 3.2 TR 4-Way/Round Flow Cassette | C43: Nos | D43: 11 | E43: 48968 | F43: =+E43*$D43 -> 538648 | G43: 5935 | H43: =+G43*$D43 -> 65285
A44: i | B44: 3.95 TR 4-Way/Round Flow Cassette | C44: Nos | D44: 13 | E44: 51194 | F44: =+E44*$D44 -> 665522 | G44: 6184 | H44: =+G44*$D44 -> 80392
A46: 2.3 | B46: Hi Wall type Indoor unit
A47: a | B47: 0.63 TR- Hi-Wall type | C47: Nos | D47: 0 | E47: 19530 | F47: =+E47*$D47 -> 0 | G47: 2325 | H47: =+G47*$D47 -> 0
A48: b | B48: 0.83 TR- Hi-Wall type | C48: Nos | D48: 0 | E48: 20460 | F48: =+E48*$D48 -> 0 | G48: 3023 | H48: =+G48*$D48 -> 0
A49: c | B49: 1.05 TR- Hi-Wall type | C49: Nos | D49: 0 | E49: 22785 | F49: =+E49*$D49 -> 0 | G49: 3255 | H49: =+G49*$D49 -> 0
A50: d | B50: 1.59 TR- Hi-Wall type | C50: Nos | D50: 0 | E50: 25575 | F50: =+E50*$D50 -> 0 | G50: 6324 | H50: =+G50*$D50 -> 0
A51: e | B51: 2.05 TR- Hi-Wall type | C51: Nos | D51: 0 | E51: 29760 | F51: =+E51*$D51 -> 0 | G51: 7440 | H51: =+G51*$D51 -> 0
A53: 3 | B53: Ducted Unit
B54: SITC of Ceiling Suspended ( HSP ) High Static Pressure ducted type Indoor units with compact DX cooling coil, electronic expansion valve and multispeed fan motor. The blower shall be dynamically balanced and design for silent operation, the filter shall be Plasma & Synthetic washable media type arranged for convenient cleaning & replacement, built in drain pump, the drain pan shall be fabricated out of heavy sheet steel insulated with 6mm expanded polyethylene sheet. All Low Noise Ducted Unit shall be controlled with corded remote control.Refer attached layout for location of IDU.Unit cost shall include the cost of starter panel.
A55: 3.1 | B55: SLIM CEILING MOUNTED DUCT TYPE
A57: a | B57: 0.63 TR/283 CFM | C57: Nos | D57: 0 | F57: =+E57*$D57 -> 0 | H57: =+G57*$D57 -> 0
A58: b | B58: 0.63 TR/283 CFM | C58: Nos | D58: 0 | F58: =+E58*$D58 -> 0 | H58: =+G58*$D58 -> 0
A59: c | B59: 1.05 TR/283 CFM | C59: Nos | D59: 0 | F59: =+E59*$D59 -> 0 | H59: =+G59*$D59 -> 0
C60: Nos | D60: 0 | F60: =+E60*$D60 -> 0 | H60: =+G60*$D60 -> 0
A61: 3.2 | B61: MIDDLE STATIC PRESSURE CEILING MOUNTED DUCT TYPE
C62: Nos | D62: 0 | F62: =+E62*$D62 -> 0 | H62: =+G62*$D62 -> 0
A63: a | B63: 1.3TR/ 530 CFM | C63: Nos | D63: 0 | F63: =+E63*$D63 -> 0 | H63: =+G63*$D63 -> 0
A64: b | B64: 1.59 TR/671 CFM | C64: Nos | D64: 0 | F64: =+E64*$D64 -> 0 | H64: =+G64*$D64 -> 0
A65: c | B65: 2.05 TR/858 CFM | F65: =+E65*D65 -> 0 | H65: =+G65*F65 -> 0
A66: d | B66: 2.59 TR/1060 CFM | C66: Nos | D66: 0 | F66: =+E66*$D66 -> 0 | H66: =+G66*$D66 -> 0
A67: e | B67: 3.2 TR/1200 CFM | C67: Nos | D67: 0 | F67: =+E67*$D67 -> 0 | H67: =+G67*$D67 -> 0
A69: 3.3 | B69: CEILING MOUNTED DUCT TYPE
A71: a | B71: 0.63 TR/318 CFM | C71: Nos | D71: 0 | F71: =+E71*$D71 -> 0 | H71: =+G71*$D71 -> 0
A72: b | B72: 0.83 TR/335 CFM | C72: Nos | D72: 0 | F72: =+E72*$D72 -> 0 | H72: =+G72*$D72 -> 0
A73: c | B73: 1.3 TR / 565 CFM | C73: Nos | D73: 0 | F73: =+E73*$D73 -> 0 | H73: =+G73*$D73 -> 0
A74: d | B74: 1.59 TR/635 CFM | C74: Nos | D74: 0 | F74: =+E74*$D74 -> 0 | H74: =+G74*$D74 -> 0
A75: e | B75: 2.05 TR/ 688 CFM | C75: Nos | D75: 0 | F75: =+E75*$D75 -> 0 | H75: =+G75*$D75 -> 0
A76: f | B76: 2.59 TR/883 CFM | C76: Nos | D76: 0 | F76: =+E76*$D76 -> 0 | H76: =+G76*$D76 -> 0
A77: g | B77: 3.2 TR/1130 FM | C77: Nos | D77: 0 | F77: =+E77*$D77 -> 0 | H77: =+G77*$D77 -> 0
A78: h | B78: 3.95 TR/1377 CFM | C78: Nos | D78: 0 | F78: =+E78*$D78 -> 0 | H78: =+G78*$D78 -> 0
A79: i | B79: 4.5 TR/1624 CFM | C79: Nos | D79: 0 | E79: 139500 | F79: =+E79*$D79 -> 0 | G79: 27900 | H79: =+G79*$D79 -> 0
A81: 3.4 | B81: HIGH STATIC DUCT TYPE
A83: a | B83: 4.2 TR/2047 CFM | C83: Nos | D83: 0 | F83: =+E83*$D83 -> 0 | H83: =+G83*$D83 -> 0
A84: b | B84: 6.4 TR /2295 CFM | C84: Nos | D84: 0 | E84: 153450 | F84: =+E84*$D84 -> 0 | G84: 31155 | H84: =+G84*$D84 -> 0
A85: c | B85: 8.2 TR/2825 CFM | C85: Nos | D85: 0 | F85: =+E85*$D85 -> 0 | H85: =+G85*$D85 -> 0
A87: 3.5 | B87: 2-WAY VRV CASSETTES
B88: Supply, Installation, Testing & Commissioning (SITC) of 2-Way Cassette Type Indoor Unit suitable for VRV/VRF air conditioning system, factory assembled and tested, using R410A/R32 refrigerant, having cooling capacity range from 1.5 TR to 4.0 TR, dual directional (180°) air discharge, equipped with direct driven multi-speed fan, low noise operation (≤40 dB(A)), ESP minimum 15–30 Pa, complete with powder-coated decorative panel, washable air filter, anti-corrosion drain pan, built-in condensate drain pump (minimum 750 mm lift), suitable for false ceiling mounting, including wired wall-mounted controller, provision for BMS integration (BACnet/Modbus), communication cable with outdoor unit, and all necessary accessories; the scope includes suspension arrangement with threaded rods, anti-vibration supports, insulated drain piping up to nearest drain point, refrigerant piping connections (liquid & gas) with insulation, control wiring, testing, commissioning and handing over, complete in all respects as per specifications
A90: a | B90: 1.05 TR/460 CFM | C90: Nos | D90: 0 | F90: =+E90*$D90 -> 0 | H90: =+G90*$D90 -> 0
A91: b | B91: 1.59 TR/530 CFM | C91: Nos | D91: 0 | E91: 65000 | F91: =+E91*$D91 -> 0 | G91: 3500 | H91: =+G91*$D91 -> 0
A92: c | B92: 2.05/565 CFM | C92: Nos | D92: 0 | F92: =+E92*$D92 -> 0 | H92: =+G92*$D92 -> 0
A94: 3.6 | B94: 1-WAY VRV CASSETTES
B95: Supply, Installation, Testing & Commissioning (SITC) of 1-Way Cassette Type Indoor Unit suitable for VRV/VRF air conditioning system, factory assembled and tested, using R410A/R32 refrigerant, having cooling capacity range from 0.8 TR to 2.5 TR, single directional air discharge suitable for perimeter zones and narrow spaces, equipped with direct driven multi-speed fan, low noise operation (≤38 dB(A)), ESP minimum 10–20 Pa, complete with compact slim body, powder-coated decorative panel, washable air filter, anti-corrosion drain pan, built-in condensate drain pump (minimum 750 mm lift), suitable for false ceiling installation, including wired wall-mounted controller, provision for BMS integration (BACnet/Modbus), communication cable with outdoor unit, and all necessary accessories; the scope includes suspension arrangement with threaded rods, anti-vibration supports, insulated drain piping up to nearest drain point, refrigerant piping connections (liquid & gas) with insulation, control wiring, testing, commissioning and handing over, complete in all respects as per specifications
A97: a | B97: 1.05 TR/282 CFM | C97: Nos | D97: 0 | E97: 37200 | F97: =+E97*$D97 -> 0 | G97: 4046 | H97: =+G97*$D97 -> 0
A98: b | B98: 1.59 TR/414 CFM | C98: Nos | D98: 0 | E98: 41850 | F98: =+E98*$D98 -> 0 | G98: 4464 | H98: =+G98*$D98 -> 0
B100: VRV IDU-ODU+DX CSUs+HRW+ AHU+AHU Modification | F100: =SUM(F7:F99) -> 3893408 | H100: =SUM(H7:H99) -> 482109
A102: B | B102: Refrigerant Piping
A104: 1 | B104: Supply, installation, testing and commissioning of refrigerant liquid & gas piping(Circuit Piping rates) using eddy current tested Copper pipes and fittings like elbows, couplers, tee joints, brass fittings, "U" loops, expansion loops etc. Supports consisting of GI box / "C" sections & female anchor fasteners with full threaded GI rods, insulation of pipes using 19 mm thick elastomeric closed cell Nitrile Rubber insulation material having class "O" for fire properties, structural clamps with hard PVC pipe sleeves under the clamps to protect insulation at supports, tagging to enable tracing connectivity to respective units as per shop drawings to be generated by contractor and approved by consultant. Refrigerant piping shall be laid in GI cable tray as per drawing. | C104: Rmt | D104: 280 | E104: 1861 | F104: =+E104*$D104 -> 521080 | G104: 319 | H104: =+G104*$D104 -> 89320
B105: Note : Vendor shall be selected required refrigerant pipe size as per respective factory based IDU. We have considered Common length of liquid & gas pipe together & average rates for refrigerant pipes.Vendor shall be submitted exact required pipe size & length of each circuit with respective market rates.
A107: 2 | B107: Refnut Joints
B108: Providing, fixing, testing and commissioning of Variable refrigerant flow distribution REFNUTS / T Joints (pair) in the suction & Liquid lines for various sizes of copper refrigerant piping including insulation etc. as required. | C108: Nos | D108: 32 | E108: 4205 | F108: =+E108*$D108 -> 134560 | G108: 471 | H108: =+G108*$D108 -> 15072
A110: 3 | B110: Drain Piping
B111: Make : SUPREME / DURALINE
B112: Supply, installation, testing & commissioning of following sizes 9 mm Nitrile rubber insulated hard PVC drain pipes from CASSETTE UNIT to drain header and drain header to nearest floor drain complete with interconnection, flanges, elbows, tees, nuts, P-trap etc.
B113: The insulation should be similar to chilled water piping insulation
A114: a | B114: 65mm dia. | C114: Rmt | D114: 0 | F114: =+E114*$D114 -> 0 | H114: =+G114*$D114 -> 0
A115: b | B115: 50mm dia. | C115: Rmt | D115: 0 | E115: 837 | F115: =+E115*$D115 -> 0 | G115: 93 | H115: =+G115*$D115 -> 0
A116: c | B116: 40mm dia. | C116: Rmt | D116: 49 | E116: 792 | F116: =+E116*$D116 -> 38808 | G116: 94 | H116: =+G116*$D116 -> 4606
A117: d | B117: 32mm dia. | C117: Rmt | D117: 98 | E117: 684 | F117: =+E117*$D117 -> 67032 | G117: 84 | H117: =+G117*$D117 -> 8232
A118: e | B118: 25mm dia | C118: Rmt | D118: 65 | E118: 545 | F118: =+E118*$D118 -> 35425 | G118: 64 | H118: =+G118*$D118 -> 4160
B120: NOTES FOR PIPING:
B121: Cover all open pipe ends with muslin cloth during construction
B122: Pipe cleaning as per specs shall be included in the piping cost.
B123: Unit rates for all indicated sizes of pipes & valves shall be furnished.
B124: Cleaning/Painting of pipe before insulation shall be included in piping cost
B125: The piping support should be as per tender specification and additional supports are to be provided as decided by Consultant.
A127: 4 | B127: Supply Installation testing & Commissioning of ASPEN Make Drain Pumps, 12 L/h , Lift 2 m, with Discharge tube,safety switch & all Necessary accessories for Hi Wall & Ducted Units. | C127: Nos | D127: 2 | E127: 6925 | F127: =+E127*$D127 -> 13850 | G127: 792 | H127: =+G127*$D127 -> 1584
A129: 5 | B129: Supply & installation of secondary drain tray (for all Ceiling suspended & Hi wall Units) for condensate drain collection (MOC : SS 304) | C129: Nos | D129: 2 | E129: 5441 | F129: =+E129*$D129 -> 10882 | G129: 743 | H129: =+G129*$D129 -> 1486
...

Sheet Passive Networking
A1: SL NO | B1: ITEM DESCRIPTION | C1: MAKE LIST | D1: UNIT | E1: QTY | F1: SUPPLY RATE | G1: SUPPLY AMOUNT | H1: REMARKS
A3: 1 | B3: Passive Networking + Rack Side
A5: 4.1 | B5: Cat6A UTP cable Box of 305 Mtrs 23Awg LSZH | C5: CommScope-Netconnect | D5: BOX | E5: 30 | F5: 24875 | G5: =N(E5)*N(F5) -> 746250 | H5: 40% existing cabling to be retained
A6: 4.2 | B6: Cat6A Information Outlet - Active Data - Blue | C6: CommScope-Netconnect | D6: NOS | E6: 136 | F6: 525 | G6: =N(E6)*N(F6) -> 71400
A7: 4.3 | B7: Cat6A Information Outlet - Redundant Data- Yellow | C7: CommScope-Netconnect | D7: NOS | E7: 92 | F7: 525 | G7: =N(E7)*N(F7) -> 48300
A8: 4.4 | B8: 24 Port Jack Panel Angled - Unloaded | C8: CommScope-Netconnect | D8: NOS | E8: 10 | F8: 9674 | G8: =N(E8)*N(F8) -> 96740
A9: 4.5 | B9: Cat6APatch cord -2 meters for Active Data - Blue | C9: CommScope-Netconnect | D9: NOS | E9: 136 | F9: 525 | G9: =N(E9)*N(F9) -> 71400
A10: 4.6 | B10: Cat6APatch cord -2 meters Redundant Data - Yellow | C10: CommScope-Netconnect | D10: NOS | E10: 92 | F10: 525 | G10: =N(E10)*N(F10) -> 48300
A12: 5 | B12: Workstation Side
A14: 5.1 | B14: Cat6A Information Outlet - Active Data - Blue | C14: CommScope-Netconnect | D14: NOS | E14: 136 | F14: 525 | G14: =N(E14)*N(F14) -> 71400
A15: 5.2 | B15: Cat6A Information Outlet - Redundant Data- Yellow | C15: CommScope-Netconnect | D15: NOS | E15: 93 | F15: 525 | G15: =N(E15)*N(F15) -> 48825
A16: 5.3 | B16: Face Plate, 2 Port (White) | C16: CommScope-Netconnect | D16: NOS | E16: 113 | F16: 221 | G16: =N(E16)*N(F16) -> 24973
A17: 5.4 | B17: Face Plate, 4 Port (White) | C17: CommScope-Netconnect | D17: NOS | E17: 0 | F17: 358 | G17: =N(E17)*N(F17) -> 0
A18: 5.5 | B18: Cat6A Patch cord -2 meters for Active Data - Blue | C18: CommScope-Netconnect | D18: NOS | E18: 64 | F18: 525 | G18: =N(E18)*N(F18) -> 33600
A20: 8 | B20: Network Racks
B21: 42 U Racks - 2nos
A23: 8.1 | B23: 42U - 800X1000MM Closed Rack with all Standard accessories | C23: Netrack | D23: NOS | E23: 1 | F23: 96580 | G23: =N(E23)*N(F23) -> 96580
A24: 8.2 | B24: 24 U - 550X500MM Closed Rack with all Standard accessories | C24: Netrack | D24: NOS | E24: 0 | F24: 40040 | G24: =N(E24)*N(F24) -> 0
A25: 8.3 | B25: Horz. Cable Organiser/2U/Channel On Front | C25: Netrack | D25: NOS | E25: 4 | F25: 1658 | G25: =N(E25)*N(F25) -> 6632
A26: 8.4 | B26: High Density Vertical Cable Organiser/12 inch/Front &Back/42U/Black | C26: Netrack | D26: NOS | E26: 2 | F26: 10365 | G26: =N(E26)*N(F26) -> 20730
A27: 8.5 | B27: High Density Vertical Cable Organiser/8 inch/Front &Back/42U/Black | C27: Netrack | D27: NOS | E27: 2 | F27: 8983 | G27: =N(E27)*N(F27) -> 17966
A28: 8.6 | B28: Run-Way Kit-20Inch/Black | C28: Netrack | D28: NOS | E28: 2 | F28: 9674 | G28: =N(E28)*N(F28) -> 19348
A29: 8.7 | B29: Mounting Hardware/OR/Pk-20 | C29: Netrack | D29: NOS | E29: 60 | F29: 415 | G29: =N(E29)*N(F29) -> 24900
A30: 8.8 | B30: PDU Brackets for mounting the Vertical PDU | C30: Netrack | D30: NOS | E30: 4 | F30: 1244 | G30: =N(E30)*N(F30) -> 4976
A31: 8.9 | B31: Ladder water fall kit | C31: Netrack | D31: NOS | E31: 2 | F31: 3317 | G31: =N(E31)*N(F31) -> 6634
A32: 8.1 | B32: Server /IT Rack mount power distribution unit, 1Ph, 230V, 32A, 50/60Hz, Zero U standard with 12 X Indian Round Pin 5/15A, 16A MCB X 2 Circuits- PDU Rating 7.3KVA/Bottom feed-3Mt/ Black/ Inlet Plug Not Installed (32 Power Sockets) | C32: Netrack | D32: NOS | E32: 1 | F32: 34549 | G32: =N(E32)*N(F32) -> 34549
A33: 8.11 | B33: Server /IT Rack mount power distribution unit, 1Ph, 230V, 32A, 50/60Hz, Zero U standard with 12 X Indian Round Pin 5/15A, 16A MCB X 2 Circuits- PDU Rating 7.3KVA/Bottom feed-3Mt/ Black/ Inlet Plug Not Installed | C33: Netrack | D33: NOS | E33: 2 | F33: 34549 | G33: =N(E33)*N(F33) -> 69098
A35: 9 | B35: Local Materials
A37: 9.1 | B37: Patchcord Labels | C37: Local | D37: LS | E37: 1 | F37: 20729 | G37: =N(E37)*N(F37) -> 20729
A38: 9.2 | B38: Consumables | C38: Local | D38: LS | E38: 1 | F38: 13820 | G38: =N(E38)*N(F38) -> 13820
A39: 9.3 | B39: WIFI Stand | C39: Local | D39: NOS | E39: 7 | F39: 1106 | G39: =N(E39)*N(F39) -> 7742
A40: 9.4 | B40: CCTV Pole wite Round clamp | C40: Local | D40: NOS | E40: 15 | F40: 2073 | G40: =N(E40)*N(F40) -> 31095
A42: 10 | B42: Services - Installation Charges
A44: 10.1 | B44: UTP cable laying Bunching dressing termination Jack panel mounting faceplate termination | C44: Services | D44: Per node | E44: 228 | F44: 553 | G44: =N(E44)*N(F44) -> 126084
A45: 10.2 | B45: Fluke Testing - UTP testing and scanning | C45: Services | D45: NOS | E45: 228 | F45: 166 | G45: =N(E45)*N(F45) -> 37848
A46: 10.3 | B46: Labelling - Jack panel & Faceplate | C46: Services | D46: NOS | E46: 228 | F46: 55 | G46: =N(E46)*N(F46) -> 12540
A47: 10.4 | B47: Rack Mounting and installation | C47: Services | D47: NOS | E47: 1 | F47: 6910 | G47: =N(E47)*N(F47) -> 6910
A48: 10.5 | B48: Access point mounting which is supplied by customer | C48: Services | D48: NOS | E48: 8 | F48: 691 | G48: =N(E48)*N(F48) -> 5528
A49: 10.6 | B49: CCTV Pole and WIFI Poles supply and installation | C49: Services | D49: NOS | E49: 25 | F49: 1519 | G49: =N(E49)*N(F49) -> 37975
A50: 10.7 | B50: On Site Coordination, Project Management, As built Docs & warranty ,WCP & CAR policy | C50: Services | D50: LS | E50: 1 | F50: 69098 | G50: =N(E50)*N(F50) -> 69098
B52: TOTAL (without Taxes) | G52: =SUM(G3:G51) -> 1931970
B54: GRAND TOTAL - PASSIVE NETWORKING | G54: =G52 -> 1931970

Sheet PHE
A1: SL NO | B1: ITEM DESCRIPTION | C1: UNIT | D1: QTY | E1: RATE(INR) | H1: AMOUNT(INR)
E2: SUPPLY | F2: INSTALLATION | G2: TOTAL | H2: SUPPLY | I2: INSTALLATION | J2: TOTAL
A4: 1 | B4: SANITARY FIXTURES
A6: 1.1 | B6: Installing, testing and commissioning of White colour wall mounted European water closet with concealed flush tank with necessary pan connecter, bend,checknut, solid seat cover with polythene buffer and flap etc.,(The item rate shall include all costs towards labour, tools, tackles & machineries, all leads & lifts, work related cleaning ) complete. The flow rate of fixture shall be as per IGBC requirement. | C6: NOS | D6: 0 | F6: 3500 | G6: =F6+E6 -> 3500 | H6: =N(E6)*N(D6) -> 0 | I6: =N(F6)*N(D6) -> 0 | J6: =N(D6)*N(G6) -> 0
B7: Make : Kohler
A9: 1.2 | B9: Installing, testing and commissioning of under counter wash basin, 15mm dia Pillar cock with waste coupling, 32mm dia CP bottle trap with extension pipe, supporting bracket with necessary steel to support basin 1 No.15mm CP angle valve with 450mm long CP connection pipe and CP wall flanges all of approved make etc.,(The item rate shall include all costs towards labour, tools, tackles & machineries, all leads & lifts, work related cleaning ) complete. The flow rate of fixture shall be as per IGBC requirement. | C9: NOS | D9: 9 | F9: 3385 | G9: =F9+E9 -> 3385 | H9: =N(E9)*N(D9) -> 0 | I9: =N(F9)*N(D9) -> 30465 | J9: =N(D9)*N(G9) -> 30465
B10: Make : Kohler
A13: 1.3 | B13: Installing, testing and commissioning of handicapped toilet including water closet, concelaed flush tank for closet, rectangular wall hung wash basin, 15mm dia sensor Pillar cock with waste coupling, CP angle cock, 32mm dia CP bottle trap with extension pipe, grab bar vertical swing satin, supporting bracket with necessary steel to support basin, 450mm long CP connection pipe and CP wall flanges all of approved make etc.,complete. | C13: NOS | D13: 1 | F13: 9658 | G13: =F13+E13 -> 9658 | H13: =N(E13)*N(D13) -> 0 | I13: =N(F13)*N(D13) -> 9658 | J13: =N(D13)*N(G13) -> 9658
B14: Make : Kohler
A16: 1.4 | B16: installing, testing and commissioning White Vitreous large flat back urinal with sensor flush value supported by CI/GI bracket duly painted, including CP brass waste with dome type grating, CP cast brass bottle trap with extension piece, wall flanges, automatic flushing systems for urinal to ensure flushing only immediately after use, comprising of all plumbing, electronic and electrical items. , CP wall flange, infrared photo cells (Sensor), eyes electrically operated solenoid valve, step down transformer/equipment and any other item required to provide satisfactory functioning. Including necessary wall cutting/chasing and making good, as required. The flow rate of fixture shall be as per IGBC requirement. | C16: NOS | D16: 0 | F16: 1800 | G16: =F16+E16 -> 1800 | H16: =N(E16)*N(D16) -> 0 | I16: =N(F16)*N(D16) -> 0 | J16: =N(D16)*N(G16) -> 0
B17: Make / Model : Kohler/
A19: 1.5 | B19: Installing, testing and commissioning of 15mm CP health faucet of approved make with necessary CP flexible hose 1000mm long nozzle wall flange, CP angle cock etc., (The item rate shall include all costs towards labour, tools, tackles & machineries, all leads & lifts, work related cleaning ). The flow rate of fixture shall be as per IGBC requirement. | C19: NOS | D19: 0 | F19: 300 | G19: =F19+E19 -> 300 | H19: =N(E19)*N(D19) -> 0 | I19: =N(F19)*N(D19) -> 0 | J19: =N(D19)*N(G19) -> 0
B20: Make / Model :Kohler/
A22: 1.6 | B22: Installing & testing 15mm hot & cold wall Mixer along with spout with overhead shower with shower arm including CP flanges necessary fixing materials etc., complete. The flow rate of fixture shall be as per IGBC requirement. | C22: NOS | D22: RO | H22: =N(E22)*N(D22) -> 0 | I22: =N(F22)*N(D22) -> 0 | J22: =N(D22)*N(G22) -> 0
B23: Make / Model : Kohler /
A25: 1.7 | B25: Fixing Towel Rail fixed with SS screws on to the Shower area. | C25: NOS | D25: RO | H25: =N(E25)*N(D25) -> 0 | I25: =N(F25)*N(D25) -> 0 | J25: =N(D25)*N(G25) -> 0
B26: Make / Model : Kohler /
A28: 1.8 | B28: Installing, testing and commissioning of Stainless sink with single bowl manufactured from 1mm thick stainless steel, 18G high grade indestructible chrome nickel steel with top quality polish,1no.40mmdia CP waste coupling, Sink cock with wall flange with aerator etc., complete. For Kitchen/Cafe/Wet Pantry. | C28: NOS | D28: 2 | F28: 1160 | G28: =F28+E28 -> 1160 | H28: =N(E28)*N(D28) -> 0 | I28: =N(F28)*N(D28) -> 2320 | J28: =N(D28)*N(G28) -> 2320
B29: Make / Model : Kohler /
A31: 1.9 | B31: Installing, testing and commissioning of 15 mm dia CP Angle cocks (The item rate shall include all costs towards labour, tools, tackles & machineries, all leads & lifts, work related cleaning)complete. | C31: NOS | D31: 12 | F31: 174 | G31: =F31+E31 -> 174 | H31: =N(E31)*N(D31) -> 0 | I31: =N(F31)*N(D31) -> 2088 | J31: =N(D31)*N(G31) -> 2088
B32: Make / Model : Kohler /
A34: 1.1 | B34: Installing, testing and commissioning of Horizontal / Vertical type electrical water heater of up to 15 Liters capacity including support, 2 Nos CP angle valve, connection hose, support etc. Complete | C34: NOS | D34: 1 | F34: 1741 | G34: =F34+E34 -> 1741 | H34: =N(E34)*N(D34) -> 0 | I34: =N(F34)*N(D34) -> 1741 | J34: =N(D34)*N(G34) -> 1741
B35: Make / Model :Kohler/
A37: 1.11 | B37: Lifting Station - pre-fabricated package unit, 1.5 kW, vertical lift up to 7 m Make: Sulzer / Wilo / Grundfos / Saner Greywater Pre-fabricated polyethylene tank with built-in pump + check valve + control panel Capacity: ~50 L holding + 1.5 kW pump @ 2.5 m³/hr Float-switch auto operation, dry-run protection, alarm + visual indicator Inlet 110 mm UPVC SWR, Outlet 50 / 75 mm pressurised line to stack 230V single-phase, with control panel + cabling INCLUDES: tank + pump + check valve + control panel + alarm + connections | C37: NOS | D37: 0 | E37: 150000 | F37: 15000 | G37: =F37+E37 -> 165000 | H37: =N(E37)*N(D37) -> 0 | I37: =N(F37)*N(D37) -> 0 | J37: =N(D37)*N(G37) -> 0
A39: 1.12 | B39: Lifting Station Outlet Pressurised Line - CPVC / GI to nearest stack inlet 50 mm CPVC / GI pressurised pipe, ~10 m run with check valve + isolation | C39: NOS | D39: 0 | E39: 30000 | F39: 5000 | G39: =F39+E39 -> 35000 | H39: =N(E39)*N(D39) -> 0 | I39: =N(F39)*N(D39) -> 0 | J39: =N(D39)*N(G39) -> 0
A41: 1.13 | B41: Lifting Station Power + Alarm Wiring - to LV / Plumbing DB 230V single-phase supply + alarm relay to BMS / monitoring | C41: NOS | D41: 0 | E41: 12500 | F41: 2500 | G41: =F41+E41 -> 15000 | H41: =N(E41)*N(D41) -> 0 | I41: =N(F41)*N(D41) -> 0 | J41: =N(D41)*N(G41) -> 0
B44: TOTAL AMOUNT C/O TO SUMMARY | H44: =+SUM(H4:H43) -> 0 | I44: =+SUM(I4:I43) -> 46272 | J44: =+SUM(J4:J43) -> 46272
A46: 2 | B46: INTERNAL SOIL AND WASTE WATER SYSTEM
A48: 2.1 | B48: Supply and fixing , Testing and Commissioning of Type - B SWR PVC pipe confirming to IS 13592 soil & waste pipes jointed with solvent cement of good quality lubricant inclusive of all necessary specials like bends, tees, offsets, junctions, pan connector, cowls, Rodding eye at 15 Mtr Interval etc., laid under floor / under ceiling / on walls with suitable clamps including making bores in masonry etc., and rendering the bores in cement mortar after laying the pipes and specials curing etc., complete. The quoted rate should include necessary supports like hanger supports, grip bolts and clamps etc.,. Fixing of universal clamp for hanging pipeline is done at no extra cost and is included in the cost of installation of piping.(Brand & Specifications as per Design )
A49: a | B49: 75mm dia (low noise pipe) | C49: RMT | D49: RO | E49: 264 | F49: 60 | G49: =F49+E49 -> 324 | H49: =N(E49)*N(D49) -> 0 | I49: =N(F49)*N(D49) -> 0 | J49: =N(D49)*N(G49) -> 0
A50: b | B50: 110mm dia (low noise pipe) | C50: RMT | D50: RO | E50: 300 | F50: 60 | G50: =F50+E50 -> 360 | H50: =N(E50)*N(D50) -> 0 | I50: =N(F50)*N(D50) -> 0 | J50: =N(D50)*N(G50) -> 0
A51: c | B51: 160mm dia (low noise pipe) | C51: RMT | D51: RO | E51: 480 | F51: 60 | G51: =F51+E51 -> 540 | H51: =N(E51)*N(D51) -> 0 | I51: =N(F51)*N(D51) -> 0 | J51: =N(D51)*N(G51) -> 0
A52: d | B52: 200mm dia (low noise pipe) | C52: RMT | D52: RO | E52: 660 | F52: 60 | G52: =F52+E52 -> 720 | H52: =N(E52)*N(D52) -> 0 | I52: =N(F52)*N(D52) -> 0 | J52: =N(D52)*N(G52) -> 0
A54: 2.2 | B54: Supply and fixing , Testing and Commissioning of PVC pressure pipes Class-III (10Kg/sqcm) confirming to IS-4985 soil & waste pipes jointed with solvent cement of good quality lubricant inclusive of all necessary specials like bends, tees, offsets, junctions, pan connector, etc., laid under floor / under ceiling / on walls with suitable clamps including making bores in masonry etc., and rendering the bores in cement mortar after laying the pipes and specials curing etc., complete. The quoted rate should include necessary supports like hanger supports, grip bolts and clamps etc.,. Fixing of universal clamp for hanging pipeline is done at no extra cost and is included in the cost of installation of piping.(Brand & Specifications as per Design ) ( For Wash Basins, Urinals, etc...)
A55: a | B55: 32mm dia (low noise pipe) | C55: RMT | D55: RO | H55: =N(E55)*N(D55) -> 0 | I55: =N(F55)*N(D55) -> 0 | J55: =N(D55)*N(G55) -> 0
A56: b | B56: 40mm dia (low noise pipe) | C56: RMT | D56: 75 | E56: 209 | F56: 46 | G56: =F56+E56 -> 255 | H56: =N(E56)*N(D56) -> 15675 | I56: =N(F56)*N(D56) -> 3450 | J56: =N(D56)*N(G56) -> 19125
A57: c | B57: 50mm dia (low noise pipe) | C57: RMT | D57: RO | G57: =F57+E57 -> 0 | H57: =N(E57)*N(D57) -> 0 | I57: =N(F57)*N(D57) -> 0 | J57: =N(D57)*N(G57) -> 0
A60: 2.3 | B60: Supply and fixing of PVC self cleansing, deep seal type 110 mm dia Floor trap and 75mm outlet with necessary cement concrete, water proofing the internal surfaces of chamber etc., or laid under floor / under ceiling / on walls with suitable clamps including making bores in masonry etc., and rendering the bores in cement mortar after laying the pipes and specials curing etc., complete. complete as per specifications. depth of trap shall not be less than 125mm.(The item rate shall include all costs towards labour, tools, tackles & machineries, all leads & lifts, work related cleaning) | C60: NOS | D60: RO | H60: =N(E60)*N(D60) -> 0 | I60: =N(F60)*N(D60) -> 0 | J60: =N(D60)*N(G60) -> 0
A62: 2.4 | B62: Supply and fixing of PVC self cleasing, deep seal type 110 mm dia Multi Floor trap and 75mm outlet with necessary cement concrete, water proofing the internal surfaces of chamber etc.,or laid under floor / under ceiling / on walls with suitable clamps including making bores in masonry etc., and rendering the bores in cement mortar after laying the pipes and specials curing etc., complete as per specifications. depth of trap shall not be less than 125mm.(The item rate shall include all costs towards labour, tools, tackles & machineries, all leads & lifts, work related cleaning) complete | C62: NOS | D62: 6 | E62: 522 | F62: 174 | G62: =F62+E62 -> 696 | H62: =N(E62)*N(D62) -> 3132 | I62: =N(F62)*N(D62) -> 1044 | J62: =N(D62)*N(G62) -> 4176
A64: 2.5 | B64: Supplying, fixing and testing 75 dia PVC 'P' trap for urinals with boss connection suitable as per piping detail with fixed in bed of cement concrete. etc., or laid under floor / under ceiling / on walls with suitable clamps including making bores in masonry etc., and rendering the bores in cement mortar after laying the pipes and specials curing etc., complete. | C64: NOS | D64: 0 | E64: 300 | F64: 120 | G64: =F64+E64 -> 420 | H64: =N(E64)*N(D64) -> 0 | I64: =N(F64)*N(D64) -> 0 | J64: =N(D64)*N(G64) -> 0
A66: 2.6 | B66: Supply and fixing of cockroach trap of size 153mm x 153mm, complete as per specifications. (The item rate shall include all costs towards labour, tools, tackles & machineries, all leads & lifts, work related cleaning) complete | C66: NOS | D66: 0 | E66: 1800 | F66: 120 | G66: =F66+E66 -> 1920 | H66: =N(E66)*N(D66) -> 0 | I66: =N(F66)*N(D66) -> 0 | J66: =N(D66)*N(G66) -> 0
B67: Make : Chilly / Model No: CCTL-SMHCL-150
A69: 2.7 | B69: Supplying and fixing MS angle brackets, hangers, supports as required for supporting pipes with suitable GI U- clamps, bolts, nuts and washers etc. The clamps shall be painted with two coats of enamel (approved) paint over a coat of primer etc., complete. | C69: KG | D69: 0 | E69: 108 | F69: 42 | G69: =F69+E69 -> 150 | H69: =N(E69)*N(D69) -> 0 | I69: =N(F69)*N(D69) -> 0 | J69: =N(D69)*N(G69) -> 0
A71: 2.8 | B71: Supply, fixing and testing of Garbodrain G-1000 (Food waste crusher), including all fittings, should be anti-jam impellers made of SS 304 for efficient grinding & corrosion free, run with AC power supply with calling bell switch for dry run protection. (for cafeteria plate wash counter sink area) | C71: NOS | D71: 1 | E71: 18566 | F71: 1741 | G71: =F71+E71 -> 20307 | H71: =N(E71)*N(D71) -> 18566 | I71: =N(F71)*N(D71) -> 1741 | J71: =N(D71)*N(G71) -> 20307
A73: 2.9 | B73: SFA-Grease separator below counter (grease trap Undersink, Standard, or equivalent,.), café plate wash sink area. | C73: NOS | D73: 1 | E73: 48350 | F73: 1741 | G73: =F73+E73 -> 50091 | H73: =N(E73)*N(D73) -> 48350 | I73: =N(F73)*N(D73) -> 1741 | J73: =N(D73)*N(G73) -> 50091
B74: This separator for greasy waste water is suitable for freestanding installation in frost-protected rooms below a sink. Free of any metal components, the collecting tank is made of durable plastic (HDPE) equipped with an integrated sludge trap. An odor-tight lid with a wrap-around seal and closure clip allows easy access during manual emptying and cleaning. The separator also has quick-release pipe connections for easy removal, and an inspection window as an additional accessorry for on-site installation for visually checking the thickness of the grease layer. Version: Seal: yes Type of disposal: manual Refill inlet in accordance with DIN 1988: no Nominal size (NS): 0.7 Delivery state: Modular set for assembly on site Installation situation: free-standing set-up General characteristics: Material: PP Dimensions: Set-up area, length: 891 mm Set-up area, width: 406 mm Set-up area, height: 354 mm Tank: Inlet nominal size (DN): 50 mm Inlet nominal size (OD): 50 mm Outlet nominal size (DN): 50 Outlet nominal size (OD): 50 Distance pipe bottom inlet to tank bottom: 235 mm Distance pipe bottom outlet to tank bottom: 225 mm Coverage features: Locking: Clip closure Wastewater contents: Separator contents: 21 l Total volume: 33 l Contents of sludge trap: 12 l Storage quantity of grease: 8 l Max. grease layer thickness: 57 mm Dimensions and weights: Operating weight: 38
B77: TOTAL AMOUNT C/O TO SUMMARY | H77: =+SUM(H46:H76) -> 85723 | I77: =+SUM(I46:I76) -> 7976 | J77: =+SUM(J46:J76) -> 93699
B78: `
A79: 3 | B79: INTERNAL WATER SUPPLY
A81: 3.1 | B81: Supply, installation and testing of CPVC pipes and fittings SDR-11 conforming to ASTM D 2846. CPVC fusion compound shall conform tro ASTM F493. The scope of including, cutting, cleaning and fixing in/on walls under ceiling, on terrace, etc.,. The quoted rate shall include for making necessary chasing, making bores in foundation, walls, slabs, etc., and making good the chased surfaces and bores in cement mortar. Fixing of universal clamp for hanging pipeline is done at no extra cost and is included in the cost of installation of piping. (Internal and Concealed cold and hot water piping).
A82: a | B82: 15mm Dia | C82: RMT | D82: RO | E82: 144 | F82: 48 | G82: =F82+E82 -> 192 | H82: =N(E82)*N(D82) -> 0 | I82: =N(F82)*N(D82) -> 0 | J82: =N(D82)*N(G82) -> 0
A83: b | B83: 20mm Dia | C83: RMT | D83: 75 | E83: 157 | F83: 46 | G83: =F83+E83 -> 203 | H83: =N(E83)*N(D83) -> 11775 | I83: =N(F83)*N(D83) -> 3450 | J83: =N(D83)*N(G83) -> 15225
A84: c | B84: 25mm Dia | C84: RMT | D84: RO | E84: 180 | F84: 48 | G84: =F84+E84 -> 228 | H84: =N(E84)*N(D84) -> 0 | I84: =N(F84)*N(D84) -> 0 | J84: =N(D84)*N(G84) -> 0
A85: d | B85: 32mm Dia | C85: RMT | D85: RO | E85: 198 | F85: 60 | G85: =F85+E85 -> 258 | H85: =N(E85)*N(D85) -> 0 | I85: =N(F85)*N(D85) -> 0 | J85: =N(D85)*N(G85) -> 0
A86: e | B86: 40mm Dia | C86: RMT | D86: RO | E86: 216 | F86: 60 | G86: =F86+E86 -> 276 | H86: =N(E86)*N(D86) -> 0 | I86: =N(F86)*N(D86) -> 0 | J86: =N(D86)*N(G86) -> 0
A87: f | B87: 50mm Dia | C87: RMT | D87: RO | E87: 264 | F87: 60 | G87: =F87+E87 -> 324 | H87: =N(E87)*N(D87) -> 0 | I87: =N(F87)*N(D87) -> 0 | J87: =N(D87)*N(G87) -> 0
A89: 3.2 | B89: Supply, installation & commissioning of thermal insulation for hot water pipe 25 mm thick class'O' closed cellelastomeric (Nitrile rubber) insulating material with one side tubular insulation for Internal pipes as per description below and finished with polyshield
A90: a | B90: 15mm Dia | C90: RMT | D90: RO | H90: =N(E90)*N(D90) -> 0 | I90: =N(F90)*N(D90) -> 0 | J90: =N(D90)*N(G90) -> 0
A91: b | B91: 20mm Dia | C91: RMT | D91: RO | H91: =N(E91)*N(D91) -> 0 | I91: =N(F91)*N(D91) -> 0 | J91: =N(D91)*N(G91) -> 0
A92: c | B92: 25mm Dia | C92: RMT | D92: RO | H92: =N(E92)*N(D92) -> 0 | I92: =N(F92)*N(D92) -> 0 | J92: =N(D92)*N(G92) -> 0
A94: 3.3 | B94: Supply & fixing of Brass Ball Valve (PN 10)conforming to Screwed Ends as per ISO 9001 -ISO 14001 consists of a body and end connector made out of hot forged brass, a chromium plated brass ball , an anti blow out stem of brass , seat rings of PTFE(Ploytetraflouroethylene) , anti-friction stem of PTFE ,NBR(Nitro Butyl Rubber) O-Rings .complete with necessary accessories.
A95: a | B95: 20mm Dia | C95: NOS | D95: 4 | E95: 1044 | F95: 232 | G95: =F95+E95 -> 1276 | H95: =N(E95)*N(D95) -> 4176 | I95: =N(F95)*N(D95) -> 928 | J95: =N(D95)*N(G95) -> 5104
B98: TOTAL AMOUNT C/O TO SUMMARY | H98: =+SUM(H79:H97) -> 15951 | I98: =+SUM(I79:I97) -> 4378 | J98: =+SUM(J79:J97) -> 20329
B100: GRAND TOTAL - PHE | H100: =H98+H77+H44 -> 101674 | I100: =I98+I77+I44 -> 58626 | J100: =J98+J77+J44 -> 160300

Sheet TOILET WORKS
A1: SL NO | B1: ITEM DESCRIPTION | C1: REF | D1: BASIC RATE | E1: UNIT | F1: QTY | G1: RATE(INR) | H1: AMOUNT(INR) | I1: REMARKS
A3: 1 | B3: CIVIL WORKS
A5: 1.1 | B5: AAC (AUTOCLAVED AERATED CONCRETE) Block Wall
B6: Providing and constructing autoclaved 6" thick wall of 150mm X 240mm X 600mm Light Weight Block in proper line and level, at all levels in cement mortor 1:4 (1 cement and 4 river sand) using standard size of blocks. Rate shall include providing concrete binders in proportion 1:2:4, RCC binder to be at every 1mtr interval from floor level. The rate to be inclusive of cost of reinforcement and formwork, cover block for reinforcement and all other incidental charges etc., all complete and as directed. The rate shall also include closing the gap between the masonary and RCC beam/ slab finished to required slope.
A7: a | B7: 150mm Thik AAC Block Wall | C7: Washroom | E7: SQM | F7: 65 | G7: 1692 | H7: =G7*F7 -> 109980
A9: 1.2 | B9: 100mm Thick Ledge Wall - 1200mm Height | E9: SQM | F9: 16 | G9: 1499 | H9: =G9*F9 -> 23984
B10: Providing & constructing of 100mm thk siporex wall in 1:6 cement mortar. Rates to include scaffolding, curing, at all heights, constructed to true line & plumb, etc., complete as per the Architect's instructions. Note : Rate should be inclusive of Masking for fixtures & wooden frames. Wall to be built as per detail drawing .Providing cut out for services and filling up gaps around duts. (Location - Toilet cubicles + urinals ) | C10: Toilet cubicles + urinals
A12: 1.3 | B12: Cement Plastering | E12: SQM | F12: 135 | G12: 464 | H12: =G12*F12 -> 62640
B13: Proving and laying 12-15mm thick plaster in cement mortar 1:4 (1 cement : 4 coarse sand) at all levels in line, level and plumb including smooth cement finish or roughening of surface to hold tiles and providing necessary grooves at junctions of walls and ceiling, door/window frames including racking the joints, roughening the RCC surface, necessary curing, scaffolding etc. Rate shall include for the cost of brick masonry and concrete members to be plastered or clapped or other locations as called for, properly stretched and nailed ensuring equal thickness of plaster.
A15: 1.4 | B15: Self levelling | C15: Washroom | E15: SQM | F15: 0
B16: Providing and laying Self levelling screed 3-5mm thk over the Screed concrete as per the instructions of the Manufacturer .
A18: 1.5 | B18: RCC Lintel (for Doors) | E18: RMT | F18: 6 | G18: 2079 | H18: =G18*F18 -> 12474
B19: Providing and laying in place reinforced cement concrete with cement concrete of grade 1:2:4 (1 cement: 2 fine aggregates: coarse aggregates) in Lintels, beam counters, shelves etc., at all heights & width and level, including vibrating and curing. Rate shall include cost of centring and shuttering including strutting, propping etc. and removal of form for all heights. The rate shall also include for reinforcement with Fe500 grade TMT bars including straightening, cutting, bending, placing in position and binding all complete.
A21: 1.6 | B21: Waterproofing (For Floor + Walls 600 mm High) | C21: Washroom | E21: SQM | F21: 60 | G21: 1015 | H21: =G21*F21 -> 60900
B22: Providing of water proofing - chemical Treatment – the slab to be cleaned and apply 3 coats of chemical on the floor. Base coat – Applying base coat of 1:6 mortar over chemical treatment on the floor and on the peripheral walls upto 600mm.Cost of the water proofing shall include cleaning of the surface of all dirt and grit before the application. The water proofed area shall be ponded and tested for a minimum of 24 hours or as per manufacturer's specification. Note - Warranty to be provided upto 10 years
B23: * Clean surface to remove all dust, foreign matters, loose particles or any deposits of contaminants which could affect the bond between the surface and waterproof coating. * Remove all sharp projections and make surface reasonably smooth * Thoroughly pre-wet all concrete surfaces for at least one hour prior to application of coating, by ponding of water on flat surfaces and by vigorous spraying of water on vertical surfaces. * Remove all water from surfaces prior to applying of water proof coating, so that the surface is only damp or surface dry. Standing water or shiny wet surface shall not be present under any circumstances * Apply water proof coating / Brush Topping as specified for various conditions. * Apply 12mm thick cement plaster 1:4 (1cement : 4 coarse sand) after applications of final coat. * After application of final coat of Tape Crete, allow to air dry for 4-6 hours. Do not use any water for curing during this time. * In case of high temperatures and low humidity combined with high wind condition, cover the coating with polythene sheet to prevent rapid drying. * Maximum 6 hours after final application, moist cure for 24 hours by spraying water. Ensure that at no time during this 24 hour period the coating is completely dry or completely submerged in water. * After moist curing, allow to air dry for 3 days. * After air drying, complete the curing by submersion in water for 24 hours.
A25: 1.7 | B25: Pest Control and Anti-Termite Treatment | C25: Washroom | E25: SQM | F25: 75 | G25: 73 | H25: =G25*F25 -> 5475
B26: Providing & applying Pest Control & Anti-termite treatment by appointing a specialized agency. All work shall in general be executed as specified in IS : 6313 Part II-1981 & as per approved specification of the agency having special know-how for the job. All necessary work to ensure uniform distribution & proper penetration of treatment of treating solution shall be done according to the instruction of the Engineer. This includes treatment to floor area, Walls, Soil Surrounding pipes, Waste & Conduits, Expansion Joints, Junction of the Wall & the floor, Timber & Carpentry Works, Gypsum related works, etc all complete as per the instructions of architect. Pest control need to be done in 3 steps including periodic monthly fumigation and pest control at stores/site/temporary off as EHS requirement. Note: 10 year warranty to be provided on stamp paper.
B28: TOTAL FOR CIVIL WORKS | H28: =sum(H3:H27) -> 275453
A30: 2 | B30: FLOORING WORKS
A32: 2.1 | B32: Vitrified Tile Flooring (Level to Match Finished Floor Level)
B33: Providing & laying Premium vitrified tiles or stone-finish ceramic tiles with specified slip resistance. with 1st quality homogeneous tiles of approved make, of size as per details, set in average 10mm thk approved tile based adhesive or 1:4 CM upto 30mm to 40mm average thickness as per site conditions. Rate to include for laying tiles to the pattern as directed by Architect/Consultant including curing, soft cleaning chemical wash etc. Tiles to be laid with spacers (2-3mm) in-between as per architects/PM instructions. Rate to include the cutting the tiles to size if there are any variations. Cost should include house keeping & cleaning for the vitrified flooring till the handover. Joints to filled with epoxy grout of approved shade. Quoted rate to include the cost of curing, protection with polythene sheet and POP overlay till hand-over. Make: Kajaria, Nitco, Somany.
B34: Printed Tile - Type -05 (Size: 1200mm X 600mm) | C34: Washroom | D34: INR 90/SFT | E34: SQM | F34: 55 | G34: 1949 | H34: =IF(F34="QRO",0,(F34*$G34)) -> 107195 | I34: Basic Rate: Vitrified Tile - INR 60/SFT
A36: 2.2 | B36: Tile Dado / Cladding
B37: Providing & cladding of Premium vitrified tiles or stone-finish ceramic tiles with specified slip resistance. tile dadoing with 1st quality homogeneous tiles of approved make, of size as per drawings, set in average 6mm thk approved tile based adhesive or CM 1:4. Rate to include for cladding tiles to the pattern as directed by Architect / Consultant, including curing, approved chemical wash etc. Tiles to be cladded with 3mm spacers in between as per architects/PM instructions. Rate to include the cutting the tiles to size if there are any variations. Cost should include house keeping & cleaning of vitrified dadoing till the handover. Rate to include approved epoxy grouting matching to tile colour and also to include cladding of tile with necessary adhesive as per Architects /Pms instructions. Rate to include necessary corner beading / Fine edge curve 10mm corner guard profile to match the tile shade. To have necessary provision for switch cutout other necessary services cut out to be considered. Make: Kajaria, Nitco, Somany.
B38: Tile Cladding (Size: 1200mm X 600mm) | C38: Washroom | D38: INR 80/SFT | E38: SQM | F38: 132 | G38: 1934 | H38: =IF(F38="QRO",0,(F38*$G38)) -> 255288 | I38: Basic Rate: Wall tile - INR 80/SFT
A40: 2.3 | B40: BBC Raised Flooring - 300mm Height | C40: Washroom | E40: SQM | F40: 55 | G40: 1354 | H40: =IF(F40="QRO",0,(F40*$G40)) -> 74470
B41: Providing and laying of Cinder / Brick bat coba raised floor of required height ~300mm height with required pattern – Waste water lines to be encased with 1:3:6 grade concrete and applying Cinder /brick bat coba (1:6 mortar) in 2layers proper level, curing 2 days and then finishing the surface with 50 mm thk pcc flooring with cement concrete 1:2:4 (1 unit - cement, 2 units - sand, 4 units - coarse aggregates) to receive final smooth finish to proper level and slope. Rate to include necessary steps and ramp as per architects instructions. (The contractor should survey the site to ensure that the level differences are within the above limits to ensure that the rates quoted would be based on the site condition).
B43: TOTAL FOR FLOORING WORKS | H43: =sum(H30:H42) -> 436953
A46: 3 | B46: CEILING WORKS
A48: 3.1 | B48: Metal Modular perforated - Grid Ceiling - Waterproof :- | C48: Washroom | E48: SQM | F48: 50 | G48: 1886 | H48: =IF(F48="QRO",0,(F48*$G48)) -> 94300
B49: Providing and installing metal modular perforated grid ceiling system using powder-coated aluminium or galvanized steel tiles of approved make, finish, and perforation pattern, fixed into an exposed or concealed T-grid framework suspended from the slab using GI suspension system. Ceiling panels shall be moisture-resistant, corrosion-resistant, and suitable for wet or semi-wet areas. Perforated tiles shall include acoustical fleece backing or insulation layer (if specified) to improve sound absorption. System to allow for easy access to services above and include cut-outs for lighting, HVAC, sprinklers, and other ceiling-mounted equipment. All installation to be done in true line and level as per manufacturer guidelines and architect approved layout.
B51: TOTAL CEILING WORKS | H51: =H48 -> 94300
A53: 4 | B53: WALL FINISHES
A55: 4.1 | B55: Mirror Panelling | C55: Washroom | E55: SQM | F55: 6 | G55: 4352 | H55: =IF(F55="QRO",0,(F55*$G55)) -> 26112
B56: Providing and fixing mirror paneling using 6 mm thick mirror glass of approved make and finish (plain, bronze, grey, or antique), mounted over a BWP plywood or MDF backing, with decorative framework in wood, PU-coated mouldings, or metal trims as per design. Mirrors shall be machine-cut to size with polished edges and securely fixed using mirror adhesive and concealed fasteners. The framework shall be arranged in a modular grid or custom pattern, neatly mitred at joints and finished in approved color or texture. Includes surface preparation, cut-outs for electrical fittings (if any), and all alignment work to ensure a seamless, reflective feature wall. Execution to be carried out in line with architect drawings and approved mock-up.
B58: TOTAL FOR WALL FINISHES | H58: =H55 -> 26112
A61: 5 | B61: MISCELLANEOUS WORKS
A63: 5.1 | B63: TOILET CUBICLES - 1350MM(L) X 1000MM(W) | C63: Washroom | E63: NOS | F63: 9 | G63: 23692 | H63: =IF(F63="QRO",0,(F63*$G63)) -> 213228
B64: Providing and Installing of Modular toilet cubicles made out of 12mm thick compact laminate, with overall size asper detailed drawing with the door size confirming to ISO 2046 as per the detail drawings. The cost to include for the following accessories as below with all incidentals required to complete the job:
B65: a) SS Door Knob, b) SS Gravity Self Closing Type Hinges (Door Closure), c) SS Thumb Turn Occupancy Indicator, d) SS Top Rail (Inside Steel Pipe and Thread Rod), e) SS Adjustable Leg, f) SS Coat Hook, g) SS Panel Holder, h) Aluminum "U" Channel, i) Aluminum Door Stopper Channel, j) Aluminum "F" Channel, k) Door Stopper Rubber Lining, l) Screw & Wall Plugs etc.
A67: 5.2 | B67: Restroom Signages - 300mm x 100mm | E67: NOS | F67: 4 | G67: 435 | H67: =G67*F67 -> 1740
B68: Supply and fixing of door signage of size 300mm x 100mm formed of anodised aluminium plate fixed with 3M double sided tape. To have black vinyl letters pasted onto the aluminium plate. Rate to include braille as per design | C68: All Doors
A70: =A67+0.1 -> 5.3 | B70: LED Strip LIght
B71: Indoor strip light, 5Watts/Mtr, 5Mtr Reel , 24V DC, 3SDCM - PRIME WITH Surface Mount Aluminum Profile W: 16mm X H: 18mm Standard length -3 meter and 5 Nos Electronic Driver | C71: Washroom | E71: RMT | F71: 15 | G71: 435 | H71: =G71*F71 -> 6525
A73: =A70+0.1 -> 5.4 | B73: Ceiling Recessed Downlight (LED)
B74: Supply, installation, testing and commissioning of ceiling-recessed LED downlight, complete with electronic ballast/driver, housing, clamps, and accessories for proper fixing. | C74: Washroom | E74: NOS | F74: 20 | G74: 919 | H74: =G74*F74 -> 18380
A76: =A73+0.1 -> 5.5 | B76: Granite jamb & soffit for door opening - 200mm to 250mm deep | E76: RMT | F76: 38 | G76: 1305 | H76: =G76*F76 -> 49590
B77: Providing and fixing of granite jambs & soffit formed of 19mm thick & 200mm to 250mm wide pre polished granite jambs and jambs to be fixed using necessary 1:4 cement mortar or adhesive as per details. Rate to include bullnose edging as per architects instruction.
A79: =A76+0.1 -> 5.6 | B79: Granite on counters | E79: RMT | F79: 8 | G79: 9187 | H79: =G79*F79 -> 73496 | I79: above RCC Counter in wash room
B80: Providing and fixing 19mm thick pre-polished Granite counters ,or fascias laid in 19mm thick bed of cement mortar 1:4 and jointed with cement slurry with pigment to match the shade of granite including rubbing mirror polishing, bevelling of edges etc complete at all levels having 300 mm jhalar . (allowing for necessary cutouts for fixing of wash basin, pipes, waste coupling etc.if & where required)
A82: =A79+0.1 -> 5.7 | B82: Full Height Storages (800mm x 450 mm x 2100mm) | E82: NOS | F82: 0 | G82: 24500 | H82: =G82*F82 -> 0 | I82: as per Dwg
B83: Providing & fixing Full Height Laminated storage as per drawing . The overall Structure made in 18mm thick BWP board & back of storages with 6 mm thick ply . Storages finished in 1 mm thick textured laminate from everywhere except outer back side of storages and also including all SS snap hinges, handles, locks etc & all necessary hardware as required. Shutter size varies between 375-450mm wide & 450 mm deep as required with reverse bull nose edge on top & bottom of shutter (for files, folders coats etc) with select shelves duly adjustable as required on metal stud supports with sleeves set in at intervals of every 375 mm height. PVC lipping on all edges with matching shade, including laminated skirting in approved shade with all hardware, magnetic catchers, tower bolts, etc complete as per detailed drawings. (Front elevation area to be measured) All hinge, drawer channels etc to be soft closing from standard make list
A85: 5.8 | B85: Professional Deep Cleaning | E85: LS | F85: 1 | G85: 33813 | H85: =G85*F85 -> 33813
B86: Towards the cost of cleaning charges being executed by a professional house keeping agency along with all necessary materials and equipment's. This does not include the house keeping that happens on daily basis (Timeline for this work can be coordinated with PMC.). | C86: Washroom
A88: 5.9 | B88: Regular Housekeeping During Project Execution, Debris Removal | E88: LS | F88: 1 | G88: 53185 | H88: =G88*F88 -> 53185
B89: Towards the cost of cleaning charges being executed by a housekeeping personnel along with all necessary materials and equipment's. This covers the house keeping that happens on regular basis for maintaining the site hygiene. THis also includes the debris collection, removal, trasfer and disposal to designated and authorized sumping locations | C89: Washroom
B91: TOTAL FOR MISCELLANEOUS WORKS | H91: =sum(H61:H90) -> 449957
A93: 6 | B93: SANITARY FIXTURES, FAUCETS & TOILET REQUISITES
A95: 6.1 | B95: Fixing white glazed vitreous china under-counter wash basin, installed below counter slab, complete with required cut-out in counter, including chrome plated brass waste coupling, fixing brackets, sealing with silicone, connection to inlet and outlet pipes, and making good all finishes, complete as required. Includes connection to plumbing lines and alignment as per approved layout; Make: Kohler | E95: NOS | F95: 12 | G95: 1451 | H95: =G95*F95 -> 17412
A96: 6.2 | B96: Installation of rimless wall-hung WC with UF soft-close seat cover and concealed fixing system. Includes all accessories, connection to drainage system, and proper alignment; Make: Kohler | E96: NOS | F96: 9 | G96: 3385 | H96: =G96*F96 -> 30465
A97: 6.3 | B97: Installation of wall-mounted urinal complete with fixing brackets and accessories. Includes connection to water inlet and drainage system; Make: Kohler | E97: NOS | F97: 5 | G97: 2272 | H97: =G97*F97 -> 11360
A98: 6.4 | B98: Fixing of stainless steel toilet roll holder with concealed mounting arrangement. Includes all hardware, fasteners, and installation complete; Make: Kohler | E98: NOS | F98: 9 | G98: 338 | H98: =G98*F98 -> 3042
A99: 6.5 | B99: Installation of double robe hook in stainless steel finish with concealed fixing. Complete with all mounting accessories and installation; Make: Kohler | E99: NOS | F99: 1 | G99: 145 | H99: =G99*F99 -> 145
A100: 6.6 | B100: Installation of health faucet set including 8 mm dia flexible hose, handset, and wall bracket. Complete with connection to water supply and all accessories; Make: Kohler | E100: NOS | F100: 9 | G100: 338 | H100: =G100*F100 -> 3042
A101: 6.7 | B101: Installation of 32 mm click-clack waste coupling with full thread for wash basin. Includes proper sealing, fixing, and connection to waste line; Make: Kohler | E101: NOS | F101: 12 | G101: 338 | H101: =G101*F101 -> 4056
A102: 6.8 | B102: Installation of 32 mm bottle trap with internal partition in chrome finish. Includes connection to basin outlet and waste line with all fittings; Make: Kohler | E102: NOS | F102: 12 | G102: 435 | H102: =G102*F102 -> 5220
A103: 6.9 | B103: Installation of angular stop cock with wall flange in chrome finish. Includes connection to water supply line and proper fixing; Make: Kohler | E103: NOS | F103: 25 | G103: 338 | H103: =G103*F103 -> 8450
A104: 6.1 | B104: Fixing of dual flush control plate compatible with concealed cistern system. Includes installation, alignment, and testing for proper operation; Make: Kohler | E104: NOS | F104: 9 | G104: 725 | H104: =G104*F104 -> 6525
A105: 6.11 | B105: Installation of slim concealed cistern with complete internal mechanism and accessories. Includes flushing system, mounting frame, and connection to plumbing lines; Make: Kohler | E105: NOS | F105: 9 | G105: 1451 | H105: =G105*F105 -> 13059
A106: 6.12 | B106: Installation of sensor-based tall boy faucet for wash basin with IR sensor technology. Includes power supply, control unit, and all connections; Make: Kohler | E106: NOS | F106: 12 | G106: 1451 | H106: =G106*F106 -> 17412
... A117: 6.24 | B117: Fixing of 15 mm dia, 450 mm long flexible connection pipe having EPDM rubber internal core and stainless steel braided outer sheath complete with C.P brass end nuts, of approved make. Make :Kohler | E117: NOS | F117: 14 | G117: 145 | H117: =G117*F117 -> 2030
A118: 6.25 | B118: Fixing electric water storage heater (geyser) of following capacities including making inlet / outlet connections, of approved makes. Make:Kohler
A119: a | B119: Capacity : 25 litre | E119: NOS | F119: 2 | G119: 2418 | H119: =G119*F119 -> 4836
A120: b | B120: Capacity : 50 litre | E120: NOS | F120: 0 | G120: 4000 | H120: =G120*F120 -> 0
A121: 6.26 | B121: Installation of WALL MOUNTED BASIN WITH FIXING ACCESSORIES - Handicap Washroom Make :Kohler | E121: NOS | F121: 1 | G121: 1692 | H121: =G121*F121 -> 1692
A122: 6.27 | B122: Fixing and commissioning of sanitary pad disposal bin for female washroom, wall-mounted unit made of durable material, suitable for hygienic disposal, including fixing arrangements, cutting and making good of walls, complete with all necessary fittings and accessories, installed as per manufacturer’s specifications and standards. Make: Kohler | E122: NOS | F122: 1 | G122: 725 | H122: =G122*F122 -> 725
A123: 6.28 | B123: Fixing and commissioning of stainless steel grab rails for handicapped toilet, fabricated from high-quality stainless steel with smooth finish for durability and safety, including cutting, drilling and making good of walls, complete with all necessary fixing accessories, ensuring firm support and stability, installed as per manufacturer’s specifications and standards. Make: Kohler
A124: a | B124: for handicapped toilets - Fixed Type | E124: NOS | F124: 1 | G124: 870 | H124: =G124*F124 -> 870
A125: b | B125: for Handicapped toilets - foldable type | E125: NOS | F125: 1 | G125: 1451 | H125: =G125*F125 -> 1451
A127: 6.29 | B127: Installation of Floor Trap (FT) - cast-iron / SS body, 100 mm dia, with grating SS 304 grating, 100 mm dia, for toilet floor drainage Trap depth 50 mm, removable for cleaning | E127: NOS | F127: 15 | G127: 242 | H127: =G127*F127 -> 3630
A128: 6.32 | B128: Installation of Nahani Trap - cast-iron, 75 mm, with seal | E128: NOS | F128: 15 | G128: 290 | H128: =G128*F128 -> 4350
A129: 6.33 | B129: Installation of Gully Trap (GT) - with screwed cover, for external drainage | E129: NOS | F129: 2 | G129: 677 | H129: =G129*F129 -> 1354
A131: 6.34 | B131: Common backend / enabling works (per washroom) - Waterproofing with upstand + contained wet tray; IPS wall sub-structure with demountable access panel (no tile over mounting zones); service/unistrut rail for accessories; isolation manifold; concealed soil/supply with capped stubs; concealed power + data + RCD backbone; datum set-out and validation against shortlisted models; commissioning, pressure-test, dummy-swap validation; handover swap SOP + isolation map. | E131: Nos | F131: 2 | G131: 241750 | H131: =G131*F131 -> 483500
A132: 6.35 | B132: WC test position Heavy-duty concealed carrier frame + cistern rated for repeated cycling; fixed mounting datum (standard stud centres); isolation valve + braided supply tail + telescopic pan-to-soil connector; capped floor soil/supply stub (floor-mount option); RCD socket + water feed + data point (smart/washlet ready); adaptor-plate provision (blank + machining allowance); demountable IPS panel section. Pan, seat, premium actuator excluded. | E132: Nos | F132: 2 | G132: 106370 | H132: =G132*F132 -> 212740
A133: 6.36 | B133: Urinal test position Urinal carrier frame with adjustable supply + waste; isolation valve + flexible supply tail; flexible waste connector for back-outlet and bottom-outlet models; LV/power + data provision for sensor flush; waterless-ready supply cap; demountable IPS panel section. Urinal bowl and shipped sensor unit excluded. Male washrooms only. | E133: Nos | F133: 1 | G133: 72525 | H133: =G133*F133 -> 72525
A134: 6.37 | B134: Washbasin test position Vanity counter with fixed concealed waste/supply void + interchangeable insert panels / adaptor collars for varying footprints (or wall-hung basin carrier frame as alternate); isolation valves + braided tap hoses + accessible bottle trap; power + data provision for sensor tap; demountable service access. Basin, tapware and sensor unit excluded. | E134: Nos | F134: 2 | G134: 77360 | H134: =G134*F134 -> 154720
A136: 7 | B136: SOIL WASTE AND VENT PIPING
A138: 7.1 | B138: Soil / Waste Pipes - UPVC SWR (per Rmt, INCLUSIVE of fittings + supports)
A139: a | B139: UPVC SWR Pipe - 110 mm (4") - Soil + Vent stack Astral / Supreme / Prince / Finolex per IS 13592 Type B Includes: elbows / tees / reducers / cleanout / cap fittings Includes: GI brackets / clamps / supports per IS 5572 | E139: RMT | F139: 80 | G139: 575 | H139: =G139*F139 -> 46000
A140: b | B140: UPVC SWR Pipe - 75 mm (3") - Waste branch / urinal stack Same family (Astral / Supreme / Prince) Inclusive of fittings + supports (Waste branches) | E140: RMT | F140: 60 | G140: 424 | H140: =G140*F140 -> 25440
A141: c | B141: UPVC SWR Pipe - 50 mm (2") - Floor drain branches / basin / shower waste | E141: RMT | F141: 80 | G141: 322 | H141: =G141*F141 -> 25760
A142: d | B142: UPVC SWR Pipe - 40 mm (1.5") - Basin trap / lavatory waste | E142: RMT | F142: 60 | G142: 264 | H142: =G142*F142 -> 15840
A144: 7.2 | B144: Vent Pipes - UPVC SWR
A145: a | B145: UPVC SWR Vent Pipe - 75 mm (3") - branch vent | E145: RMT | F145: 40 | G145: 390 | H145: =G145*F145 -> 15600
A146: b | B146: UPVC SWR Vent Pipe - 50 mm (2") - branch vent | E146: RMT | F146: 30 | G146: 305 | H146: =G146*F146 -> 9150
A147: c | B147: Vent Cowl - GI / SS, with bird-screen, terrace termination | E147: NOS | F147: 4 | G147: 1252 | H147: =G147*F147 -> 5008
A149: 7.3 | B149: Cleanouts / Inspection Chambers
A150: a | B150: Cleanout (CO) Plug - brass / bronze, threaded, at base of stacks + branches | E150: NOS | F150: 12 | G150: 1209 | H150: =G150*F150 -> 14508
A151: b | B151: Floor-mounted Inspection Chamber (FRP / SS, sized 200 x 200 / 300 x 300 mm) | E151: NOS | F151: 6 | G151: 6286 | H151: =G151*F151 -> 37716
...

Sheet MAKE LIST
A1: PROPOSED MAKES
A3: SR. NO. | B3: MATERIAL | C3: MAKE
A5: A | B5: INTERIOR, CIVIL & ALLIED WORKS
A7: 1 | B7: ANTI TERMITE COMPOUND | C7: PCI
A8: 2 | B8: ACC BLOCKS | C8: AEROCON
A9: 3 | B9: WATER PROOFING COMPUND | C9: PIDILITE
A10: 4 | B10: CEMENT | C10: ACC/Ultratech
A11: 5 | B11: TMT BARS | C11: Tata/Jindal
A12: 6 | B12: SELF LEVELLING | C12: Fosroc, pidilite, Ardex
A13: 7 | B13: CERAMIC/ VITRIFIED TILES | C13: KAJARIA/RAK/SOMANY
A14: 8 | B14: SANITORY WARE | C14: Kolher
A15: 9 | B15: CP FITTING/FIXTURES | C15: Kolher
A16: 10 | B16: DRY WALL PARTITION/CEILING | C16: Saint Gobian, USG Knauf
A17: 11 | B17: MODULAR CEILING | C17: ARMSTRONG/Knauf
A18: 12 | B18: BAFFEL / METAL CEILING/DESIGNER CEILING | C18: ARMSTRONG/Knauf
... A42: 36 | B42: RAISED FLOORING TILES | C42: Unitile/ AET
A44: B | B44: CARPET/MODULARS/CHAIRS
A45: 1 | B45: MODULAR FURNITURE | C45: AFC, Featherlite, Spacwood, Monarch
A46: 2 | B46: CHAIRS | C46: AFC, Featherlite, Aster, Spacewood, Monarch
A47: 3 | B47: BOARDROOM CHAIRS | C47: AFC, Featherlite, Aster, Spacewood, Monarch
A48: 3 | B48: LOOSE FURNITURE | C48: Amardeep, Multiseats, Spacewood, Albans
A49: 4 | B49: Carpet tiles make: | C49: Interface, Welspun, Mohawk, Tuntex
A51: C | B51: HVAC & ALLIED WORKS
A53: 1 | B53: HIGH SIDE MATERIAL | C53: Daikin/Mistubishi/Toshiba/ Samsung
A54: 2 | B54: COPPER PIPES AND FITTINGS | C54: MEXFLOW/MANDEDV/TOTALLINE
A55: 3 | B55: INLINE FAN | C55: KRUGER/SYSTEMAIR
A56: 4 | B56: DUCTS | C56: ZECO/VEDHA/Ductofab
A57: 5 | B57: FLEXIBLE DUCTS (INSULATED AND NON-INSULATED) | C57: UP-TWIGA/SEVENSTAR
A58: 6 | B58: AIR TERMINALS (SWIRL DIFFUSERS, GRILLS, DISC VALVES, NOZZLES, LOUVERS, NON-VISION DOOR GRILLS, COLLAR DAMPERS, HIT AND MISS DAMPERS, NRDS, VCDS, MVCDS, SOUND ATTENUATORS, CROSS TALK SILENCERS,SLOT DIFFUSER, BUTTERFLY DAMPERS) | C58: AIRMASTER/SYSTEMAIR/COSMIC/CARYAIRE
A59: 7 | B59: COMMUNICATION CABLES | C59: POLYCAB
A60: 8 | B60: NITRILE RUBBER | C60: K-FLEX/ARM FLEX
A61: 9 | B61: THREADED ROD & SOLLOTED CHANNEL | C61: MOONSHINE
A62: 10 | B62: DRAIN PUMP | C62: WIPCOOL/ASPEN
A63: 11 | B63: DRAIN PIPE | C63: VECTUS/ASTRAL
A65: D | B65: ELECTRICAL & ALLIED WORKS
B67: CABLES & ACCESSORIES
A68: 1 | B68: CABLES | C68: POLYCAB/Havells
A69: 2 | B69: CABLE LUGS/GLANDS | C69: DOWELS/HMI
A70: 3 | B70: CABLE TRAYS | C70: Customized
B72: WIRES & ACCESSORIES
A73: 1 | B73: SINGLE CORE WIRES | C73: POLYCAB/Havells/Finolex (HRFR)
A74: 2 | B74: THREE CORE FLEXIBLE WIRES (BLACK & WHITE) | C74: POLYCAB/Havells/Finolex (HRFR)
A75: 3 | B75: CONDUIT PIPES & FITTINGS (PVC) | C75: Customized / Reputed Make as available
A76: 3 | B76: CONDUIT PIPES & FITTINGS (MS) | C76: Customized / Reputed Make as available
A77: 4 | B77: SWITCHES/SOCKETS | C77: LEGRAND/Havells/Schneider/GM
A78: 5 | B78: METAL CLAD SOCKETS/IEC TYPE PLUG-SOCKETS | C78: NEPTUNE BALLS
B80: LIGHT FITINGS/FIXTURES
A81: 1 | B81: LED FITTINGS | C81: PHILIPS/Havells/Wipro
A82: 2 | B82: LED SPOT LIGHTS | C82: PHILIPS/Havells/Wipro
A83: 3 | B83: DECORATIVE LIGHTS | C83: CUSTOM MADE WITH PHILIPS / HAVELLS FITTINGS
B85: DB & MCB
A86: 1 | B86: MCCB, MCB, DB, RCBO, ELCB | C86: ABB/LEGRAND/SCHNEIDER
A87: 2 | B87: LT PANELS | C87: CPRI APPROVED
A89: E | B89: Fire Security
B91: FAS
A92: 1 | B92: CONVENTIONAL FIRE ALARM SYSTEM | C92: HONEYWELL (NOTIFIER)/RAVEL/Siemens
A93: 2 | B93: SMOKE DETECTORS | C93: HONEYWELL (NOTIFIER)/RAVEL/Siemens
A94: 3 | B94: RESPONSE INDICATORS | C94: HONEYWELL (NOTIFIER)/RAVEL/Siemens
A95: 4 | B95: HOOTERS | C95: HONEYWELL (NOTIFIER)/RAVEL/Siemens
A96: 5 | B96: MANUALL CALL PINTS | C96: HONEYWELL (NOTIFIER)/RAVEL/Siemens
A97: 6 | B97: CABLES | C97: POLYCAB/RR Kabel
B99: SprInkler/Drenching System
A100: 1 | B100: Mild Steel Pipes/ G.I. Pipes conforming to IS:1239 | C100: Tata/Jindal(Hissar)
A101: 2 | B101: Mild Steel Pipes conforming to IS:3589 | C101: Tata/Jindal(Hissar)
A102: 3 | B102: Standard M.S. Fittings | C102: VS Engineering/True Forge/Sant
A103: 4 | B103: Forged Steel Fittings | C103: VS Engineering/True Forge/JK Forging
A104: 5 | B104: Ball Valves | C104: ARCO, Spain/CIM, Italy/Tieamy, Italy.
A105: 6 | B105: Butterfly Valves | C105: Audco/Advance/Danfoss.
A106: 7 | B106: Gunmetal Non-return Valves | C106: Leader/Zoloto
A107: 8 | B107: Air Release Valves | C107: Zoloto/CIM, Italy/RBM, Italy.
A108: 9 | B108: Gunmetal Landing Valve, Branch Pipe Nozzle, Fireman Axe, Fire Brigade Connection, Male-Female Couplings etc. (ISI Marked) | C108: Minimax/Newage.
A109: 10 | B109: Quartozoid Bulb type Sprinkler Heads ( UL and FM Approved) | C109: Tyco/Viking.
